[
  {
    "id": "acaa99e66d47b98c",
    "code": "202604153706386911",
    "title": "美媒：美国与伊朗考虑将停火延长两周",
    "summary": "据美国彭博新闻社15日报道，美国与伊朗考虑将停火延长两周。",
    "content": "据美国彭博新闻社15日报道，美国与伊朗考虑将停火延长两周。",
    "full_content": "据美国彭博新闻社15日报道，美国与伊朗考虑将停火延长两周。",
    "sort_time": "1776267434086911",
    "showTime": "2026-04-15 23:37:14",
    "time": "2026-04-15 23:37:14",
    "publish_time": "2026-04-15 23:37:14",
    "raw_data": {
      "code": "202604153706386911",
      "image": [],
      "pinglun_Num": 49,
      "realSort": "1776267434086911",
      "share": 148,
      "showTime": "2026-04-15 23:37:14",
      "stockList": [],
      "summary": "据美国彭博新闻社15日报道，美国与伊朗考虑将停火延长两周。",
      "title": "美媒：美国与伊朗考虑将停火延长两周",
      "titleColor": 3
    },
    "source": "东方财富快讯",
    "url": "https://kuaixun.eastmoney.com/news/202604153706386911.html",
    "category": "其他",
    "importance": 5,
    "sentiment": "neutral",
    "related_stocks": [],
    "has_stock_mention": false,
    "comment_count": 49,
    "share_count": 148,
    "tags": {
      "industries": [],
      "concepts": [],
      "industry_ids": [],
      "concept_ids": []
    }
  },
  {
    "id": "0d6953318a7d7318",
    "code": "202604153706384174",
    "title": "美国柴油期货价格上涨5%",
    "summary": "美国柴油期货价格上涨5%，原因是美国上周馏分油库存的下降幅度超出预期。",
    "content": "美国柴油期货价格上涨5%，原因是美国上周馏分油库存的下降幅度超出预期。",
    "full_content": "美国柴油期货价格上涨5%，原因是美国上周馏分油库存的下降幅度超出预期。",
    "sort_time": "1776267075084174",
    "showTime": "2026-04-15 23:31:15",
    "time": "2026-04-15 23:31:15",
    "publish_time": "2026-04-15 23:31:15",
    "raw_data": {
      "code": "202604153706384174",
      "image": [],
      "pinglun_Num": 1,
      "realSort": "1776267075084174",
      "share": 0,
      "showTime": "2026-04-15 23:31:15",
      "stockList": [
        "90.BK1361"
      ],
      "summary": "美国柴油期货价格上涨5%，原因是美国上周馏分油库存的下降幅度超出预期。",
      "title": "美国柴油期货价格上涨5%",
      "titleColor": 0
    },
    "source": "东方财富快讯",
    "url": "https://kuaixun.eastmoney.com/news/202604153706384174.html",
    "category": "期货",
    "importance": 6,
    "sentiment": "bullish",
    "related_stocks": [
      "90.BK1361"
    ],
    "has_stock_mention": true,
    "comment_count": 1,
    "share_count": 0,
    "tags": {
      "industries": [],
      "concepts": [],
      "industry_ids": [],
      "concept_ids": []
    }
  },
  {
    "id": "616d2ed9323b5729",
    "code": "202604153706377421",
    "title": "美军称“没有任何船只成功通过美军防线”",
    "summary": "【美军称“没有任何船只成功通过美军防线”】美军中央司令部15日发表声明称，在美国开始对进出伊朗港口的船只实施封锁后的48小时内，“没有任何船只成功通过美军防线”。此外，有9艘船只遵从美军指令，掉头返回伊朗港口或沿海区域。",
    "content": "【美军称“没有任何船只成功通过美军防线”】美军中央司令部15日发表声明称，在美国开始对进出伊朗港口的船只实施封锁后的48小时内，“没有任何船只成功通过美军防线”。此外，有9艘船只遵从美军指令，掉头返回伊朗港口或沿海区域。",
    "full_content": "【美军称“没有任何船只成功通过美军防线”】美军中央司令部15日发表声明称，在美国开始对进出伊朗港口的船只实施封锁后的48小时内，“没有任何船只成功通过美军防线”。此外，有9艘船只遵从美军指令，掉头返回伊朗港口或沿海区域。",
    "sort_time": "1776266777077421",
    "showTime": "2026-04-15 23:26:17",
    "time": "2026-04-15 23:26:17",
    "publish_time": "2026-04-15 23:26:17",
    "raw_data": {
      "code": "202604153706377421",
      "image": [],
      "pinglun_Num": 10,
      "realSort": "1776266777077421",
      "share": 2,
      "showTime": "2026-04-15 23:26:17",
      "stockList": [],
      "summary": "【美军称“没有任何船只成功通过美军防线”】美军中央司令部15日发表声明称，在美国开始对进出伊朗港口的船只实施封锁后的48小时内，“没有任何船只成功通过美军防线”。此外，有9艘船只遵从美军指令，掉头返回伊朗港口或沿海区域。",
      "title": "美军称“没有任何船只成功通过美军防线”",
      "titleColor": 0
    },
    "source": "东方财富快讯",
    "url": "https://kuaixun.eastmoney.com/news/202604153706377421.html",
    "category": "其他",
    "importance": 5,
    "sentiment": "neutral",
    "related_stocks": [],
    "has_stock_mention": false,
    "comment_count": 10,
    "share_count": 2,
    "tags": {
      "industries": [],
      "concepts": [],
      "industry_ids": [],
      "concept_ids": []
    }
  },
  {
    "id": "b1cede59eab63154",
    "code": "202604153706372016",
    "title": "美股持续攀升 纳斯达克综合指数涨1%",
    "summary": "【美股持续攀升 纳斯达克综合指数涨1%】美股持续攀升，道琼斯指数跌0.33%，标普500指数涨0.44%，纳斯达克综合指数涨1%。",
    "content": "【美股持续攀升 纳斯达克综合指数涨1%】美股持续攀升，道琼斯指数跌0.33%，标普500指数涨0.44%，纳斯达克综合指数涨1%。",
    "full_content": "【美股持续攀升 纳斯达克综合指数涨1%】美股持续攀升，道琼斯指数跌0.33%，标普500指数涨0.44%，纳斯达克综合指数涨1%。",
    "sort_time": "1776266313072016",
    "showTime": "2026-04-15 23:18:33",
    "time": "2026-04-15 23:18:33",
    "publish_time": "2026-04-15 23:18:33",
    "raw_data": {
      "code": "202604153706372016",
      "image": [],
      "pinglun_Num": 5,
      "realSort": "1776266313072016",
      "share": 5,
      "showTime": "2026-04-15 23:18:33",
      "stockList": [],
      "summary": "【美股持续攀升 纳斯达克综合指数涨1%】美股持续攀升，道琼斯指数跌0.33%，标普500指数涨0.44%，纳斯达克综合指数涨1%。",
      "title": "美股持续攀升 纳斯达克综合指数涨1%",
      "titleColor": 0
    },
    "source": "东方财富快讯",
    "url": "https://kuaixun.eastmoney.com/news/202604153706372016.html",
    "category": "其他",
    "importance": 5,
    "sentiment": "neutral",
    "related_stocks": [],
    "has_stock_mention": false,
    "comment_count": 5,
    "share_count": 5,
    "tags": {
      "industries": [],
      "concepts": [],
      "industry_ids": [],
      "concept_ids": []
    }
  },
  {
    "id": "201db0a6844945b2",
    "code": "202604153706371274",
    "title": "微软股价涨近4% 大幅上调Surface全系售价",
    "summary": "【微软股价涨近4% 大幅上调Surface全系售价】微软(MSFT.US)股价周三涨近4%，报407.650美元/股，总市值报3.03万亿美元。消息面上，4月14日，微软全面上调其美国官网SurfaceLaptop和SurfacePro的价格。其中，旗舰型号SurfacePro11及SurfaceLaptop7的入门价格由999美元涨至1499美元，涨幅高达50%。本次加价涵盖Surface全产品线，即时生效，其他零售商预料亦会跟随调整。",
    "content": "【微软股价涨近4% 大幅上调Surface全系售价】微软(MSFT.US)股价周三涨近4%，报407.650美元/股，总市值报3.03万亿美元。消息面上，4月14日，微软全面上调其美国官网SurfaceLaptop和SurfacePro的价格。其中，旗舰型号SurfacePro11及SurfaceLaptop7的入门价格由999美元涨至1499美元，涨幅高达50%。本次加价涵盖Surface全产品线，即时生效，其他零售商预料亦会跟随调整。",
    "full_content": "【微软股价涨近4% 大幅上调Surface全系售价】微软(MSFT.US)股价周三涨近4%，报407.650美元/股，总市值报3.03万亿美元。消息面上，4月14日，微软全面上调其美国官网SurfaceLaptop和SurfacePro的价格。其中，旗舰型号SurfacePro11及SurfaceLaptop7的入门价格由999美元涨至1499美元，涨幅高达50%。本次加价涵盖Surface全产品线，即时生效，其他零售商预料亦会跟随调整。",
    "sort_time": "1776266221071274",
    "showTime": "2026-04-15 23:17:01",
    "time": "2026-04-15 23:17:01",
    "publish_time": "2026-04-15 23:17:01",
    "raw_data": {
      "code": "202604153706371274",
      "image": [],
      "pinglun_Num": 3,
      "realSort": "1776266221071274",
      "share": 4,
      "showTime": "2026-04-15 23:17:01",
      "stockList": [
        "105.MSFT"
      ],
      "summary": "【微软股价涨近4% 大幅上调Surface全系售价】微软(MSFT.US)股价周三涨近4%，报407.650美元/股，总市值报3.03万亿美元。消息面上，4月14日，微软全面上调其美国官网SurfaceLaptop和SurfacePro的价格。其中，旗舰型号SurfacePro11及SurfaceLaptop7的入门价格由999美元涨至1499美元，涨幅高达50%。本次加价涵盖Surface全产品线，即时生效，其他零售商预料亦会跟随调整。",
      "title": "微软股价涨近4% 大幅上调Surface全系售价",
      "titleColor": 0
    },
    "source": "东方财富快讯",
    "url": "https://kuaixun.eastmoney.com/news/202604153706371274.html",
    "category": "其他",
    "importance": 6,
    "sentiment": "neutral",
    "related_stocks": [
      "105.MSFT"
    ],
    "has_stock_mention": true,
    "comment_count": 3,
    "share_count": 4,
    "tags": {
      "industries": [],
      "concepts": [
        {
          "id": "C605",
          "name": "零售",
          "matched_keyword": "零售"
        }
      ],
      "industry_ids": [],
      "concept_ids": [
        "C605"
      ]
    }
  },
  {
    "id": "e19efee81c9e33e3",
    "code": "202604153706370371",
    "title": "以军总参谋长：已批准针对伊朗和黎巴嫩的新作战计划",
    "summary": "【以军总参谋长：已批准针对伊朗和黎巴嫩的新作战计划】当地时间15日，以色列国防军总参谋长埃亚尔·扎米尔中将在黎巴嫩南部前线表示，他已批准针对黎巴嫩和伊朗的新作战计划。",
    "content": "【以军总参谋长：已批准针对伊朗和黎巴嫩的新作战计划】当地时间15日，以色列国防军总参谋长埃亚尔·扎米尔中将在黎巴嫩南部前线表示，他已批准针对黎巴嫩和伊朗的新作战计划。",
    "full_content": "【以军总参谋长：已批准针对伊朗和黎巴嫩的新作战计划】当地时间15日，以色列国防军总参谋长埃亚尔·扎米尔中将在黎巴嫩南部前线表示，他已批准针对黎巴嫩和伊朗的新作战计划。",
    "sort_time": "1776266165070371",
    "showTime": "2026-04-15 23:16:05",
    "time": "2026-04-15 23:16:05",
    "publish_time": "2026-04-15 23:16:05",
    "raw_data": {
      "code": "202604153706370371",
      "image": [],
      "pinglun_Num": 35,
      "realSort": "1776266165070371",
      "share": 34,
      "showTime": "2026-04-15 23:16:05",
      "stockList": [],
      "summary": "【以军总参谋长：已批准针对伊朗和黎巴嫩的新作战计划】当地时间15日，以色列国防军总参谋长埃亚尔·扎米尔中将在黎巴嫩南部前线表示，他已批准针对黎巴嫩和伊朗的新作战计划。",
      "title": "以军总参谋长：已批准针对伊朗和黎巴嫩的新作战计划",
      "titleColor": 3
    },
    "source": "东方财富快讯",
    "url": "https://kuaixun.eastmoney.com/news/202604153706370371.html",
    "category": "其他",
    "importance": 5,
    "sentiment": "neutral",
    "related_stocks": [],
    "has_stock_mention": false,
    "comment_count": 35,
    "share_count": 34,
    "tags": {
      "industries": [],
      "concepts": [
        {
          "id": "C201",
          "name": "军工",
          "matched_keyword": "国防"
        }
      ],
      "industry_ids": [],
      "concept_ids": [
        "C201"
      ]
    }
  },
  {
    "id": "a9405b48b44c60f4",
    "code": "202604153706368237",
    "title": "王毅同伊朗外长阿拉格齐通电话",
    "summary": "【王毅同伊朗外长阿拉格齐通电话】中共中央政治局委员、外交部长王毅15日同伊朗外长阿拉格齐通电话。阿拉格齐通报了伊美谈判最新情况及伊方下步考虑，表示伊方愿通过和平谈判方式，继续寻求理性、现实的解决方案。伊方高度赞赏中方一直以来为推动局势缓和降温所作努力，期待中方为促和止战发挥积极作用。",
    "content": "【王毅同伊朗外长阿拉格齐通电话】中共中央政治局委员、外交部长王毅15日同伊朗外长阿拉格齐通电话。阿拉格齐通报了伊美谈判最新情况及伊方下步考虑，表示伊方愿通过和平谈判方式，继续寻求理性、现实的解决方案。伊方高度赞赏中方一直以来为推动局势缓和降温所作努力，期待中方为促和止战发挥积极作用。",
    "full_content": "【王毅同伊朗外长阿拉格齐通电话】中共中央政治局委员、外交部长王毅15日同伊朗外长阿拉格齐通电话。阿拉格齐通报了伊美谈判最新情况及伊方下步考虑，表示伊方愿通过和平谈判方式，继续寻求理性、现实的解决方案。伊方高度赞赏中方一直以来为推动局势缓和降温所作努力，期待中方为促和止战发挥积极作用。",
    "sort_time": "1776265975068237",
    "showTime": "2026-04-15 23:12:55",
    "time": "2026-04-15 23:12:55",
    "publish_time": "2026-04-15 23:12:55",
    "raw_data": {
      "code": "202604153706368237",
      "image": [],
      "pinglun_Num": 2,
      "realSort": "1776265975068237",
      "share": 13,
      "showTime": "2026-04-15 23:12:55",
      "stockList": [],
      "summary": "【王毅同伊朗外长阿拉格齐通电话】中共中央政治局委员、外交部长王毅15日同伊朗外长阿拉格齐通电话。阿拉格齐通报了伊美谈判最新情况及伊方下步考虑，表示伊方愿通过和平谈判方式，继续寻求理性、现实的解决方案。伊方高度赞赏中方一直以来为推动局势缓和降温所作努力，期待中方为促和止战发挥积极作用。",
      "title": "王毅同伊朗外长阿拉格齐通电话",
      "titleColor": 3
    },
    "source": "东方财富快讯",
    "url": "https://kuaixun.eastmoney.com/news/202604153706368237.html",
    "category": "其他",
    "importance": 5,
    "sentiment": "neutral",
    "related_stocks": [],
    "has_stock_mention": false,
    "comment_count": 2,
    "share_count": 13,
    "tags": {
      "industries": [],
      "concepts": [],
      "industry_ids": [],
      "concept_ids": []
    }
  },
  {
    "id": "0f1f43e84a0360ec",
    "code": "202604153706363754",
    "title": "特斯拉股价涨5% AI5芯片成功流片",
    "summary": "【特斯拉股价涨5% AI5芯片成功流片】特斯拉股价上涨5%，报382.5美元/股。消息面上，特斯拉首席执行官埃隆·马斯克宣布，特斯拉AI芯片设计团队已成功完成AI5芯片的流片。这标志着该芯片迈向制造阶段的重要里程碑。",
    "content": "【特斯拉股价涨5% AI5芯片成功流片】特斯拉股价上涨5%，报382.5美元/股。消息面上，特斯拉首席执行官埃隆·马斯克宣布，特斯拉AI芯片设计团队已成功完成AI5芯片的流片。这标志着该芯片迈向制造阶段的重要里程碑。",
    "full_content": "【特斯拉股价涨5% AI5芯片成功流片】特斯拉股价上涨5%，报382.5美元/股。消息面上，特斯拉首席执行官埃隆·马斯克宣布，特斯拉AI芯片设计团队已成功完成AI5芯片的流片。这标志着该芯片迈向制造阶段的重要里程碑。",
    "sort_time": "1776265476063754",
    "showTime": "2026-04-15 23:04:36",
    "time": "2026-04-15 23:04:36",
    "publish_time": "2026-04-15 23:04:36",
    "raw_data": {
      "code": "202604153706363754",
      "image": [],
      "pinglun_Num": 10,
      "realSort": "1776265476063754",
      "share": 44,
      "showTime": "2026-04-15 23:04:36",
      "stockList": [
        "90.BK0644",
        "90.BK0800"
      ],
      "summary": "【特斯拉股价涨5% AI5芯片成功流片】特斯拉股价上涨5%，报382.5美元/股。消息面上，特斯拉首席执行官埃隆·马斯克宣布，特斯拉AI芯片设计团队已成功完成AI5芯片的流片。这标志着该芯片迈向制造阶段的重要里程碑。",
      "title": "特斯拉股价涨5% AI5芯片成功流片",
      "titleColor": 0
    },
    "source": "东方财富快讯",
    "url": "https://kuaixun.eastmoney.com/news/202604153706363754.html",
    "category": "科技",
    "importance": 6,
    "sentiment": "bullish",
    "related_stocks": [
      "90.BK0644",
      "90.BK0800"
    ],
    "has_stock_mention": true,
    "comment_count": 10,
    "share_count": 44,
    "tags": {
      "industries": [
        {
          "id": "I010101",
          "name": "半导体",
          "level1": "制造业",
          "level2": "计算机、通信和其他电子设备制造业",
          "matched_keyword": "芯片"
        }
      ],
      "concepts": [
        {
          "id": "C001",
          "name": "人工智能",
          "matched_keyword": "AI"
        },
        {
          "id": "C002",
          "name": "芯片",
          "matched_keyword": "芯片"
        },
        {
          "id": "C805",
          "name": "特斯拉",
          "matched_keyword": "特斯拉"
        }
      ],
      "industry_ids": [
        "I010101"
      ],
      "concept_ids": [
        "C001",
        "C002",
        "C805"
      ]
    }
  },
  {
    "id": "6936028596a20e71",
    "code": "202604153706360353",
    "title": "部分期货品种夜盘收盘 多数商品上涨",
    "summary": "【部分期货品种夜盘收盘 多数商品上涨】部分期货品种夜盘收盘，多数商品上涨，PTA涨超2%，铁矿石涨1.7%，沥青涨1.5%，纯碱涨1.3%，LPG涨1.25%。尚无品种跌幅超过1%。",
    "content": "【部分期货品种夜盘收盘 多数商品上涨】部分期货品种夜盘收盘，多数商品上涨，PTA涨超2%，铁矿石涨1.7%，沥青涨1.5%，纯碱涨1.3%，LPG涨1.25%。尚无品种跌幅超过1%。",
    "full_content": "【部分期货品种夜盘收盘 多数商品上涨】部分期货品种夜盘收盘，多数商品上涨，PTA涨超2%，铁矿石涨1.7%，沥青涨1.5%，纯碱涨1.3%，LPG涨1.25%。尚无品种跌幅超过1%。",
    "sort_time": "1776265229060353",
    "showTime": "2026-04-15 23:00:29",
    "time": "2026-04-15 23:00:29",
    "publish_time": "2026-04-15 23:00:29",
    "raw_data": {
      "code": "202604153706360353",
      "image": [],
      "pinglun_Num": 1,
      "realSort": "1776265229060353",
      "share": 0,
      "showTime": "2026-04-15 23:00:29",
      "stockList": [
        "90.BK1361"
      ],
      "summary": "【部分期货品种夜盘收盘 多数商品上涨】部分期货品种夜盘收盘，多数商品上涨，PTA涨超2%，铁矿石涨1.7%，沥青涨1.5%，纯碱涨1.3%，LPG涨1.25%。尚无品种跌幅超过1%。",
      "title": "部分期货品种夜盘收盘 多数商品上涨",
      "titleColor": 0
    },
    "source": "东方财富快讯",
    "url": "https://kuaixun.eastmoney.com/news/202604153706360353.html",
    "category": "期货",
    "importance": 6,
    "sentiment": "bullish",
    "related_stocks": [
      "90.BK1361"
    ],
    "has_stock_mention": true,
    "comment_count": 1,
    "share_count": 0,
    "tags": {
      "industries": [],
      "concepts": [],
      "industry_ids": [],
      "concept_ids": []
    }
  },
  {
    "id": "4adf5c1869a24d21",
    "code": "202604153706356138",
    "title": "盘后A股上市公司重点业绩公告精选",
    "summary": "【盘后A股上市公司重点业绩公告精选】据财联社不完全统计，截至发稿，盘后包括宁德时代、蓝思科技、佰维存储、中金公司、中国巨石、鼎泰高科、鼎通科技、金海通、龙蟠科技、宁波富邦、海正药业、南网储能、正泰电器、舍得酒业在内的多家A股上市公司发布2026年一季度业绩预告/报告。其中，宁德时代公告，一季度净利润同比增长49%。吉比特、申通快递昨日盘后发布一季度业绩预告，今日均收盘涨停。",
    "content": "【盘后A股上市公司重点业绩公告精选】据财联社不完全统计，截至发稿，盘后包括宁德时代、蓝思科技、佰维存储、中金公司、中国巨石、鼎泰高科、鼎通科技、金海通、龙蟠科技、宁波富邦、海正药业、南网储能、正泰电器、舍得酒业在内的多家A股上市公司发布2026年一季度业绩预告/报告。其中，宁德时代公告，一季度净利润同比增长49%。吉比特、申通快递昨日盘后发布一季度业绩预告，今日均收盘涨停。",
    "full_content": "【盘后A股上市公司重点业绩公告精选】据财联社不完全统计，截至发稿，盘后包括宁德时代、蓝思科技、佰维存储、中金公司、中国巨石、鼎泰高科、鼎通科技、金海通、龙蟠科技、宁波富邦、海正药业、南网储能、正泰电器、舍得酒业在内的多家A股上市公司发布2026年一季度业绩预告/报告。其中，宁德时代公告，一季度净利润同比增长49%。吉比特、申通快递昨日盘后发布一季度业绩预告，今日均收盘涨停。",
    "sort_time": "1776264749056138",
    "showTime": "2026-04-15 22:52:29",
    "time": "2026-04-15 22:52:29",
    "publish_time": "2026-04-15 22:52:29",
    "raw_data": {
      "code": "202604153706356138",
      "image": [],
      "pinglun_Num": 3,
      "realSort": "1776264749056138",
      "share": 7,
      "showTime": "2026-04-15 22:52:29",
      "stockList": [],
      "summary": "【盘后A股上市公司重点业绩公告精选】据财联社不完全统计，截至发稿，盘后包括宁德时代、蓝思科技、佰维存储、中金公司、中国巨石、鼎泰高科、鼎通科技、金海通、龙蟠科技、宁波富邦、海正药业、南网储能、正泰电器、舍得酒业在内的多家A股上市公司发布2026年一季度业绩预告/报告。其中，宁德时代公告，一季度净利润同比增长49%。吉比特、申通快递昨日盘后发布一季度业绩预告，今日均收盘涨停。",
      "title": "盘后A股上市公司重点业绩公告精选",
      "titleColor": 0
    },
    "source": "东方财富快讯",
    "url": "https://kuaixun.eastmoney.com/news/202604153706356138.html",
    "category": "股市",
    "importance": 5,
    "sentiment": "bullish",
    "related_stocks": [],
    "has_stock_mention": false,
    "comment_count": 3,
    "share_count": 7,
    "tags": {
      "industries": [],
      "concepts": [
        {
          "id": "C105",
          "name": "储能",
          "matched_keyword": "储能"
        },
        {
          "id": "C601",
          "name": "白酒",
          "matched_keyword": "酒"
        },
        {
          "id": "C810",
          "name": "宁德时代概念",
          "matched_keyword": "宁德时代"
        }
      ],
      "industry_ids": [],
      "concept_ids": [
        "C105",
        "C601",
        "C810"
      ]
    }
  },
  {
    "id": "37aa2b37dfc58224",
    "code": "202604153706355671",
    "title": "美伊接近达成结束冲突的框架性协议",
    "summary": "【美伊接近达成结束冲突的框架性协议】央视记者15日自美国方面获悉，美国与伊朗谈判代表在最新一轮会谈中取得进展，正逐步接近达成一项结束冲突的框架性协议。",
    "content": "【美伊接近达成结束冲突的框架性协议】央视记者15日自美国方面获悉，美国与伊朗谈判代表在最新一轮会谈中取得进展，正逐步接近达成一项结束冲突的框架性协议。",
    "full_content": "【美伊接近达成结束冲突的框架性协议】央视记者15日自美国方面获悉，美国与伊朗谈判代表在最新一轮会谈中取得进展，正逐步接近达成一项结束冲突的框架性协议。",
    "sort_time": "1776264674055671",
    "showTime": "2026-04-15 22:51:14",
    "time": "2026-04-15 22:51:14",
    "publish_time": "2026-04-15 22:51:14",
    "raw_data": {
      "code": "202604153706355671",
      "image": [],
      "pinglun_Num": 15,
      "realSort": "1776264674055671",
      "share": 38,
      "showTime": "2026-04-15 22:51:14",
      "stockList": [],
      "summary": "【美伊接近达成结束冲突的框架性协议】央视记者15日自美国方面获悉，美国与伊朗谈判代表在最新一轮会谈中取得进展，正逐步接近达成一项结束冲突的框架性协议。",
      "title": "美伊接近达成结束冲突的框架性协议",
      "titleColor": 0
    },
    "source": "东方财富快讯",
    "url": "https://kuaixun.eastmoney.com/news/202604153706355671.html",
    "category": "其他",
    "importance": 5,
    "sentiment": "neutral",
    "related_stocks": [],
    "has_stock_mention": false,
    "comment_count": 15,
    "share_count": 38,
    "tags": {
      "industries": [],
      "concepts": [],
      "industry_ids": [],
      "concept_ids": []
    }
  },
  {
    "id": "f541ea9f583bf71a",
    "code": "202604153706351566",
    "title": "美官员：美伊在谈判结束战争框架协议方面取得进展",
    "summary": "【美官员：美伊在谈判结束战争框架协议方面取得进展】据美国媒体15日援引两名美国官员的话报道说，美国和伊朗在14日的对话中取得了进展，更接近于达成“一项结束战争的框架协议”。",
    "content": "【美官员：美伊在谈判结束战争框架协议方面取得进展】据美国媒体15日援引两名美国官员的话报道说，美国和伊朗在14日的对话中取得了进展，更接近于达成“一项结束战争的框架协议”。",
    "full_content": "【美官员：美伊在谈判结束战争框架协议方面取得进展】据美国媒体15日援引两名美国官员的话报道说，美国和伊朗在14日的对话中取得了进展，更接近于达成“一项结束战争的框架协议”。",
    "sort_time": "1776264321051566",
    "showTime": "2026-04-15 22:45:21",
    "time": "2026-04-15 22:45:21",
    "publish_time": "2026-04-15 22:45:21",
    "raw_data": {
      "code": "202604153706351566",
      "image": [],
      "pinglun_Num": 16,
      "realSort": "1776264321051566",
      "share": 10,
      "showTime": "2026-04-15 22:45:21",
      "stockList": [],
      "summary": "【美官员：美伊在谈判结束战争框架协议方面取得进展】据美国媒体15日援引两名美国官员的话报道说，美国和伊朗在14日的对话中取得了进展，更接近于达成“一项结束战争的框架协议”。",
      "title": "美官员：美伊在谈判结束战争框架协议方面取得进展",
      "titleColor": 0
    },
    "source": "东方财富快讯",
    "url": "https://kuaixun.eastmoney.com/news/202604153706351566.html",
    "category": "其他",
    "importance": 5,
    "sentiment": "neutral",
    "related_stocks": [],
    "has_stock_mention": false,
    "comment_count": 16,
    "share_count": 10,
    "tags": {
      "industries": [],
      "concepts": [],
      "industry_ids": [],
      "concept_ids": []
    }
  },
  {
    "id": "3017aab535b61b6a",
    "code": "202604153706352276",
    "title": "美国能源信息署（EIA）公布上周的数据显示 美国石油出口总量创历史新高",
    "summary": "美国能源信息署（EIA）公布上周的数据显示，美国石油出口总量创历史新高。",
    "content": "美国能源信息署（EIA）公布上周的数据显示，美国石油出口总量创历史新高。",
    "full_content": "美国能源信息署（EIA）公布上周的数据显示，美国石油出口总量创历史新高。",
    "sort_time": "1776264244052276",
    "showTime": "2026-04-15 22:44:04",
    "time": "2026-04-15 22:44:04",
    "publish_time": "2026-04-15 22:44:04",
    "raw_data": {
      "code": "202604153706352276",
      "image": [],
      "pinglun_Num": 4,
      "realSort": "1776264244052276",
      "share": 0,
      "showTime": "2026-04-15 22:44:04",
      "stockList": [
        "90.BK0464"
      ],
      "summary": "美国能源信息署（EIA）公布上周的数据显示，美国石油出口总量创历史新高。",
      "title": "美国能源信息署（EIA）公布上周的数据显示 美国石油出口总量创历史新高",
      "titleColor": 0
    },
    "source": "东方财富快讯",
    "url": "https://kuaixun.eastmoney.com/news/202604153706352276.html",
    "category": "其他",
    "importance": 6,
    "sentiment": "neutral",
    "related_stocks": [
      "90.BK0464"
    ],
    "has_stock_mention": true,
    "comment_count": 4,
    "share_count": 0,
    "tags": {
      "industries": [],
      "concepts": [
        {
          "id": "C506",
          "name": "石油",
          "matched_keyword": "石油"
        }
      ],
      "industry_ids": [],
      "concept_ids": [
        "C506"
      ]
    }
  },
  {
    "id": "f76812793ae93642",
    "code": "202604153706349391",
    "title": "巴基斯坦总理抵达吉达 开启对沙特的访问",
    "summary": "【巴基斯坦总理抵达吉达 开启对沙特的访问】据巴基斯坦总理办公室消息，4月15日，巴基斯坦总理夏巴兹率团抵达吉达，开启对沙特阿拉伯的访问。",
    "content": "【巴基斯坦总理抵达吉达 开启对沙特的访问】据巴基斯坦总理办公室消息，4月15日，巴基斯坦总理夏巴兹率团抵达吉达，开启对沙特阿拉伯的访问。",
    "full_content": "【巴基斯坦总理抵达吉达 开启对沙特的访问】据巴基斯坦总理办公室消息，4月15日，巴基斯坦总理夏巴兹率团抵达吉达，开启对沙特阿拉伯的访问。",
    "sort_time": "1776264071049391",
    "showTime": "2026-04-15 22:41:11",
    "time": "2026-04-15 22:41:11",
    "publish_time": "2026-04-15 22:41:11",
    "raw_data": {
      "code": "202604153706349391",
      "image": [],
      "pinglun_Num": 2,
      "realSort": "1776264071049391",
      "share": 0,
      "showTime": "2026-04-15 22:41:11",
      "stockList": [],
      "summary": "【巴基斯坦总理抵达吉达 开启对沙特的访问】据巴基斯坦总理办公室消息，4月15日，巴基斯坦总理夏巴兹率团抵达吉达，开启对沙特阿拉伯的访问。",
      "title": "巴基斯坦总理抵达吉达 开启对沙特的访问",
      "titleColor": 0
    },
    "source": "东方财富快讯",
    "url": "https://kuaixun.eastmoney.com/news/202604153706349391.html",
    "category": "其他",
    "importance": 5,
    "sentiment": "neutral",
    "related_stocks": [],
    "has_stock_mention": false,
    "comment_count": 2,
    "share_count": 0,
    "tags": {
      "industries": [],
      "concepts": [],
      "industry_ids": [],
      "concept_ids": []
    }
  },
  {
    "id": "61d72a0c6a785af7",
    "code": "202604153706346269",
    "title": "伊朗外交部说不可能“全盘接受”美国方案",
    "summary": "【伊朗外交部说不可能“全盘接受”美国方案】据伊朗媒体15日报道，伊朗外交部发言人当天说，美国给伊朗提出一揽子方案并希望伊朗“全盘接受”，美国很清楚“这是不可能的”，这不符合谈判和对话的逻辑。 该发言人表示，此前，伊朗通过巴基斯坦向美国方面提交了10项停战条款，以回应所谓美方停火“15点计划”。",
    "content": "【伊朗外交部说不可能“全盘接受”美国方案】据伊朗媒体15日报道，伊朗外交部发言人当天说，美国给伊朗提出一揽子方案并希望伊朗“全盘接受”，美国很清楚“这是不可能的”，这不符合谈判和对话的逻辑。 该发言人表示，此前，伊朗通过巴基斯坦向美国方面提交了10项停战条款，以回应所谓美方停火“15点计划”。",
    "full_content": "【伊朗外交部说不可能“全盘接受”美国方案】据伊朗媒体15日报道，伊朗外交部发言人当天说，美国给伊朗提出一揽子方案并希望伊朗“全盘接受”，美国很清楚“这是不可能的”，这不符合谈判和对话的逻辑。 该发言人表示，此前，伊朗通过巴基斯坦向美国方面提交了10项停战条款，以回应所谓美方停火“15点计划”。",
    "sort_time": "1776263714046269",
    "showTime": "2026-04-15 22:35:14",
    "time": "2026-04-15 22:35:14",
    "publish_time": "2026-04-15 22:35:14",
    "raw_data": {
      "code": "202604153706346269",
      "image": [],
      "pinglun_Num": 8,
      "realSort": "1776263714046269",
      "share": 5,
      "showTime": "2026-04-15 22:35:14",
      "stockList": [],
      "summary": "【伊朗外交部说不可能“全盘接受”美国方案】据伊朗媒体15日报道，伊朗外交部发言人当天说，美国给伊朗提出一揽子方案并希望伊朗“全盘接受”，美国很清楚“这是不可能的”，这不符合谈判和对话的逻辑。 该发言人表示，此前，伊朗通过巴基斯坦向美国方面提交了10项停战条款，以回应所谓美方停火“15点计划”。",
      "title": "伊朗外交部说不可能“全盘接受”美国方案",
      "titleColor": 0
    },
    "source": "东方财富快讯",
    "url": "https://kuaixun.eastmoney.com/news/202604153706346269.html",
    "category": "其他",
    "importance": 5,
    "sentiment": "neutral",
    "related_stocks": [],
    "has_stock_mention": false,
    "comment_count": 8,
    "share_count": 5,
    "tags": {
      "industries": [],
      "concepts": [],
      "industry_ids": [],
      "concept_ids": []
    }
  },
  {
    "id": "f5f8c69eba0f3228",
    "code": "202604153706343249",
    "title": "美国能源信息署（EIA）数据显示 美国上周原油库存减少91.3万桶",
    "summary": "【美国能源信息署（EIA）数据显示 美国上周原油库存减少91.3万桶】美国能源信息署（EIA）数据显示，美国上周原油库存减少91.3万桶，市场预估为增加15.4万桶。美国上周汽油库存减少632.8万桶，市场预估为减少207.7万桶。美国上周原油每日进口量减少210.9万桶。",
    "content": "【美国能源信息署（EIA）数据显示 美国上周原油库存减少91.3万桶】美国能源信息署（EIA）数据显示，美国上周原油库存减少91.3万桶，市场预估为增加15.4万桶。美国上周汽油库存减少632.8万桶，市场预估为减少207.7万桶。美国上周原油每日进口量减少210.9万桶。",
    "full_content": "【美国能源信息署（EIA）数据显示 美国上周原油库存减少91.3万桶】美国能源信息署（EIA）数据显示，美国上周原油库存减少91.3万桶，市场预估为增加15.4万桶。美国上周汽油库存减少632.8万桶，市场预估为减少207.7万桶。美国上周原油每日进口量减少210.9万桶。",
    "sort_time": "1776263435043249",
    "showTime": "2026-04-15 22:30:35",
    "time": "2026-04-15 22:30:35",
    "publish_time": "2026-04-15 22:30:35",
    "raw_data": {
      "code": "202604153706343249",
      "image": [],
      "pinglun_Num": 4,
      "realSort": "1776263435043249",
      "share": 3,
      "showTime": "2026-04-15 22:30:35",
      "stockList": [],
      "summary": "【美国能源信息署（EIA）数据显示 美国上周原油库存减少91.3万桶】美国能源信息署（EIA）数据显示，美国上周原油库存减少91.3万桶，市场预估为增加15.4万桶。美国上周汽油库存减少632.8万桶，市场预估为减少207.7万桶。美国上周原油每日进口量减少210.9万桶。",
      "title": "美国能源信息署（EIA）数据显示 美国上周原油库存减少91.3万桶",
      "titleColor": 0
    },
    "source": "东方财富快讯",
    "url": "https://kuaixun.eastmoney.com/news/202604153706343249.html",
    "category": "期货",
    "importance": 5,
    "sentiment": "neutral",
    "related_stocks": [],
    "has_stock_mention": false,
    "comment_count": 4,
    "share_count": 3,
    "tags": {
      "industries": [],
      "concepts": [
        {
          "id": "C506",
          "name": "石油",
          "matched_keyword": "原油"
        }
      ],
      "industry_ids": [],
      "concept_ids": [
        "C506"
      ]
    }
  },
  {
    "id": "3b96df3c3f891ad1",
    "code": "202604153706342182",
    "title": "纳思达：2025年净亏损7.18亿元 同比转亏",
    "summary": "【纳思达：2025年净亏损7.18亿元 同比转亏】纳思达(002180.SZ)发布2025年年度报告，实现营业收入165.15亿元，同比下降37.48%；归属于上市公司股东的净利润为-7.18亿元，较2024年净利润7.49亿元由盈转亏。公司计划不派发现金红利，不送红股，不以公积金转增股本。小财注：公司Q4净利润-3.62亿，Q3净利润-0.44亿，据此计算，Q4净利润持续亏损。",
    "content": "【纳思达：2025年净亏损7.18亿元 同比转亏】纳思达(002180.SZ)发布2025年年度报告，实现营业收入165.15亿元，同比下降37.48%；归属于上市公司股东的净利润为-7.18亿元，较2024年净利润7.49亿元由盈转亏。公司计划不派发现金红利，不送红股，不以公积金转增股本。小财注：公司Q4净利润-3.62亿，Q3净利润-0.44亿，据此计算，Q4净利润持续亏损。",
    "full_content": "【纳思达：2025年净亏损7.18亿元 同比转亏】纳思达(002180.SZ)发布2025年年度报告，实现营业收入165.15亿元，同比下降37.48%；归属于上市公司股东的净利润为-7.18亿元，较2024年净利润7.49亿元由盈转亏。公司计划不派发现金红利，不送红股，不以公积金转增股本。小财注：公司Q4净利润-3.62亿，Q3净利润-0.44亿，据此计算，Q4净利润持续亏损。",
    "sort_time": "1776263347042182",
    "showTime": "2026-04-15 22:29:07",
    "time": "2026-04-15 22:29:07",
    "publish_time": "2026-04-15 22:29:07",
    "raw_data": {
      "code": "202604153706342182",
      "image": [],
      "pinglun_Num": 3,
      "realSort": "1776263347042182",
      "share": 2,
      "showTime": "2026-04-15 22:29:07",
      "stockList": [
        "0.002180"
      ],
      "summary": "【纳思达：2025年净亏损7.18亿元 同比转亏】纳思达(002180.SZ)发布2025年年度报告，实现营业收入165.15亿元，同比下降37.48%；归属于上市公司股东的净利润为-7.18亿元，较2024年净利润7.49亿元由盈转亏。公司计划不派发现金红利，不送红股，不以公积金转增股本。小财注：公司Q4净利润-3.62亿，Q3净利润-0.44亿，据此计算，Q4净利润持续亏损。",
      "title": "纳思达：2025年净亏损7.18亿元 同比转亏",
      "titleColor": 0
    },
    "source": "东方财富快讯",
    "url": "https://kuaixun.eastmoney.com/news/202604153706342182.html",
    "category": "公司",
    "importance": 6,
    "sentiment": "neutral",
    "related_stocks": [
      "0.002180"
    ],
    "has_stock_mention": true,
    "comment_count": 3,
    "share_count": 2,
    "tags": {
      "industries": [],
      "concepts": [],
      "industry_ids": [],
      "concept_ids": []
    }
  },
  {
    "id": "6114b1db5df44587",
    "code": "202604153706339782",
    "title": "美股稀土概念股走高 UAMY涨超8%",
    "summary": "【美股稀土概念股走高 UAMY涨超8%】美股稀土概念股走高，UAMY涨超8%，USAR涨超6%，CRML、MPMaterials涨超4%。",
    "content": "【美股稀土概念股走高 UAMY涨超8%】美股稀土概念股走高，UAMY涨超8%，USAR涨超6%，CRML、MPMaterials涨超4%。",
    "full_content": "【美股稀土概念股走高 UAMY涨超8%】美股稀土概念股走高，UAMY涨超8%，USAR涨超6%，CRML、MPMaterials涨超4%。",
    "sort_time": "1776263257039782",
    "showTime": "2026-04-15 22:27:37",
    "time": "2026-04-15 22:27:37",
    "publish_time": "2026-04-15 22:27:37",
    "raw_data": {
      "code": "202604153706339782",
      "image": [],
      "pinglun_Num": 6,
      "realSort": "1776263257039782",
      "share": 13,
      "showTime": "2026-04-15 22:27:37",
      "stockList": [],
      "summary": "【美股稀土概念股走高 UAMY涨超8%】美股稀土概念股走高，UAMY涨超8%，USAR涨超6%，CRML、MPMaterials涨超4%。",
      "title": "美股稀土概念股走高 UAMY涨超8%",
      "titleColor": 0
    },
    "source": "东方财富快讯",
    "url": "https://kuaixun.eastmoney.com/news/202604153706339782.html",
    "category": "行业",
    "importance": 5,
    "sentiment": "neutral",
    "related_stocks": [],
    "has_stock_mention": false,
    "comment_count": 6,
    "share_count": 13,
    "tags": {
      "industries": [
        {
          "id": "I010103",
          "name": "消费电子",
          "level1": "制造业",
          "level2": "计算机、通信和其他电子设备制造业",
          "matched_keyword": "AR"
        }
      ],
      "concepts": [
        {
          "id": "C009",
          "name": "元宇宙",
          "matched_keyword": "AR"
        },
        {
          "id": "C503",
          "name": "稀土",
          "matched_keyword": "稀土"
        }
      ],
      "industry_ids": [
        "I010103"
      ],
      "concept_ids": [
        "C009",
        "C503"
      ]
    }
  },
  {
    "id": "f0b3464d5162e681",
    "code": "202604153706339238",
    "title": "国际货币基金组织总裁：如果油价持续高企 各国需做好迎接“艰难时期”的准备",
    "summary": "国际货币基金组织总裁表示，如果油价持续高企，各国需做好迎接“艰难时期”的准备。",
    "content": "国际货币基金组织总裁表示，如果油价持续高企，各国需做好迎接“艰难时期”的准备。",
    "full_content": "国际货币基金组织总裁表示，如果油价持续高企，各国需做好迎接“艰难时期”的准备。",
    "sort_time": "1776263228039238",
    "showTime": "2026-04-15 22:27:08",
    "time": "2026-04-15 22:27:08",
    "publish_time": "2026-04-15 22:27:08",
    "raw_data": {
      "code": "202604153706339238",
      "image": [],
      "pinglun_Num": 4,
      "realSort": "1776263228039238",
      "share": 1,
      "showTime": "2026-04-15 22:27:08",
      "stockList": [
        "90.BK0464"
      ],
      "summary": "国际货币基金组织总裁表示，如果油价持续高企，各国需做好迎接“艰难时期”的准备。",
      "title": "国际货币基金组织总裁：如果油价持续高企 各国需做好迎接“艰难时期”的准备",
      "titleColor": 0
    },
    "source": "东方财富快讯",
    "url": "https://kuaixun.eastmoney.com/news/202604153706339238.html",
    "category": "其他",
    "importance": 6,
    "sentiment": "neutral",
    "related_stocks": [
      "90.BK0464"
    ],
    "has_stock_mention": true,
    "comment_count": 4,
    "share_count": 1,
    "tags": {
      "industries": [
        {
          "id": "I020201",
          "name": "基金管理",
          "level1": "金融业",
          "level2": "资本市场服务",
          "matched_keyword": "基金"
        }
      ],
      "concepts": [],
      "industry_ids": [
        "I020201"
      ],
      "concept_ids": []
    }
  },
  {
    "id": "57e5fe0f27d1208c",
    "code": "202604153706342354",
    "title": "国科天成：拟1.99亿元收购晨锐腾晶51%股权",
    "summary": "【国科天成：拟1.99亿元收购晨锐腾晶51%股权】国科天成(301571.SZ)公告称，公司拟使用自有或自筹资金1.989亿元受让马俊、唐友清等持有的南京晨锐腾晶激光科技有限公司(简称“晨锐腾晶”)合计51%股权。本次交易完成后，晨锐腾晶将成为公司控股子公司，纳入合并报表范围。晨锐腾晶主营射频激励二氧化碳激光器及光学系统研发生产。2025年度，晨锐腾晶实现营收1.10亿元，净利润3899.29万元。本次交易不构成关联交易及重大资产重组，无需提交股东会审议。公司旨在通过此举切入气体激光器市场，丰富产品矩阵，培育新的业绩增长点。",
    "content": "【国科天成：拟1.99亿元收购晨锐腾晶51%股权】国科天成(301571.SZ)公告称，公司拟使用自有或自筹资金1.989亿元受让马俊、唐友清等持有的南京晨锐腾晶激光科技有限公司(简称“晨锐腾晶”)合计51%股权。本次交易完成后，晨锐腾晶将成为公司控股子公司，纳入合并报表范围。晨锐腾晶主营射频激励二氧化碳激光器及光学系统研发生产。2025年度，晨锐腾晶实现营收1.10亿元，净利润3899.29万元。本次交易不构成关联交易及重大资产重组，无需提交股东会审议。公司旨在通过此举切入气体激光器市场，丰富产品矩阵，培育新的业绩增长点。",
    "full_content": "【国科天成：拟1.99亿元收购晨锐腾晶51%股权】国科天成(301571.SZ)公告称，公司拟使用自有或自筹资金1.989亿元受让马俊、唐友清等持有的南京晨锐腾晶激光科技有限公司(简称“晨锐腾晶”)合计51%股权。本次交易完成后，晨锐腾晶将成为公司控股子公司，纳入合并报表范围。晨锐腾晶主营射频激励二氧化碳激光器及光学系统研发生产。2025年度，晨锐腾晶实现营收1.10亿元，净利润3899.29万元。本次交易不构成关联交易及重大资产重组，无需提交股东会审议。公司旨在通过此举切入气体激光器市场，丰富产品矩阵，培育新的业绩增长点。",
    "sort_time": "1776263212042354",
    "showTime": "2026-04-15 22:26:52",
    "time": "2026-04-15 22:26:52",
    "publish_time": "2026-04-15 22:26:52",
    "raw_data": {
      "code": "202604153706342354",
      "image": [],
      "pinglun_Num": 2,
      "realSort": "1776263212042354",
      "share": 2,
      "showTime": "2026-04-15 22:26:52",
      "stockList": [
        "0.301571"
      ],
      "summary": "【国科天成：拟1.99亿元收购晨锐腾晶51%股权】国科天成(301571.SZ)公告称，公司拟使用自有或自筹资金1.989亿元受让马俊、唐友清等持有的南京晨锐腾晶激光科技有限公司(简称“晨锐腾晶”)合计51%股权。本次交易完成后，晨锐腾晶将成为公司控股子公司，纳入合并报表范围。晨锐腾晶主营射频激励二氧化碳激光器及光学系统研发生产。2025年度，晨锐腾晶实现营收1.10亿元，净利润3899.29万元。本次交易不构成关联交易及重大资产重组，无需提交股东会审议。公司旨在通过此举切入气体激光器市场，丰富产品矩阵，培育新的业绩增长点。",
      "title": "国科天成：拟1.99亿元收购晨锐腾晶51%股权",
      "titleColor": 0
    },
    "source": "东方财富快讯",
    "url": "https://kuaixun.eastmoney.com/news/202604153706342354.html",
    "category": "公司",
    "importance": 6,
    "sentiment": "bullish",
    "related_stocks": [
      "0.301571"
    ],
    "has_stock_mention": true,
    "comment_count": 2,
    "share_count": 2,
    "tags": {
      "industries": [],
      "concepts": [],
      "industry_ids": [],
      "concept_ids": []
    }
  },
  {
    "id": "1a3ab6388e5030f4",
    "code": "202604153706337274",
    "title": "以色列将召开安全内阁会议 讨论黎巴嫩停火可能性",
    "summary": "【以色列将召开安全内阁会议 讨论黎巴嫩停火可能性】当地时间15日，一名以色列官员透露，以总理内塔尼亚胡将于当晚召开安全内阁会议，讨论黎巴嫩停火的可能性。",
    "content": "【以色列将召开安全内阁会议 讨论黎巴嫩停火可能性】当地时间15日，一名以色列官员透露，以总理内塔尼亚胡将于当晚召开安全内阁会议，讨论黎巴嫩停火的可能性。",
    "full_content": "【以色列将召开安全内阁会议 讨论黎巴嫩停火可能性】当地时间15日，一名以色列官员透露，以总理内塔尼亚胡将于当晚召开安全内阁会议，讨论黎巴嫩停火的可能性。",
    "sort_time": "1776263035037274",
    "showTime": "2026-04-15 22:23:55",
    "time": "2026-04-15 22:23:55",
    "publish_time": "2026-04-15 22:23:55",
    "raw_data": {
      "code": "202604153706337274",
      "image": [],
      "pinglun_Num": 2,
      "realSort": "1776263035037274",
      "share": 3,
      "showTime": "2026-04-15 22:23:55",
      "stockList": [],
      "summary": "【以色列将召开安全内阁会议 讨论黎巴嫩停火可能性】当地时间15日，一名以色列官员透露，以总理内塔尼亚胡将于当晚召开安全内阁会议，讨论黎巴嫩停火的可能性。",
      "title": "以色列将召开安全内阁会议 讨论黎巴嫩停火可能性",
      "titleColor": 0
    },
    "source": "东方财富快讯",
    "url": "https://kuaixun.eastmoney.com/news/202604153706337274.html",
    "category": "其他",
    "importance": 5,
    "sentiment": "neutral",
    "related_stocks": [],
    "has_stock_mention": false,
    "comment_count": 2,
    "share_count": 3,
    "tags": {
      "industries": [],
      "concepts": [],
      "industry_ids": [],
      "concept_ids": []
    }
  },
  {
    "id": "4971e99043920f35",
    "code": "202604153706338470",
    "title": "美国能源部长：委内瑞拉石油产量已增加至120万桶/日",
    "summary": "美国能源部长赖特称，委内瑞拉石油产量已增加至120万桶/日。",
    "content": "美国能源部长赖特称，委内瑞拉石油产量已增加至120万桶/日。",
    "full_content": "美国能源部长赖特称，委内瑞拉石油产量已增加至120万桶/日。",
    "sort_time": "1776262957038470",
    "showTime": "2026-04-15 22:22:37",
    "time": "2026-04-15 22:22:37",
    "publish_time": "2026-04-15 22:22:37",
    "raw_data": {
      "code": "202604153706338470",
      "image": [],
      "pinglun_Num": 7,
      "realSort": "1776262957038470",
      "share": 4,
      "showTime": "2026-04-15 22:22:37",
      "stockList": [
        "90.BK0464"
      ],
      "summary": "美国能源部长赖特称，委内瑞拉石油产量已增加至120万桶/日。",
      "title": "美国能源部长：委内瑞拉石油产量已增加至120万桶/日",
      "titleColor": 0
    },
    "source": "东方财富快讯",
    "url": "https://kuaixun.eastmoney.com/news/202604153706338470.html",
    "category": "其他",
    "importance": 6,
    "sentiment": "neutral",
    "related_stocks": [
      "90.BK0464"
    ],
    "has_stock_mention": true,
    "comment_count": 7,
    "share_count": 4,
    "tags": {
      "industries": [],
      "concepts": [
        {
          "id": "C506",
          "name": "石油",
          "matched_keyword": "石油"
        }
      ],
      "industry_ids": [],
      "concept_ids": [
        "C506"
      ]
    }
  },
  {
    "id": "5353e7f84ac51303",
    "code": "202604153706333745",
    "title": "特朗普暗示对伊朗的打击行动将持续",
    "summary": "【特朗普暗示对伊朗的打击行动将持续】据美国媒体15日报道，美国总统特朗普称，他认为与伊朗的战争已“接近尾声”，但同时暗示，只要是为了阻止伊朗制造核武器，美国的打击行动就会持续。",
    "content": "【特朗普暗示对伊朗的打击行动将持续】据美国媒体15日报道，美国总统特朗普称，他认为与伊朗的战争已“接近尾声”，但同时暗示，只要是为了阻止伊朗制造核武器，美国的打击行动就会持续。",
    "full_content": "【特朗普暗示对伊朗的打击行动将持续】据美国媒体15日报道，美国总统特朗普称，他认为与伊朗的战争已“接近尾声”，但同时暗示，只要是为了阻止伊朗制造核武器，美国的打击行动就会持续。",
    "sort_time": "1776262810033745",
    "showTime": "2026-04-15 22:20:10",
    "time": "2026-04-15 22:20:10",
    "publish_time": "2026-04-15 22:20:10",
    "raw_data": {
      "code": "202604153706333745",
      "image": [],
      "pinglun_Num": 22,
      "realSort": "1776262810033745",
      "share": 18,
      "showTime": "2026-04-15 22:20:10",
      "stockList": [],
      "summary": "【特朗普暗示对伊朗的打击行动将持续】据美国媒体15日报道，美国总统特朗普称，他认为与伊朗的战争已“接近尾声”，但同时暗示，只要是为了阻止伊朗制造核武器，美国的打击行动就会持续。",
      "title": "特朗普暗示对伊朗的打击行动将持续",
      "titleColor": 0
    },
    "source": "东方财富快讯",
    "url": "https://kuaixun.eastmoney.com/news/202604153706333745.html",
    "category": "其他",
    "importance": 5,
    "sentiment": "neutral",
    "related_stocks": [],
    "has_stock_mention": false,
    "comment_count": 22,
    "share_count": 18,
    "tags": {
      "industries": [],
      "concepts": [],
      "industry_ids": [],
      "concept_ids": []
    }
  },
  {
    "id": "3751a5ab0bf72041",
    "code": "202604153706333448",
    "title": "卡塔尔官员：用于全球芯片制造的氦气出口同样令人担忧",
    "summary": "卡塔尔官员表示，用于全球芯片制造的氦气出口同样令人担忧。",
    "content": "卡塔尔官员表示，用于全球芯片制造的氦气出口同样令人担忧。",
    "full_content": "卡塔尔官员表示，用于全球芯片制造的氦气出口同样令人担忧。",
    "sort_time": "1776262734033448",
    "showTime": "2026-04-15 22:18:54",
    "time": "2026-04-15 22:18:54",
    "publish_time": "2026-04-15 22:18:54",
    "raw_data": {
      "code": "202604153706333448",
      "image": [],
      "pinglun_Num": 6,
      "realSort": "1776262734033448",
      "share": 3,
      "showTime": "2026-04-15 22:18:54",
      "stockList": [
        "150.013446"
      ],
      "summary": "卡塔尔官员表示，用于全球芯片制造的氦气出口同样令人担忧。",
      "title": "卡塔尔官员：用于全球芯片制造的氦气出口同样令人担忧",
      "titleColor": 0
    },
    "source": "东方财富快讯",
    "url": "https://kuaixun.eastmoney.com/news/202604153706333448.html",
    "category": "科技",
    "importance": 6,
    "sentiment": "neutral",
    "related_stocks": [
      "150.013446"
    ],
    "has_stock_mention": true,
    "comment_count": 6,
    "share_count": 3,
    "tags": {
      "industries": [
        {
          "id": "I010101",
          "name": "半导体",
          "level1": "制造业",
          "level2": "计算机、通信和其他电子设备制造业",
          "matched_keyword": "芯片"
        }
      ],
      "concepts": [
        {
          "id": "C002",
          "name": "芯片",
          "matched_keyword": "芯片"
        }
      ],
      "industry_ids": [
        "I010101"
      ],
      "concept_ids": [
        "C002"
      ]
    }
  },
  {
    "id": "6edb330dd3ed14b7",
    "code": "202604153706332883",
    "title": "美国能源部长：没有必要进一步释放石油储备",
    "summary": "美国能源部长赖特表示，没有必要进一步释放石油储备。",
    "content": "美国能源部长赖特表示，没有必要进一步释放石油储备。",
    "full_content": "美国能源部长赖特表示，没有必要进一步释放石油储备。",
    "sort_time": "1776262670032883",
    "showTime": "2026-04-15 22:17:50",
    "time": "2026-04-15 22:17:50",
    "publish_time": "2026-04-15 22:17:50",
    "raw_data": {
      "code": "202604153706332883",
      "image": [],
      "pinglun_Num": 1,
      "realSort": "1776262670032883",
      "share": 0,
      "showTime": "2026-04-15 22:17:50",
      "stockList": [
        "90.BK0464"
      ],
      "summary": "美国能源部长赖特表示，没有必要进一步释放石油储备。",
      "title": "美国能源部长：没有必要进一步释放石油储备",
      "titleColor": 0
    },
    "source": "东方财富快讯",
    "url": "https://kuaixun.eastmoney.com/news/202604153706332883.html",
    "category": "其他",
    "importance": 6,
    "sentiment": "neutral",
    "related_stocks": [
      "90.BK0464"
    ],
    "has_stock_mention": true,
    "comment_count": 1,
    "share_count": 0,
    "tags": {
      "industries": [],
      "concepts": [
        {
          "id": "C506",
          "name": "石油",
          "matched_keyword": "石油"
        }
      ],
      "industry_ids": [],
      "concept_ids": [
        "C506"
      ]
    }
  },
  {
    "id": "07afe7232e75b87d",
    "code": "202604153706330957",
    "title": "赣锋锂业：2026年公司储能电池出货量预计增长较快",
    "summary": "【赣锋锂业：2026年公司储能电池出货量预计增长较快】赣锋锂业在2025年度网上业绩说明会上表示，目前公司电芯产能利用率较高，2026年储能电池出货量预计将保持较快增长。",
    "content": "【赣锋锂业：2026年公司储能电池出货量预计增长较快】赣锋锂业在2025年度网上业绩说明会上表示，目前公司电芯产能利用率较高，2026年储能电池出货量预计将保持较快增长。",
    "full_content": "【赣锋锂业：2026年公司储能电池出货量预计增长较快】赣锋锂业在2025年度网上业绩说明会上表示，目前公司电芯产能利用率较高，2026年储能电池出货量预计将保持较快增长。",
    "sort_time": "1776262319030957",
    "showTime": "2026-04-15 22:11:59",
    "time": "2026-04-15 22:11:59",
    "publish_time": "2026-04-15 22:11:59",
    "raw_data": {
      "code": "202604153706330957",
      "image": [],
      "pinglun_Num": 5,
      "realSort": "1776262319030957",
      "share": 4,
      "showTime": "2026-04-15 22:11:59",
      "stockList": [
        "0.002460",
        "116.01772"
      ],
      "summary": "【赣锋锂业：2026年公司储能电池出货量预计增长较快】赣锋锂业在2025年度网上业绩说明会上表示，目前公司电芯产能利用率较高，2026年储能电池出货量预计将保持较快增长。",
      "title": "赣锋锂业：2026年公司储能电池出货量预计增长较快",
      "titleColor": 0
    },
    "source": "东方财富快讯",
    "url": "https://kuaixun.eastmoney.com/news/202604153706330957.html",
    "category": "公司",
    "importance": 6,
    "sentiment": "bullish",
    "related_stocks": [
      "0.002460",
      "116.01772"
    ],
    "has_stock_mention": true,
    "comment_count": 5,
    "share_count": 4,
    "tags": {
      "industries": [
        {
          "id": "I010201",
          "name": "锂离子电池制造",
          "level1": "制造业",
          "level2": "电气机械和器材制造业",
          "matched_keyword": "储能电池"
        }
      ],
      "concepts": [
        {
          "id": "C102",
          "name": "锂电池",
          "matched_keyword": "储能电池"
        },
        {
          "id": "C105",
          "name": "储能",
          "matched_keyword": "储能"
        }
      ],
      "industry_ids": [
        "I010201"
      ],
      "concept_ids": [
        "C102",
        "C105"
      ]
    }
  },
  {
    "id": "bc5ebde27406e5be",
    "code": "202604153706312145",
    "title": "巴基斯坦代表团抵达伊朗 将讨论第二轮伊美谈判事宜",
    "summary": "【巴基斯坦代表团抵达伊朗 将讨论第二轮伊美谈判事宜】总台记者15日自伊朗方面获悉，巴基斯坦知情人士透露，当天，巴基斯坦陆军参谋长阿西姆·穆尼尔率领一个高级别政治与安全代表团抵达德黑兰。该高级代表团携带着美国发给伊朗的最新信息，计划与伊朗官员会面，讨论即将在伊斯兰堡举行的第二轮伊美谈判相关事宜。",
    "content": "【巴基斯坦代表团抵达伊朗 将讨论第二轮伊美谈判事宜】总台记者15日自伊朗方面获悉，巴基斯坦知情人士透露，当天，巴基斯坦陆军参谋长阿西姆·穆尼尔率领一个高级别政治与安全代表团抵达德黑兰。该高级代表团携带着美国发给伊朗的最新信息，计划与伊朗官员会面，讨论即将在伊斯兰堡举行的第二轮伊美谈判相关事宜。",
    "full_content": "【巴基斯坦代表团抵达伊朗 将讨论第二轮伊美谈判事宜】总台记者15日自伊朗方面获悉，巴基斯坦知情人士透露，当天，巴基斯坦陆军参谋长阿西姆·穆尼尔率领一个高级别政治与安全代表团抵达德黑兰。该高级代表团携带着美国发给伊朗的最新信息，计划与伊朗官员会面，讨论即将在伊斯兰堡举行的第二轮伊美谈判相关事宜。",
    "sort_time": "1776262040012145",
    "showTime": "2026-04-15 22:07:20",
    "time": "2026-04-15 22:07:20",
    "publish_time": "2026-04-15 22:07:20",
    "raw_data": {
      "code": "202604153706312145",
      "image": [],
      "pinglun_Num": 24,
      "realSort": "1776262040012145",
      "share": 32,
      "showTime": "2026-04-15 22:07:20",
      "stockList": [],
      "summary": "【巴基斯坦代表团抵达伊朗 将讨论第二轮伊美谈判事宜】总台记者15日自伊朗方面获悉，巴基斯坦知情人士透露，当天，巴基斯坦陆军参谋长阿西姆·穆尼尔率领一个高级别政治与安全代表团抵达德黑兰。该高级代表团携带着美国发给伊朗的最新信息，计划与伊朗官员会面，讨论即将在伊斯兰堡举行的第二轮伊美谈判相关事宜。",
      "title": "巴基斯坦代表团抵达伊朗 将讨论第二轮伊美谈判事宜",
      "titleColor": 3
    },
    "source": "东方财富快讯",
    "url": "https://kuaixun.eastmoney.com/news/202604153706312145.html",
    "category": "其他",
    "importance": 5,
    "sentiment": "neutral",
    "related_stocks": [],
    "has_stock_mention": false,
    "comment_count": 24,
    "share_count": 32,
    "tags": {
      "industries": [],
      "concepts": [],
      "industry_ids": [],
      "concept_ids": []
    }
  },
  {
    "id": "78d5eb7e4317752e",
    "code": "202604153706310281",
    "title": "联合国人权专家呼吁所有会员国暂停向以色列转让武器",
    "summary": "【联合国人权专家呼吁所有会员国暂停向以色列转让武器】当地时间15日，多名联合国人权领域的专家发表联合声明，呼吁联合国所有会员国暂停向以色列转让武器。",
    "content": "【联合国人权专家呼吁所有会员国暂停向以色列转让武器】当地时间15日，多名联合国人权领域的专家发表联合声明，呼吁联合国所有会员国暂停向以色列转让武器。",
    "full_content": "【联合国人权专家呼吁所有会员国暂停向以色列转让武器】当地时间15日，多名联合国人权领域的专家发表联合声明，呼吁联合国所有会员国暂停向以色列转让武器。",
    "sort_time": "1776261822010281",
    "showTime": "2026-04-15 22:03:42",
    "time": "2026-04-15 22:03:42",
    "publish_time": "2026-04-15 22:03:42",
    "raw_data": {
      "code": "202604153706310281",
      "image": [],
      "pinglun_Num": 13,
      "realSort": "1776261822010281",
      "share": 4,
      "showTime": "2026-04-15 22:03:42",
      "stockList": [],
      "summary": "【联合国人权专家呼吁所有会员国暂停向以色列转让武器】当地时间15日，多名联合国人权领域的专家发表联合声明，呼吁联合国所有会员国暂停向以色列转让武器。",
      "title": "联合国人权专家呼吁所有会员国暂停向以色列转让武器",
      "titleColor": 0
    },
    "source": "东方财富快讯",
    "url": "https://kuaixun.eastmoney.com/news/202604153706310281.html",
    "category": "其他",
    "importance": 5,
    "sentiment": "neutral",
    "related_stocks": [],
    "has_stock_mention": false,
    "comment_count": 13,
    "share_count": 4,
    "tags": {
      "industries": [],
      "concepts": [],
      "industry_ids": [],
      "concept_ids": []
    }
  },
  {
    "id": "8d7f07791b6aca34",
    "code": "202604153706308251",
    "title": "纳斯达克综合指数涨幅扩大 现涨0.5%",
    "summary": "纳斯达克综合指数涨幅扩大，现涨0.5%，最新报23760.77点。",
    "content": "纳斯达克综合指数涨幅扩大，现涨0.5%，最新报23760.77点。",
    "full_content": "纳斯达克综合指数涨幅扩大，现涨0.5%，最新报23760.77点。",
    "sort_time": "1776261693008251",
    "showTime": "2026-04-15 22:01:33",
    "time": "2026-04-15 22:01:33",
    "publish_time": "2026-04-15 22:01:33",
    "raw_data": {
      "code": "202604153706308251",
      "image": [],
      "pinglun_Num": 14,
      "realSort": "1776261693008251",
      "share": 5,
      "showTime": "2026-04-15 22:01:33",
      "stockList": [],
      "summary": "纳斯达克综合指数涨幅扩大，现涨0.5%，最新报23760.77点。",
      "title": "纳斯达克综合指数涨幅扩大 现涨0.5%",
      "titleColor": 0
    },
    "source": "东方财富快讯",
    "url": "https://kuaixun.eastmoney.com/news/202604153706308251.html",
    "category": "其他",
    "importance": 5,
    "sentiment": "neutral",
    "related_stocks": [],
    "has_stock_mention": false,
    "comment_count": 14,
    "share_count": 5,
    "tags": {
      "industries": [],
      "concepts": [],
      "industry_ids": [],
      "concept_ids": []
    }
  },
  {
    "id": "8dca7536bd9785d8",
    "code": "202604153706308774",
    "title": "美国4月份NAHB住宅建筑商指数降至34 预估为37",
    "summary": "美国4月份NAHB住宅建筑商指数降至34，预估为37。",
    "content": "美国4月份NAHB住宅建筑商指数降至34，预估为37。",
    "full_content": "美国4月份NAHB住宅建筑商指数降至34，预估为37。",
    "sort_time": "1776261620008774",
    "showTime": "2026-04-15 22:00:20",
    "time": "2026-04-15 22:00:20",
    "publish_time": "2026-04-15 22:00:20",
    "raw_data": {
      "code": "202604153706308774",
      "image": [],
      "pinglun_Num": 0,
      "realSort": "1776261620008774",
      "share": 0,
      "showTime": "2026-04-15 22:00:20",
      "stockList": [],
      "summary": "美国4月份NAHB住宅建筑商指数降至34，预估为37。",
      "title": "美国4月份NAHB住宅建筑商指数降至34 预估为37",
      "titleColor": 0
    },
    "source": "东方财富快讯",
    "url": "https://kuaixun.eastmoney.com/news/202604153706308774.html",
    "category": "其他",
    "importance": 5,
    "sentiment": "neutral",
    "related_stocks": [],
    "has_stock_mention": false,
    "comment_count": 0,
    "share_count": 0,
    "tags": {
      "industries": [],
      "concepts": [],
      "industry_ids": [],
      "concept_ids": []
    }
  },
  {
    "id": "1b27436547ea2cb1",
    "code": "202604153706306159",
    "title": "美股核电股集体冲高 NuScale Power大涨近14%",
    "summary": "【美股核电股集体冲高 NuScale Power大涨近14%】美股核电股集体冲高，NuScale Power大涨近14%，Oklo涨超10%，Energy Fuels、NANO Nuclear Energy涨超4%。",
    "content": "【美股核电股集体冲高 NuScale Power大涨近14%】美股核电股集体冲高，NuScale Power大涨近14%，Oklo涨超10%，Energy Fuels、NANO Nuclear Energy涨超4%。",
    "full_content": "【美股核电股集体冲高 NuScale Power大涨近14%】美股核电股集体冲高，NuScale Power大涨近14%，Oklo涨超10%，Energy Fuels、NANO Nuclear Energy涨超4%。",
    "sort_time": "1776261524006159",
    "showTime": "2026-04-15 21:58:44",
    "time": "2026-04-15 21:58:44",
    "publish_time": "2026-04-15 21:58:44",
    "raw_data": {
      "code": "202604153706306159",
      "image": [],
      "pinglun_Num": 17,
      "realSort": "1776261524006159",
      "share": 28,
      "showTime": "2026-04-15 21:58:44",
      "stockList": [
        "90.BK0577",
        "106.SMR"
      ],
      "summary": "【美股核电股集体冲高 NuScale Power大涨近14%】美股核电股集体冲高，NuScale Power大涨近14%，Oklo涨超10%，Energy Fuels、NANO Nuclear Energy涨超4%。",
      "title": "美股核电股集体冲高 NuScale Power大涨近14%",
      "titleColor": 0
    },
    "source": "东方财富快讯",
    "url": "https://kuaixun.eastmoney.com/news/202604153706306159.html",
    "category": "其他",
    "importance": 6,
    "sentiment": "neutral",
    "related_stocks": [
      "90.BK0577",
      "106.SMR"
    ],
    "has_stock_mention": true,
    "comment_count": 17,
    "share_count": 28,
    "tags": {
      "industries": [],
      "concepts": [
        {
          "id": "C109",
          "name": "核能",
          "matched_keyword": "核电"
        }
      ],
      "industry_ids": [],
      "concept_ids": [
        "C109"
      ]
    }
  },
  {
    "id": "c84b737abdcd0903",
    "code": "202604153706306310",
    "title": "白宫经济顾问：我们认为油价的飙升将是相当短暂的",
    "summary": "白宫经济顾问哈塞特表示，我们认为油价的飙升将是相当短暂的。",
    "content": "白宫经济顾问哈塞特表示，我们认为油价的飙升将是相当短暂的。",
    "full_content": "白宫经济顾问哈塞特表示，我们认为油价的飙升将是相当短暂的。",
    "sort_time": "1776261435006310",
    "showTime": "2026-04-15 21:57:15",
    "time": "2026-04-15 21:57:15",
    "publish_time": "2026-04-15 21:57:15",
    "raw_data": {
      "code": "202604153706306310",
      "image": [],
      "pinglun_Num": 3,
      "realSort": "1776261435006310",
      "share": 0,
      "showTime": "2026-04-15 21:57:15",
      "stockList": [
        "90.BK0464"
      ],
      "summary": "白宫经济顾问哈塞特表示，我们认为油价的飙升将是相当短暂的。",
      "title": "白宫经济顾问：我们认为油价的飙升将是相当短暂的",
      "titleColor": 0
    },
    "source": "东方财富快讯",
    "url": "https://kuaixun.eastmoney.com/news/202604153706306310.html",
    "category": "其他",
    "importance": 6,
    "sentiment": "neutral",
    "related_stocks": [
      "90.BK0464"
    ],
    "has_stock_mention": true,
    "comment_count": 3,
    "share_count": 0,
    "tags": {
      "industries": [],
      "concepts": [],
      "industry_ids": [],
      "concept_ids": []
    }
  },
  {
    "id": "26a464254768a14a",
    "code": "202604153706304138",
    "title": "阿斯麦跌幅扩大至5%",
    "summary": "阿斯麦跌幅扩大至5%。据财联社，阿斯麦今日上调全年销售指引，但Q2展望略逊于市场预期。",
    "content": "阿斯麦跌幅扩大至5%。据财联社，阿斯麦今日上调全年销售指引，但Q2展望略逊于市场预期。",
    "full_content": "阿斯麦跌幅扩大至5%。据财联社，阿斯麦今日上调全年销售指引，但Q2展望略逊于市场预期。",
    "sort_time": "1776261219004138",
    "showTime": "2026-04-15 21:53:39",
    "time": "2026-04-15 21:53:39",
    "publish_time": "2026-04-15 21:53:39",
    "raw_data": {
      "code": "202604153706304138",
      "image": [],
      "pinglun_Num": 0,
      "realSort": "1776261219004138",
      "share": 4,
      "showTime": "2026-04-15 21:53:39",
      "stockList": [
        "105.ASML"
      ],
      "summary": "阿斯麦跌幅扩大至5%。据财联社，阿斯麦今日上调全年销售指引，但Q2展望略逊于市场预期。",
      "title": "阿斯麦跌幅扩大至5%",
      "titleColor": 0
    },
    "source": "东方财富快讯",
    "url": "https://kuaixun.eastmoney.com/news/202604153706304138.html",
    "category": "其他",
    "importance": 6,
    "sentiment": "neutral",
    "related_stocks": [
      "105.ASML"
    ],
    "has_stock_mention": true,
    "comment_count": 0,
    "share_count": 4,
    "tags": {
      "industries": [],
      "concepts": [],
      "industry_ids": [],
      "concept_ids": []
    }
  },
  {
    "id": "f4542bdcb6d80771",
    "code": "202604153706303785",
    "title": "过敏高发一款滴眼液飙至3000元",
    "summary": "【过敏高发一款滴眼液飙至3000元】近日，一款名为“他克莫司”的滴眼液在电商平台价格飙升，原价每盒700多元，涨到了一两千甚至三千元不等。这种滴眼液为什么涨价？真的是因为缺货吗？记者联系北京同仁医院、四川省人民医院、中山大学中山眼科中心等多家医院，相关科室负责人介绍，他克莫司滴眼液并不缺货，医院售价一直稳定在779元。",
    "content": "【过敏高发一款滴眼液飙至3000元】近日，一款名为“他克莫司”的滴眼液在电商平台价格飙升，原价每盒700多元，涨到了一两千甚至三千元不等。这种滴眼液为什么涨价？真的是因为缺货吗？记者联系北京同仁医院、四川省人民医院、中山大学中山眼科中心等多家医院，相关科室负责人介绍，他克莫司滴眼液并不缺货，医院售价一直稳定在779元。",
    "full_content": "【过敏高发一款滴眼液飙至3000元】近日，一款名为“他克莫司”的滴眼液在电商平台价格飙升，原价每盒700多元，涨到了一两千甚至三千元不等。这种滴眼液为什么涨价？真的是因为缺货吗？记者联系北京同仁医院、四川省人民医院、中山大学中山眼科中心等多家医院，相关科室负责人介绍，他克莫司滴眼液并不缺货，医院售价一直稳定在779元。",
    "sort_time": "1776261160003785",
    "showTime": "2026-04-15 21:52:40",
    "time": "2026-04-15 21:52:40",
    "publish_time": "2026-04-15 21:52:40",
    "raw_data": {
      "code": "202604153706303785",
      "image": [],
      "pinglun_Num": 11,
      "realSort": "1776261160003785",
      "share": 25,
      "showTime": "2026-04-15 21:52:40",
      "stockList": [],
      "summary": "【过敏高发一款滴眼液飙至3000元】近日，一款名为“他克莫司”的滴眼液在电商平台价格飙升，原价每盒700多元，涨到了一两千甚至三千元不等。这种滴眼液为什么涨价？真的是因为缺货吗？记者联系北京同仁医院、四川省人民医院、中山大学中山眼科中心等多家医院，相关科室负责人介绍，他克莫司滴眼液并不缺货，医院售价一直稳定在779元。",
      "title": "过敏高发一款滴眼液飙至3000元",
      "titleColor": 0
    },
    "source": "东方财富快讯",
    "url": "https://kuaixun.eastmoney.com/news/202604153706303785.html",
    "category": "其他",
    "importance": 5,
    "sentiment": "neutral",
    "related_stocks": [],
    "has_stock_mention": false,
    "comment_count": 11,
    "share_count": 25,
    "tags": {
      "industries": [],
      "concepts": [
        {
          "id": "C304",
          "name": "医疗服务",
          "matched_keyword": "医院"
        },
        {
          "id": "C804",
          "name": "拼多多概念",
          "matched_keyword": "电商"
        }
      ],
      "industry_ids": [],
      "concept_ids": [
        "C304",
        "C804"
      ]
    }
  },
  {
    "id": "1d89d56e2a449a3a",
    "code": "202604153706302714",
    "title": "巴基斯坦消息人士：巴外交部代表团前往伊朗",
    "summary": "【巴基斯坦消息人士：巴外交部代表团前往伊朗】巴基斯坦消息人士15日在接受采访时表示，巴外交部代表团当天已离开巴基斯坦前往伊朗。",
    "content": "【巴基斯坦消息人士：巴外交部代表团前往伊朗】巴基斯坦消息人士15日在接受采访时表示，巴外交部代表团当天已离开巴基斯坦前往伊朗。",
    "full_content": "【巴基斯坦消息人士：巴外交部代表团前往伊朗】巴基斯坦消息人士15日在接受采访时表示，巴外交部代表团当天已离开巴基斯坦前往伊朗。",
    "sort_time": "1776261118002714",
    "showTime": "2026-04-15 21:51:58",
    "time": "2026-04-15 21:51:58",
    "publish_time": "2026-04-15 21:51:58",
    "raw_data": {
      "code": "202604153706302714",
      "image": [],
      "pinglun_Num": 7,
      "realSort": "1776261118002714",
      "share": 1,
      "showTime": "2026-04-15 21:51:58",
      "stockList": [],
      "summary": "【巴基斯坦消息人士：巴外交部代表团前往伊朗】巴基斯坦消息人士15日在接受采访时表示，巴外交部代表团当天已离开巴基斯坦前往伊朗。",
      "title": "巴基斯坦消息人士：巴外交部代表团前往伊朗",
      "titleColor": 0
    },
    "source": "东方财富快讯",
    "url": "https://kuaixun.eastmoney.com/news/202604153706302714.html",
    "category": "其他",
    "importance": 5,
    "sentiment": "neutral",
    "related_stocks": [],
    "has_stock_mention": false,
    "comment_count": 7,
    "share_count": 1,
    "tags": {
      "industries": [],
      "concepts": [],
      "industry_ids": [],
      "concept_ids": []
    }
  },
  {
    "id": "a929ea414f13bad1",
    "code": "202604153706302370",
    "title": "美国白宫经济顾问：美国月度就业增长人数的中位数水平约为5万至6万人",
    "summary": "美国白宫经济顾问哈塞特表示，美国月度就业增长人数的中位数水平约为5万至6万人。",
    "content": "美国白宫经济顾问哈塞特表示，美国月度就业增长人数的中位数水平约为5万至6万人。",
    "full_content": "美国白宫经济顾问哈塞特表示，美国月度就业增长人数的中位数水平约为5万至6万人。",
    "sort_time": "1776261086002370",
    "showTime": "2026-04-15 21:51:26",
    "time": "2026-04-15 21:51:26",
    "publish_time": "2026-04-15 21:51:26",
    "raw_data": {
      "code": "202604153706302370",
      "image": [],
      "pinglun_Num": 0,
      "realSort": "1776261086002370",
      "share": 0,
      "showTime": "2026-04-15 21:51:26",
      "stockList": [],
      "summary": "美国白宫经济顾问哈塞特表示，美国月度就业增长人数的中位数水平约为5万至6万人。",
      "title": "美国白宫经济顾问：美国月度就业增长人数的中位数水平约为5万至6万人",
      "titleColor": 0
    },
    "source": "东方财富快讯",
    "url": "https://kuaixun.eastmoney.com/news/202604153706302370.html",
    "category": "其他",
    "importance": 5,
    "sentiment": "bullish",
    "related_stocks": [],
    "has_stock_mention": false,
    "comment_count": 0,
    "share_count": 0,
    "tags": {
      "industries": [],
      "concepts": [],
      "industry_ids": [],
      "concept_ids": []
    }
  },
  {
    "id": "e5752b43ff55d623",
    "code": "202604153706301822",
    "title": "太空医院要来了 全球首个太空医院照进现实",
    "summary": "【太空医院要来了 全球首个太空医院照进现实】今天（15日），中国科学院微小卫星创新研究院自主研制的轻舟试验飞船正式发布了在轨半个月来的首批科学实验与工程试验成果，其中就包括很多涉及生命健康的前沿医疗项目，也让我们看到了未来太空医院的雏形。",
    "content": "【太空医院要来了 全球首个太空医院照进现实】今天（15日），中国科学院微小卫星创新研究院自主研制的轻舟试验飞船正式发布了在轨半个月来的首批科学实验与工程试验成果，其中就包括很多涉及生命健康的前沿医疗项目，也让我们看到了未来太空医院的雏形。",
    "full_content": "【太空医院要来了 全球首个太空医院照进现实】今天（15日），中国科学院微小卫星创新研究院自主研制的轻舟试验飞船正式发布了在轨半个月来的首批科学实验与工程试验成果，其中就包括很多涉及生命健康的前沿医疗项目，也让我们看到了未来太空医院的雏形。",
    "sort_time": "1776261026001822",
    "showTime": "2026-04-15 21:50:26",
    "time": "2026-04-15 21:50:26",
    "publish_time": "2026-04-15 21:50:26",
    "raw_data": {
      "code": "202604153706301822",
      "image": [],
      "pinglun_Num": 28,
      "realSort": "1776261026001822",
      "share": 24,
      "showTime": "2026-04-15 21:50:26",
      "stockList": [
        "90.BK1601",
        "0.159891"
      ],
      "summary": "【太空医院要来了 全球首个太空医院照进现实】今天（15日），中国科学院微小卫星创新研究院自主研制的轻舟试验飞船正式发布了在轨半个月来的首批科学实验与工程试验成果，其中就包括很多涉及生命健康的前沿医疗项目，也让我们看到了未来太空医院的雏形。",
      "title": "太空医院要来了 全球首个太空医院照进现实",
      "titleColor": 0
    },
    "source": "东方财富快讯",
    "url": "https://kuaixun.eastmoney.com/news/202604153706301822.html",
    "category": "其他",
    "importance": 6,
    "sentiment": "neutral",
    "related_stocks": [
      "90.BK1601",
      "0.159891"
    ],
    "has_stock_mention": true,
    "comment_count": 28,
    "share_count": 24,
    "tags": {
      "industries": [],
      "concepts": [
        {
          "id": "C202",
          "name": "航天",
          "matched_keyword": "卫星"
        },
        {
          "id": "C304",
          "name": "医疗服务",
          "matched_keyword": "医院"
        }
      ],
      "industry_ids": [],
      "concept_ids": [
        "C202",
        "C304"
      ]
    }
  },
  {
    "id": "76bfb8a8298c8a29",
    "code": "202604153706300581",
    "title": "美股云计算服务商延续强势 甲骨文涨近5%",
    "summary": "【美股云计算服务商延续强势 甲骨文涨近5%】美股云计算服务商延续强势，ServiceNow涨超6%，甲骨文涨近5%，赛富时、Adobe涨超3%；Coreweave涨近3%，与量化交易巨头JaneStreet签署60亿美元AI云计算协议。",
    "content": "【美股云计算服务商延续强势 甲骨文涨近5%】美股云计算服务商延续强势，ServiceNow涨超6%，甲骨文涨近5%，赛富时、Adobe涨超3%；Coreweave涨近3%，与量化交易巨头JaneStreet签署60亿美元AI云计算协议。",
    "full_content": "【美股云计算服务商延续强势 甲骨文涨近5%】美股云计算服务商延续强势，ServiceNow涨超6%，甲骨文涨近5%，赛富时、Adobe涨超3%；Coreweave涨近3%，与量化交易巨头JaneStreet签署60亿美元AI云计算协议。",
    "sort_time": "1776260954000581",
    "showTime": "2026-04-15 21:49:14",
    "time": "2026-04-15 21:49:14",
    "publish_time": "2026-04-15 21:49:14",
    "raw_data": {
      "code": "202604153706300581",
      "image": [],
      "pinglun_Num": 13,
      "realSort": "1776260954000581",
      "share": 30,
      "showTime": "2026-04-15 21:49:14",
      "stockList": [
        "150.012322",
        "0.161628"
      ],
      "summary": "【美股云计算服务商延续强势 甲骨文涨近5%】美股云计算服务商延续强势，ServiceNow涨超6%，甲骨文涨近5%，赛富时、Adobe涨超3%；Coreweave涨近3%，与量化交易巨头JaneStreet签署60亿美元AI云计算协议。",
      "title": "美股云计算服务商延续强势 甲骨文涨近5%",
      "titleColor": 0
    },
    "source": "东方财富快讯",
    "url": "https://kuaixun.eastmoney.com/news/202604153706300581.html",
    "category": "科技",
    "importance": 6,
    "sentiment": "neutral",
    "related_stocks": [
      "150.012322",
      "0.161628"
    ],
    "has_stock_mention": true,
    "comment_count": 13,
    "share_count": 30,
    "tags": {
      "industries": [],
      "concepts": [
        {
          "id": "C001",
          "name": "人工智能",
          "matched_keyword": "AI"
        },
        {
          "id": "C005",
          "name": "云计算",
          "matched_keyword": "云计算"
        }
      ],
      "industry_ids": [],
      "concept_ids": [
        "C001",
        "C005"
      ]
    }
  },
  {
    "id": "c086a714e691ebc4",
    "code": "202604153706299218",
    "title": "ALLBIRDS股价飙升300%",
    "summary": "ALLBIRDS股价飙升300%。据财联社，公司转向人工智能基础设施领域。",
    "content": "ALLBIRDS股价飙升300%。据财联社，公司转向人工智能基础设施领域。",
    "full_content": "ALLBIRDS股价飙升300%。据财联社，公司转向人工智能基础设施领域。",
    "sort_time": "1776260898099218",
    "showTime": "2026-04-15 21:48:18",
    "time": "2026-04-15 21:48:18",
    "publish_time": "2026-04-15 21:48:18",
    "raw_data": {
      "code": "202604153706299218",
      "image": [],
      "pinglun_Num": 11,
      "realSort": "1776260898099218",
      "share": 15,
      "showTime": "2026-04-15 21:48:18",
      "stockList": [
        "0.161631",
        "1.515980"
      ],
      "summary": "ALLBIRDS股价飙升300%。据财联社，公司转向人工智能基础设施领域。",
      "title": "ALLBIRDS股价飙升300%",
      "titleColor": 0
    },
    "source": "东方财富快讯",
    "url": "https://kuaixun.eastmoney.com/news/202604153706299218.html",
    "category": "科技",
    "importance": 6,
    "sentiment": "neutral",
    "related_stocks": [
      "0.161631",
      "1.515980"
    ],
    "has_stock_mention": true,
    "comment_count": 11,
    "share_count": 15,
    "tags": {
      "industries": [],
      "concepts": [
        {
          "id": "C001",
          "name": "人工智能",
          "matched_keyword": "人工智能"
        }
      ],
      "industry_ids": [],
      "concept_ids": [
        "C001"
      ]
    }
  },
  {
    "id": "387ada810ea7ca91",
    "code": "202604153706297960",
    "title": "以色列称没有收到与黎巴嫩停火有关的决定或请求",
    "summary": "【以色列称没有收到与黎巴嫩停火有关的决定或请求】总台记者当地时间15日获悉，一名以色列官员表示，目前以色列没有收到与黎巴嫩停火有关的决定或请求。",
    "content": "【以色列称没有收到与黎巴嫩停火有关的决定或请求】总台记者当地时间15日获悉，一名以色列官员表示，目前以色列没有收到与黎巴嫩停火有关的决定或请求。",
    "full_content": "【以色列称没有收到与黎巴嫩停火有关的决定或请求】总台记者当地时间15日获悉，一名以色列官员表示，目前以色列没有收到与黎巴嫩停火有关的决定或请求。",
    "sort_time": "1776260759097960",
    "showTime": "2026-04-15 21:45:59",
    "time": "2026-04-15 21:45:59",
    "publish_time": "2026-04-15 21:45:59",
    "raw_data": {
      "code": "202604153706297960",
      "image": [],
      "pinglun_Num": 2,
      "realSort": "1776260759097960",
      "share": 2,
      "showTime": "2026-04-15 21:45:59",
      "stockList": [],
      "summary": "【以色列称没有收到与黎巴嫩停火有关的决定或请求】总台记者当地时间15日获悉，一名以色列官员表示，目前以色列没有收到与黎巴嫩停火有关的决定或请求。",
      "title": "以色列称没有收到与黎巴嫩停火有关的决定或请求",
      "titleColor": 0
    },
    "source": "东方财富快讯",
    "url": "https://kuaixun.eastmoney.com/news/202604153706297960.html",
    "category": "其他",
    "importance": 5,
    "sentiment": "neutral",
    "related_stocks": [],
    "has_stock_mention": false,
    "comment_count": 2,
    "share_count": 2,
    "tags": {
      "industries": [],
      "concepts": [],
      "industry_ids": [],
      "concept_ids": []
    }
  },
  {
    "id": "b522eacc513e968e",
    "code": "202604153706297569",
    "title": "韩媒：C-beauty来了 中国美妆品牌叩响韩妆主场大门",
    "summary": "【韩媒：C-beauty来了 中国美妆品牌叩响韩妆主场大门】《韩国先驱报》近日报道称，中国美妆品牌（C-beauty）已成为韩国美妆产业最受瞩目的挑战者，2025年中国化妆品对韩出口额暴涨84%，至7176万美元（约合4.9亿元人民币）。",
    "content": "【韩媒：C-beauty来了 中国美妆品牌叩响韩妆主场大门】《韩国先驱报》近日报道称，中国美妆品牌（C-beauty）已成为韩国美妆产业最受瞩目的挑战者，2025年中国化妆品对韩出口额暴涨84%，至7176万美元（约合4.9亿元人民币）。",
    "full_content": "【韩媒：C-beauty来了 中国美妆品牌叩响韩妆主场大门】《韩国先驱报》近日报道称，中国美妆品牌（C-beauty）已成为韩国美妆产业最受瞩目的挑战者，2025年中国化妆品对韩出口额暴涨84%，至7176万美元（约合4.9亿元人民币）。",
    "sort_time": "1776260715097569",
    "showTime": "2026-04-15 21:45:15",
    "time": "2026-04-15 21:45:15",
    "publish_time": "2026-04-15 21:45:15",
    "raw_data": {
      "code": "202604153706297569",
      "image": [],
      "pinglun_Num": 3,
      "realSort": "1776260715097569",
      "share": 2,
      "showTime": "2026-04-15 21:45:15",
      "stockList": [
        "90.BK1035"
      ],
      "summary": "【韩媒：C-beauty来了 中国美妆品牌叩响韩妆主场大门】《韩国先驱报》近日报道称，中国美妆品牌（C-beauty）已成为韩国美妆产业最受瞩目的挑战者，2025年中国化妆品对韩出口额暴涨84%，至7176万美元（约合4.9亿元人民币）。",
      "title": "韩媒：C-beauty来了 中国美妆品牌叩响韩妆主场大门",
      "titleColor": 0
    },
    "source": "东方财富快讯",
    "url": "https://kuaixun.eastmoney.com/news/202604153706297569.html",
    "category": "其他",
    "importance": 6,
    "sentiment": "neutral",
    "related_stocks": [
      "90.BK1035"
    ],
    "has_stock_mention": true,
    "comment_count": 3,
    "share_count": 2,
    "tags": {
      "industries": [],
      "concepts": [],
      "industry_ids": [],
      "concept_ids": []
    }
  },
  {
    "id": "2e5b2dc865e68a1d",
    "code": "202604153706298158",
    "title": "何小鹏重申“跳过L3”：最安全的路径是从L2直接到L4",
    "summary": "【何小鹏重申“跳过L3”：最安全的路径是从L2直接到L4】何小鹏认为，从安全角度看，最稳妥的路线就是直接从L2跨越到L4，并在这一过程中积累足够的数据，将安全置于首位，同时推动相关政策的完善。他进一步解释：“L4级别必须做到无人驾驶且确保安全。如果只能保障安全却无法实现无人驾驶，那本质上还是L2。”",
    "content": "【何小鹏重申“跳过L3”：最安全的路径是从L2直接到L4】何小鹏认为，从安全角度看，最稳妥的路线就是直接从L2跨越到L4，并在这一过程中积累足够的数据，将安全置于首位，同时推动相关政策的完善。他进一步解释：“L4级别必须做到无人驾驶且确保安全。如果只能保障安全却无法实现无人驾驶，那本质上还是L2。”",
    "full_content": "【何小鹏重申“跳过L3”：最安全的路径是从L2直接到L4】何小鹏认为，从安全角度看，最稳妥的路线就是直接从L2跨越到L4，并在这一过程中积累足够的数据，将安全置于首位，同时推动相关政策的完善。他进一步解释：“L4级别必须做到无人驾驶且确保安全。如果只能保障安全却无法实现无人驾驶，那本质上还是L2。”",
    "sort_time": "1776260643098158",
    "showTime": "2026-04-15 21:44:03",
    "time": "2026-04-15 21:44:03",
    "publish_time": "2026-04-15 21:44:03",
    "raw_data": {
      "code": "202604153706298158",
      "image": [],
      "pinglun_Num": 18,
      "realSort": "1776260643098158",
      "share": 4,
      "showTime": "2026-04-15 21:44:03",
      "stockList": [
        "116.09868",
        "106.XPEV"
      ],
      "summary": "【何小鹏重申“跳过L3”：最安全的路径是从L2直接到L4】何小鹏认为，从安全角度看，最稳妥的路线就是直接从L2跨越到L4，并在这一过程中积累足够的数据，将安全置于首位，同时推动相关政策的完善。他进一步解释：“L4级别必须做到无人驾驶且确保安全。如果只能保障安全却无法实现无人驾驶，那本质上还是L2。”",
      "title": "何小鹏重申“跳过L3”：最安全的路径是从L2直接到L4",
      "titleColor": 0
    },
    "source": "东方财富快讯",
    "url": "https://kuaixun.eastmoney.com/news/202604153706298158.html",
    "category": "政策",
    "importance": 6,
    "sentiment": "neutral",
    "related_stocks": [
      "116.09868",
      "106.XPEV"
    ],
    "has_stock_mention": true,
    "comment_count": 18,
    "share_count": 4,
    "tags": {
      "industries": [],
      "concepts": [],
      "industry_ids": [],
      "concept_ids": []
    }
  },
  {
    "id": "c538974317978813",
    "code": "202604153706296460",
    "title": "量子计算概念股持续走高 Arqit Quantum大涨近13%",
    "summary": "【量子计算概念股持续走高 Arqit Quantum大涨近13%】量子计算概念股持续走高，ArqitQuantum大涨近13%，IonQInc、SEALSQCorp、D-WaveQuantum涨超9%，QuantumComputing、RigettiComputing涨超6%。",
    "content": "【量子计算概念股持续走高 Arqit Quantum大涨近13%】量子计算概念股持续走高，ArqitQuantum大涨近13%，IonQInc、SEALSQCorp、D-WaveQuantum涨超9%，QuantumComputing、RigettiComputing涨超6%。",
    "full_content": "【量子计算概念股持续走高 Arqit Quantum大涨近13%】量子计算概念股持续走高，ArqitQuantum大涨近13%，IonQInc、SEALSQCorp、D-WaveQuantum涨超9%，QuantumComputing、RigettiComputing涨超6%。",
    "sort_time": "1776260524096460",
    "showTime": "2026-04-15 21:42:04",
    "time": "2026-04-15 21:42:04",
    "publish_time": "2026-04-15 21:42:04",
    "raw_data": {
      "code": "202604153706296460",
      "image": [],
      "pinglun_Num": 14,
      "realSort": "1776260524096460",
      "share": 12,
      "showTime": "2026-04-15 21:42:04",
      "stockList": [
        "90.BK0710",
        "105.ARQQ"
      ],
      "summary": "【量子计算概念股持续走高 Arqit Quantum大涨近13%】量子计算概念股持续走高，ArqitQuantum大涨近13%，IonQInc、SEALSQCorp、D-WaveQuantum涨超9%，QuantumComputing、RigettiComputing涨超6%。",
      "title": "量子计算概念股持续走高 Arqit Quantum大涨近13%",
      "titleColor": 0
    },
    "source": "东方财富快讯",
    "url": "https://kuaixun.eastmoney.com/news/202604153706296460.html",
    "category": "行业",
    "importance": 6,
    "sentiment": "neutral",
    "related_stocks": [
      "90.BK0710",
      "105.ARQQ"
    ],
    "has_stock_mention": true,
    "comment_count": 14,
    "share_count": 12,
    "tags": {
      "industries": [],
      "concepts": [],
      "industry_ids": [],
      "concept_ids": []
    }
  },
  {
    "id": "ffe01a7ac134dd96",
    "code": "202604153706276354",
    "title": "美股SaaS板块开盘走高 赛富时涨2.5%",
    "summary": "【美股SaaS板块开盘走高 赛富时涨2.5%】美股SaaS板块开盘走高。赛富时涨2.5%，Spotify涨1.8%，Adobe涨2.8%，ServiceNow涨4.3%。",
    "content": "【美股SaaS板块开盘走高 赛富时涨2.5%】美股SaaS板块开盘走高。赛富时涨2.5%，Spotify涨1.8%，Adobe涨2.8%，ServiceNow涨4.3%。",
    "full_content": "【美股SaaS板块开盘走高 赛富时涨2.5%】美股SaaS板块开盘走高。赛富时涨2.5%，Spotify涨1.8%，Adobe涨2.8%，ServiceNow涨4.3%。",
    "sort_time": "1776260215076354",
    "showTime": "2026-04-15 21:36:55",
    "time": "2026-04-15 21:36:55",
    "publish_time": "2026-04-15 21:36:55",
    "raw_data": {
      "code": "202604153706276354",
      "image": [],
      "pinglun_Num": 15,
      "realSort": "1776260215076354",
      "share": 1,
      "showTime": "2026-04-15 21:36:55",
      "stockList": [
        "106.CRM"
      ],
      "summary": "【美股SaaS板块开盘走高 赛富时涨2.5%】美股SaaS板块开盘走高。赛富时涨2.5%，Spotify涨1.8%，Adobe涨2.8%，ServiceNow涨4.3%。",
      "title": "美股SaaS板块开盘走高 赛富时涨2.5%",
      "titleColor": 0
    },
    "source": "东方财富快讯",
    "url": "https://kuaixun.eastmoney.com/news/202604153706276354.html",
    "category": "行业",
    "importance": 6,
    "sentiment": "neutral",
    "related_stocks": [
      "106.CRM"
    ],
    "has_stock_mention": true,
    "comment_count": 15,
    "share_count": 1,
    "tags": {
      "industries": [],
      "concepts": [
        {
          "id": "C005",
          "name": "云计算",
          "matched_keyword": "SaaS"
        }
      ],
      "industry_ids": [],
      "concept_ids": [
        "C005"
      ]
    }
  },
  {
    "id": "cf2253cc642b2fbc",
    "code": "202604153706269455",
    "title": "摩根士丹利股价涨超5%",
    "summary": "摩根士丹利股价涨超5%。",
    "content": "摩根士丹利股价涨超5%。",
    "full_content": "摩根士丹利股价涨超5%。",
    "sort_time": "1776260108069455",
    "showTime": "2026-04-15 21:35:08",
    "time": "2026-04-15 21:35:08",
    "publish_time": "2026-04-15 21:35:08",
    "raw_data": {
      "code": "202604153706269455",
      "image": [],
      "pinglun_Num": 4,
      "realSort": "1776260108069455",
      "share": 0,
      "showTime": "2026-04-15 21:35:08",
      "stockList": [
        "106.MS"
      ],
      "summary": "摩根士丹利股价涨超5%。",
      "title": "摩根士丹利股价涨超5%",
      "titleColor": 0
    },
    "source": "东方财富快讯",
    "url": "https://kuaixun.eastmoney.com/news/202604153706269455.html",
    "category": "其他",
    "importance": 6,
    "sentiment": "neutral",
    "related_stocks": [
      "106.MS"
    ],
    "has_stock_mention": true,
    "comment_count": 4,
    "share_count": 0,
    "tags": {
      "industries": [],
      "concepts": [],
      "industry_ids": [],
      "concept_ids": []
    }
  },
  {
    "id": "59d0e9ae62a56a29",
    "code": "202604153706267918",
    "title": "美股存储概念股开盘走低",
    "summary": "【美股存储概念股开盘走低】美股存储概念股开盘走低，闪迪跌超2%，希捷科技跌超2%，美光科技跌超1%，西部数据跌1%。",
    "content": "【美股存储概念股开盘走低】美股存储概念股开盘走低，闪迪跌超2%，希捷科技跌超2%，美光科技跌超1%，西部数据跌1%。",
    "full_content": "【美股存储概念股开盘走低】美股存储概念股开盘走低，闪迪跌超2%，希捷科技跌超2%，美光科技跌超1%，西部数据跌1%。",
    "sort_time": "1776260083067918",
    "showTime": "2026-04-15 21:34:43",
    "time": "2026-04-15 21:34:43",
    "publish_time": "2026-04-15 21:34:43",
    "raw_data": {
      "code": "202604153706267918",
      "image": [],
      "pinglun_Num": 4,
      "realSort": "1776260083067918",
      "share": 13,
      "showTime": "2026-04-15 21:34:43",
      "stockList": [],
      "summary": "【美股存储概念股开盘走低】美股存储概念股开盘走低，闪迪跌超2%，希捷科技跌超2%，美光科技跌超1%，西部数据跌1%。",
      "title": "美股存储概念股开盘走低",
      "titleColor": 0
    },
    "source": "东方财富快讯",
    "url": "https://kuaixun.eastmoney.com/news/202604153706267918.html",
    "category": "行业",
    "importance": 5,
    "sentiment": "neutral",
    "related_stocks": [],
    "has_stock_mention": false,
    "comment_count": 4,
    "share_count": 13,
    "tags": {
      "industries": [],
      "concepts": [],
      "industry_ids": [],
      "concept_ids": []
    }
  },
  {
    "id": "01ce7bfefacd03ec",
    "code": "202604153706266794",
    "title": "美国银行股价上涨3.8%",
    "summary": "美国银行股价上涨3.8%，创两个月来新高。",
    "content": "美国银行股价上涨3.8%，创两个月来新高。",
    "full_content": "美国银行股价上涨3.8%，创两个月来新高。",
    "sort_time": "1776260041066794",
    "showTime": "2026-04-15 21:34:01",
    "time": "2026-04-15 21:34:01",
    "publish_time": "2026-04-15 21:34:01",
    "raw_data": {
      "code": "202604153706266794",
      "image": [],
      "pinglun_Num": 2,
      "realSort": "1776260041066794",
      "share": 4,
      "showTime": "2026-04-15 21:34:01",
      "stockList": [
        "106.BAC"
      ],
      "summary": "美国银行股价上涨3.8%，创两个月来新高。",
      "title": "美国银行股价上涨3.8%",
      "titleColor": 0
    },
    "source": "东方财富快讯",
    "url": "https://kuaixun.eastmoney.com/news/202604153706266794.html",
    "category": "其他",
    "importance": 6,
    "sentiment": "bullish",
    "related_stocks": [
      "106.BAC"
    ],
    "has_stock_mention": true,
    "comment_count": 2,
    "share_count": 4,
    "tags": {
      "industries": [
        {
          "id": "I020101",
          "name": "银行",
          "level1": "金融业",
          "level2": "货币金融服务",
          "matched_keyword": "银行"
        }
      ],
      "concepts": [
        {
          "id": "C402",
          "name": "银行",
          "matched_keyword": "银行"
        }
      ],
      "industry_ids": [
        "I020101"
      ],
      "concept_ids": [
        "C402"
      ]
    }
  },
  {
    "id": "dd3a9c211d53321c",
    "code": "202604153706265585",
    "title": "美股三大指数小幅高开",
    "summary": "【美股三大指数小幅高开】美股三大指数小幅高开，道指涨0.31%，纳指涨0.18%，标普500指数涨0.15%。GitLab涨超4%，此前公司宣布与谷歌云达成合作。博通涨超2%，公司与Meta延长定制芯片合作协议。阿斯麦跌超3%，公司Q2展望略逊于市场预期。",
    "content": "【美股三大指数小幅高开】美股三大指数小幅高开，道指涨0.31%，纳指涨0.18%，标普500指数涨0.15%。GitLab涨超4%，此前公司宣布与谷歌云达成合作。博通涨超2%，公司与Meta延长定制芯片合作协议。阿斯麦跌超3%，公司Q2展望略逊于市场预期。",
    "full_content": "【美股三大指数小幅高开】美股三大指数小幅高开，道指涨0.31%，纳指涨0.18%，标普500指数涨0.15%。GitLab涨超4%，此前公司宣布与谷歌云达成合作。博通涨超2%，公司与Meta延长定制芯片合作协议。阿斯麦跌超3%，公司Q2展望略逊于市场预期。",
    "sort_time": "1776259942065585",
    "showTime": "2026-04-15 21:32:22",
    "time": "2026-04-15 21:32:22",
    "publish_time": "2026-04-15 21:32:22",
    "raw_data": {
      "code": "202604153706265585",
      "image": [],
      "pinglun_Num": 7,
      "realSort": "1776259942065585",
      "share": 5,
      "showTime": "2026-04-15 21:32:22",
      "stockList": [
        "150.159813",
        "150.013446"
      ],
      "summary": "【美股三大指数小幅高开】美股三大指数小幅高开，道指涨0.31%，纳指涨0.18%，标普500指数涨0.15%。GitLab涨超4%，此前公司宣布与谷歌云达成合作。博通涨超2%，公司与Meta延长定制芯片合作协议。阿斯麦跌超3%，公司Q2展望略逊于市场预期。",
      "title": "美股三大指数小幅高开",
      "titleColor": 0
    },
    "source": "东方财富快讯",
    "url": "https://kuaixun.eastmoney.com/news/202604153706265585.html",
    "category": "科技",
    "importance": 6,
    "sentiment": "neutral",
    "related_stocks": [
      "150.159813",
      "150.013446"
    ],
    "has_stock_mention": true,
    "comment_count": 7,
    "share_count": 5,
    "tags": {
      "industries": [
        {
          "id": "I010101",
          "name": "半导体",
          "level1": "制造业",
          "level2": "计算机、通信和其他电子设备制造业",
          "matched_keyword": "芯片"
        }
      ],
      "concepts": [
        {
          "id": "C002",
          "name": "芯片",
          "matched_keyword": "芯片"
        }
      ],
      "industry_ids": [
        "I010101"
      ],
      "concept_ids": [
        "C002"
      ]
    }
  },
  {
    "id": "2b86ccb5cd48a9b7",
    "code": "202604153706262936",
    "title": "豪迈科技：拟7.11亿元投建高端轮胎绿色硫化装备项目",
    "summary": "【豪迈科技：拟7.11亿元投建高端轮胎绿色硫化装备项目】豪迈科技(002595.SZ)公告称，公司全资子公司豪迈机械科技(日照)有限公司拟投资建设“高端轮胎绿色硫化装备及关键部件产业化项目”。项目总投资额预计7.11亿元。",
    "content": "【豪迈科技：拟7.11亿元投建高端轮胎绿色硫化装备项目】豪迈科技(002595.SZ)公告称，公司全资子公司豪迈机械科技(日照)有限公司拟投资建设“高端轮胎绿色硫化装备及关键部件产业化项目”。项目总投资额预计7.11亿元。",
    "full_content": "【豪迈科技：拟7.11亿元投建高端轮胎绿色硫化装备项目】豪迈科技(002595.SZ)公告称，公司全资子公司豪迈机械科技(日照)有限公司拟投资建设“高端轮胎绿色硫化装备及关键部件产业化项目”。项目总投资额预计7.11亿元。",
    "sort_time": "1776259648062936",
    "showTime": "2026-04-15 21:27:28",
    "time": "2026-04-15 21:27:28",
    "publish_time": "2026-04-15 21:27:28",
    "raw_data": {
      "code": "202604153706262936",
      "image": [],
      "pinglun_Num": 2,
      "realSort": "1776259648062936",
      "share": 3,
      "showTime": "2026-04-15 21:27:28",
      "stockList": [
        "90.BK1018",
        "0.002595"
      ],
      "summary": "【豪迈科技：拟7.11亿元投建高端轮胎绿色硫化装备项目】豪迈科技(002595.SZ)公告称，公司全资子公司豪迈机械科技(日照)有限公司拟投资建设“高端轮胎绿色硫化装备及关键部件产业化项目”。项目总投资额预计7.11亿元。",
      "title": "豪迈科技：拟7.11亿元投建高端轮胎绿色硫化装备项目",
      "titleColor": 0
    },
    "source": "东方财富快讯",
    "url": "https://kuaixun.eastmoney.com/news/202604153706262936.html",
    "category": "其他",
    "importance": 6,
    "sentiment": "neutral",
    "related_stocks": [
      "90.BK1018",
      "0.002595"
    ],
    "has_stock_mention": true,
    "comment_count": 2,
    "share_count": 3,
    "tags": {
      "industries": [
        {
          "id": "I010302",
          "name": "汽车零部件",
          "level1": "制造业",
          "level2": "汽车制造业",
          "matched_keyword": "轮胎"
        }
      ],
      "concepts": [],
      "industry_ids": [
        "I010302"
      ],
      "concept_ids": []
    }
  },
  {
    "id": "a6fdce0bc9c25880",
    "code": "202604153706262515",
    "title": "豪迈科技：拟投22.12亿元建设高端装备关键零部件研发及产业化项目",
    "summary": "【豪迈科技：拟投22.12亿元建设高端装备关键零部件研发及产业化项目】豪迈科技(002595.SZ)公告称，公司全资子公司豪迈机械科技(日照)有限公司拟投资建设“高端装备关键零部件研发及产业化项目”。项目总投资额预计22.12亿元。",
    "content": "【豪迈科技：拟投22.12亿元建设高端装备关键零部件研发及产业化项目】豪迈科技(002595.SZ)公告称，公司全资子公司豪迈机械科技(日照)有限公司拟投资建设“高端装备关键零部件研发及产业化项目”。项目总投资额预计22.12亿元。",
    "full_content": "【豪迈科技：拟投22.12亿元建设高端装备关键零部件研发及产业化项目】豪迈科技(002595.SZ)公告称，公司全资子公司豪迈机械科技(日照)有限公司拟投资建设“高端装备关键零部件研发及产业化项目”。项目总投资额预计22.12亿元。",
    "sort_time": "1776259641062515",
    "showTime": "2026-04-15 21:27:21",
    "time": "2026-04-15 21:27:21",
    "publish_time": "2026-04-15 21:27:21",
    "raw_data": {
      "code": "202604153706262515",
      "image": [],
      "pinglun_Num": 2,
      "realSort": "1776259641062515",
      "share": 3,
      "showTime": "2026-04-15 21:27:21",
      "stockList": [],
      "summary": "【豪迈科技：拟投22.12亿元建设高端装备关键零部件研发及产业化项目】豪迈科技(002595.SZ)公告称，公司全资子公司豪迈机械科技(日照)有限公司拟投资建设“高端装备关键零部件研发及产业化项目”。项目总投资额预计22.12亿元。",
      "title": "豪迈科技：拟投22.12亿元建设高端装备关键零部件研发及产业化项目",
      "titleColor": 0
    },
    "source": "东方财富快讯",
    "url": "https://kuaixun.eastmoney.com/news/202604153706262515.html",
    "category": "其他",
    "importance": 5,
    "sentiment": "neutral",
    "related_stocks": [],
    "has_stock_mention": false,
    "comment_count": 2,
    "share_count": 3,
    "tags": {
      "industries": [
        {
          "id": "I010302",
          "name": "汽车零部件",
          "level1": "制造业",
          "level2": "汽车制造业",
          "matched_keyword": "零部件"
        }
      ],
      "concepts": [],
      "industry_ids": [
        "I010302"
      ],
      "concept_ids": []
    }
  }
]