[
  {
    "id": "e98b8e22fe18e99b",
    "code": "202603153672418522",
    "title": "3·15晚会丨网红万元“万能神药”外泌体 竟然是“三无”产品",
    "summary": "【3·15晚会丨网红万元“万能神药”外泌体 竟然是“三无”产品】“外泌体这两年真的是非常火，被誉为抗衰界的宠儿。”这是近期医美市场上最为火爆的一类产品介绍，记者在多个医疗刊物和业内人士的介绍中了解到，视频里主播们宣讲的神奇物质“外泌体”，其实是一种在干细胞培养过程中分泌的生物活性物质。但这种物质在医疗界和学术界，其作用机理、临床测试等多项医学程序上，尚不能明确，更多还停留在学术研究和理论研究的阶段。",
    "content": "【3·15晚会丨网红万元“万能神药”外泌体 竟然是“三无”产品】“外泌体这两年真的是非常火，被誉为抗衰界的宠儿。”这是近期医美市场上最为火爆的一类产品介绍，记者在多个医疗刊物和业内人士的介绍中了解到，视频里主播们宣讲的神奇物质“外泌体”，其实是一种在干细胞培养过程中分泌的生物活性物质。但这种物质在医疗界和学术界，其作用机理、临床测试等多项医学程序上，尚不能明确，更多还停留在学术研究和理论研究的阶段。",
    "full_content": "【3·15晚会丨网红万元“万能神药”外泌体 竟然是“三无”产品】“外泌体这两年真的是非常火，被誉为抗衰界的宠儿。”这是近期医美市场上最为火爆的一类产品介绍，记者在多个医疗刊物和业内人士的介绍中了解到，视频里主播们宣讲的神奇物质“外泌体”，其实是一种在干细胞培养过程中分泌的生物活性物质。但这种物质在医疗界和学术界，其作用机理、临床测试等多项医学程序上，尚不能明确，更多还停留在学术研究和理论研究的阶段。",
    "sort_time": "1773577416018522",
    "showTime": "2026-03-15 20:23:36",
    "time": "2026-03-15 20:23:36",
    "publish_time": "2026-03-15 20:23:36",
    "raw_data": {
      "code": "202603153672418522",
      "image": [],
      "pinglun_Num": 0,
      "realSort": "1773577416018522",
      "share": 306,
      "showTime": "2026-03-15 20:23:36",
      "stockList": [
        "90.BK0465",
        "90.BK0727"
      ],
      "summary": "【3·15晚会丨网红万元“万能神药”外泌体 竟然是“三无”产品】“外泌体这两年真的是非常火，被誉为抗衰界的宠儿。”这是近期医美市场上最为火爆的一类产品介绍，记者在多个医疗刊物和业内人士的介绍中了解到，视频里主播们宣讲的神奇物质“外泌体”，其实是一种在干细胞培养过程中分泌的生物活性物质。但这种物质在医疗界和学术界，其作用机理、临床测试等多项医学程序上，尚不能明确，更多还停留在学术研究和理论研究的阶段。",
      "title": "3·15晚会丨网红万元“万能神药”外泌体 竟然是“三无”产品",
      "titleColor": 3
    },
    "source": "东方财富快讯",
    "url": "https://kuaixun.eastmoney.com/news/202603153672418522.html",
    "category": "其他",
    "importance": 6,
    "sentiment": "neutral",
    "related_stocks": [
      "90.BK0465",
      "90.BK0727"
    ],
    "has_stock_mention": true,
    "comment_count": 0,
    "share_count": 306,
    "tags": {
      "industries": [],
      "concepts": [],
      "industry_ids": [],
      "concept_ids": []
    }
  },
  {
    "id": "c64519d2a36d6e5e",
    "code": "202603153672418088",
    "title": "漂白鸡爪涉事公司曾巧食品曾被罚",
    "summary": "【漂白鸡爪涉事公司曾巧食品曾被罚】央视315晚会曝光漂白鸡爪的问题，乖媳妇鸡爪关联公司重庆市曾巧食品有限公司被点名。天眼查App显示，重庆市曾巧食品有限公司成立于2003年4月，法定代表人为曾巧，注册资本500万人民币，经营范围包括生产、销售：肉制品，豆制品，蔬菜制品等，由高家琴、曾巧共同持股。",
    "content": "【漂白鸡爪涉事公司曾巧食品曾被罚】央视315晚会曝光漂白鸡爪的问题，乖媳妇鸡爪关联公司重庆市曾巧食品有限公司被点名。天眼查App显示，重庆市曾巧食品有限公司成立于2003年4月，法定代表人为曾巧，注册资本500万人民币，经营范围包括生产、销售：肉制品，豆制品，蔬菜制品等，由高家琴、曾巧共同持股。",
    "full_content": "【漂白鸡爪涉事公司曾巧食品曾被罚】央视315晚会曝光漂白鸡爪的问题，乖媳妇鸡爪关联公司重庆市曾巧食品有限公司被点名。天眼查App显示，重庆市曾巧食品有限公司成立于2003年4月，法定代表人为曾巧，注册资本500万人民币，经营范围包括生产、销售：肉制品，豆制品，蔬菜制品等，由高家琴、曾巧共同持股。",
    "sort_time": "1773577291018088",
    "showTime": "2026-03-15 20:21:31",
    "time": "2026-03-15 20:21:31",
    "publish_time": "2026-03-15 20:21:31",
    "raw_data": {
      "code": "202603153672418088",
      "image": [],
      "pinglun_Num": 2,
      "realSort": "1773577291018088",
      "share": 4,
      "showTime": "2026-03-15 20:21:31",
      "stockList": [
        "150.012341"
      ],
      "summary": "【漂白鸡爪涉事公司曾巧食品曾被罚】央视315晚会曝光漂白鸡爪的问题，乖媳妇鸡爪关联公司重庆市曾巧食品有限公司被点名。天眼查App显示，重庆市曾巧食品有限公司成立于2003年4月，法定代表人为曾巧，注册资本500万人民币，经营范围包括生产、销售：肉制品，豆制品，蔬菜制品等，由高家琴、曾巧共同持股。",
      "title": "漂白鸡爪涉事公司曾巧食品曾被罚",
      "titleColor": 0
    },
    "source": "东方财富快讯",
    "url": "https://kuaixun.eastmoney.com/news/202603153672418088.html",
    "category": "其他",
    "importance": 6,
    "sentiment": "neutral",
    "related_stocks": [
      "150.012341"
    ],
    "has_stock_mention": true,
    "comment_count": 2,
    "share_count": 4,
    "tags": {
      "industries": [],
      "concepts": [
        {
          "id": "C602",
          "name": "食品饮料",
          "matched_keyword": "食品"
        }
      ],
      "industry_ids": [],
      "concept_ids": [
        "C602"
      ]
    }
  },
  {
    "id": "aa76fabfb8673c06",
    "code": "202603153672417918",
    "title": "以色列政府批准超8亿美元紧急预算拨款",
    "summary": "【以色列政府批准超8亿美元紧急预算拨款】总台记者当地时间15日自以色列方面获悉，以色列政府已批准一项约8.27亿美元的紧急预算拨款，用于军事采购。",
    "content": "【以色列政府批准超8亿美元紧急预算拨款】总台记者当地时间15日自以色列方面获悉，以色列政府已批准一项约8.27亿美元的紧急预算拨款，用于军事采购。",
    "full_content": "【以色列政府批准超8亿美元紧急预算拨款】总台记者当地时间15日自以色列方面获悉，以色列政府已批准一项约8.27亿美元的紧急预算拨款，用于军事采购。",
    "sort_time": "1773577286017918",
    "showTime": "2026-03-15 20:21:26",
    "time": "2026-03-15 20:21:26",
    "publish_time": "2026-03-15 20:21:26",
    "raw_data": {
      "code": "202603153672417918",
      "image": [],
      "pinglun_Num": 2,
      "realSort": "1773577286017918",
      "share": 0,
      "showTime": "2026-03-15 20:21:26",
      "stockList": [],
      "summary": "【以色列政府批准超8亿美元紧急预算拨款】总台记者当地时间15日自以色列方面获悉，以色列政府已批准一项约8.27亿美元的紧急预算拨款，用于军事采购。",
      "title": "以色列政府批准超8亿美元紧急预算拨款",
      "titleColor": 0
    },
    "source": "东方财富快讯",
    "url": "https://kuaixun.eastmoney.com/news/202603153672417918.html",
    "category": "其他",
    "importance": 5,
    "sentiment": "neutral",
    "related_stocks": [],
    "has_stock_mention": false,
    "comment_count": 2,
    "share_count": 0,
    "tags": {
      "industries": [],
      "concepts": [],
      "industry_ids": [],
      "concept_ids": []
    }
  },
  {
    "id": "7c1712e4bef5d16f",
    "code": "202603153672417861",
    "title": "3月15日周日《新闻联播》要闻19条",
    "summary": "3月15日周日《新闻联播》要闻19条。",
    "content": "3月15日周日《新闻联播》要闻19条。",
    "full_content": "3月15日周日《新闻联播》要闻19条。",
    "sort_time": "1773577200017861",
    "showTime": "2026-03-15 20:20:00",
    "time": "2026-03-15 20:20:00",
    "publish_time": "2026-03-15 20:20:00",
    "raw_data": {
      "code": "202603153672417861",
      "image": [],
      "pinglun_Num": 0,
      "realSort": "1773577200017861",
      "share": 0,
      "showTime": "2026-03-15 20:20:00",
      "stockList": [],
      "summary": "3月15日周日《新闻联播》要闻19条。",
      "title": "3月15日周日《新闻联播》要闻19条",
      "titleColor": 0
    },
    "source": "东方财富快讯",
    "url": "https://kuaixun.eastmoney.com/news/202603153672417861.html",
    "category": "其他",
    "importance": 5,
    "sentiment": "neutral",
    "related_stocks": [],
    "has_stock_mention": false,
    "comment_count": 0,
    "share_count": 0,
    "tags": {
      "industries": [],
      "concepts": [],
      "industry_ids": [],
      "concept_ids": []
    }
  },
  {
    "id": "b7e816d807a3b289",
    "code": "202603153672417780",
    "title": "315曝光的漂白鸡爪涉事公司曾被罚",
    "summary": "【315曝光的漂白鸡爪涉事公司曾被罚】今年央视315晚会曝光“漂白的鸡爪”，四川省蜀福香食品有限责任公司被点名，企查查APP显示，该公司成立于1997年12月，注册资本2380万元，经营范围包括：食品生产；食品销售；餐饮服务；城市配送运输服务等，由成都市众兴食品有限公司、四川省荣盛泰集团有限责任公司共同持股。",
    "content": "【315曝光的漂白鸡爪涉事公司曾被罚】今年央视315晚会曝光“漂白的鸡爪”，四川省蜀福香食品有限责任公司被点名，企查查APP显示，该公司成立于1997年12月，注册资本2380万元，经营范围包括：食品生产；食品销售；餐饮服务；城市配送运输服务等，由成都市众兴食品有限公司、四川省荣盛泰集团有限责任公司共同持股。",
    "full_content": "【315曝光的漂白鸡爪涉事公司曾被罚】今年央视315晚会曝光“漂白的鸡爪”，四川省蜀福香食品有限责任公司被点名，企查查APP显示，该公司成立于1997年12月，注册资本2380万元，经营范围包括：食品生产；食品销售；餐饮服务；城市配送运输服务等，由成都市众兴食品有限公司、四川省荣盛泰集团有限责任公司共同持股。",
    "sort_time": "1773577156017780",
    "showTime": "2026-03-15 20:19:16",
    "time": "2026-03-15 20:19:16",
    "publish_time": "2026-03-15 20:19:16",
    "raw_data": {
      "code": "202603153672417780",
      "image": [],
      "pinglun_Num": 1,
      "realSort": "1773577156017780",
      "share": 1,
      "showTime": "2026-03-15 20:19:16",
      "stockList": [
        "150.012341"
      ],
      "summary": "【315曝光的漂白鸡爪涉事公司曾被罚】今年央视315晚会曝光“漂白的鸡爪”，四川省蜀福香食品有限责任公司被点名，企查查APP显示，该公司成立于1997年12月，注册资本2380万元，经营范围包括：食品生产；食品销售；餐饮服务；城市配送运输服务等，由成都市众兴食品有限公司、四川省荣盛泰集团有限责任公司共同持股。",
      "title": "315曝光的漂白鸡爪涉事公司曾被罚",
      "titleColor": 0
    },
    "source": "东方财富快讯",
    "url": "https://kuaixun.eastmoney.com/news/202603153672417780.html",
    "category": "其他",
    "importance": 6,
    "sentiment": "neutral",
    "related_stocks": [
      "150.012341"
    ],
    "has_stock_mention": true,
    "comment_count": 1,
    "share_count": 1,
    "tags": {
      "industries": [],
      "concepts": [
        {
          "id": "C602",
          "name": "食品饮料",
          "matched_keyword": "食品"
        }
      ],
      "industry_ids": [],
      "concept_ids": [
        "C602"
      ]
    }
  },
  {
    "id": "1183bc559160f067",
    "code": "202603153672417431",
    "title": "漂白鸡爪涉事公司已获食品安全管理体系认证",
    "summary": "【漂白鸡爪涉事公司已获食品安全管理体系认证】央视315晚会曝光漂白鸡爪的问题，四川省蜀福香食品有限责任公司被点名。天眼查App显示，四川省蜀福香食品有限责任公司成立于1997年12月，法定代表人为王立群，注册资本2380万人民币，经营范围包括食品生产、食品销售、餐饮服务等，由成都市众兴食品有限公司、四川省荣盛泰集团有限责任公司共同持股。经营信息显示，已获得质量管理体系认证。",
    "content": "【漂白鸡爪涉事公司已获食品安全管理体系认证】央视315晚会曝光漂白鸡爪的问题，四川省蜀福香食品有限责任公司被点名。天眼查App显示，四川省蜀福香食品有限责任公司成立于1997年12月，法定代表人为王立群，注册资本2380万人民币，经营范围包括食品生产、食品销售、餐饮服务等，由成都市众兴食品有限公司、四川省荣盛泰集团有限责任公司共同持股。经营信息显示，已获得质量管理体系认证。",
    "full_content": "【漂白鸡爪涉事公司已获食品安全管理体系认证】央视315晚会曝光漂白鸡爪的问题，四川省蜀福香食品有限责任公司被点名。天眼查App显示，四川省蜀福香食品有限责任公司成立于1997年12月，法定代表人为王立群，注册资本2380万人民币，经营范围包括食品生产、食品销售、餐饮服务等，由成都市众兴食品有限公司、四川省荣盛泰集团有限责任公司共同持股。经营信息显示，已获得质量管理体系认证。",
    "sort_time": "1773576891017431",
    "showTime": "2026-03-15 20:14:51",
    "time": "2026-03-15 20:14:51",
    "publish_time": "2026-03-15 20:14:51",
    "raw_data": {
      "code": "202603153672417431",
      "image": [],
      "pinglun_Num": 12,
      "realSort": "1773576891017431",
      "share": 7,
      "showTime": "2026-03-15 20:14:51",
      "stockList": [
        "90.BK0614",
        "150.012341"
      ],
      "summary": "【漂白鸡爪涉事公司已获食品安全管理体系认证】央视315晚会曝光漂白鸡爪的问题，四川省蜀福香食品有限责任公司被点名。天眼查App显示，四川省蜀福香食品有限责任公司成立于1997年12月，法定代表人为王立群，注册资本2380万人民币，经营范围包括食品生产、食品销售、餐饮服务等，由成都市众兴食品有限公司、四川省荣盛泰集团有限责任公司共同持股。经营信息显示，已获得质量管理体系认证。",
      "title": "漂白鸡爪涉事公司已获食品安全管理体系认证",
      "titleColor": 0
    },
    "source": "东方财富快讯",
    "url": "https://kuaixun.eastmoney.com/news/202603153672417431.html",
    "category": "其他",
    "importance": 6,
    "sentiment": "neutral",
    "related_stocks": [
      "90.BK0614",
      "150.012341"
    ],
    "has_stock_mention": true,
    "comment_count": 12,
    "share_count": 7,
    "tags": {
      "industries": [],
      "concepts": [
        {
          "id": "C602",
          "name": "食品饮料",
          "matched_keyword": "食品"
        }
      ],
      "industry_ids": [],
      "concept_ids": [
        "C602"
      ]
    }
  },
  {
    "id": "70f98b2a251edebe",
    "code": "202603153672417250",
    "title": "漂白鸡爪被查封 漂白鸡爪企业买了超5000桶过氧化氢",
    "summary": "【漂白鸡爪被查封 漂白鸡爪企业买了超5000桶过氧化氢】315晚会曝光漂白鸡爪。经过调查取证，3月初，315晚会记者将调查素材移交国家市场监督管理总局。国家市场监督管理总局立即组织多司局研判线索，针对顶风作案的涉事商户和企业，近日调动多地执法力量，分成几路对这条食品加工黑色产业链展开全面收网行动，对蜀福香、明扬食品、曾巧食品及上游相关企业开展突击检查。",
    "content": "【漂白鸡爪被查封 漂白鸡爪企业买了超5000桶过氧化氢】315晚会曝光漂白鸡爪。经过调查取证，3月初，315晚会记者将调查素材移交国家市场监督管理总局。国家市场监督管理总局立即组织多司局研判线索，针对顶风作案的涉事商户和企业，近日调动多地执法力量，分成几路对这条食品加工黑色产业链展开全面收网行动，对蜀福香、明扬食品、曾巧食品及上游相关企业开展突击检查。",
    "full_content": "【漂白鸡爪被查封 漂白鸡爪企业买了超5000桶过氧化氢】315晚会曝光漂白鸡爪。经过调查取证，3月初，315晚会记者将调查素材移交国家市场监督管理总局。国家市场监督管理总局立即组织多司局研判线索，针对顶风作案的涉事商户和企业，近日调动多地执法力量，分成几路对这条食品加工黑色产业链展开全面收网行动，对蜀福香、明扬食品、曾巧食品及上游相关企业开展突击检查。",
    "sort_time": "1773576755017250",
    "showTime": "2026-03-15 20:12:35",
    "time": "2026-03-15 20:12:35",
    "publish_time": "2026-03-15 20:12:35",
    "raw_data": {
      "code": "202603153672417250",
      "image": [],
      "pinglun_Num": 9,
      "realSort": "1773576755017250",
      "share": 30,
      "showTime": "2026-03-15 20:12:35",
      "stockList": [
        "150.012341"
      ],
      "summary": "【漂白鸡爪被查封 漂白鸡爪企业买了超5000桶过氧化氢】315晚会曝光漂白鸡爪。经过调查取证，3月初，315晚会记者将调查素材移交国家市场监督管理总局。国家市场监督管理总局立即组织多司局研判线索，针对顶风作案的涉事商户和企业，近日调动多地执法力量，分成几路对这条食品加工黑色产业链展开全面收网行动，对蜀福香、明扬食品、曾巧食品及上游相关企业开展突击检查。",
      "title": "漂白鸡爪被查封 漂白鸡爪企业买了超5000桶过氧化氢",
      "titleColor": 0
    },
    "source": "东方财富快讯",
    "url": "https://kuaixun.eastmoney.com/news/202603153672417250.html",
    "category": "其他",
    "importance": 6,
    "sentiment": "neutral",
    "related_stocks": [
      "150.012341"
    ],
    "has_stock_mention": true,
    "comment_count": 9,
    "share_count": 30,
    "tags": {
      "industries": [],
      "concepts": [
        {
          "id": "C602",
          "name": "食品饮料",
          "matched_keyword": "食品"
        }
      ],
      "industry_ids": [],
      "concept_ids": [
        "C602"
      ]
    }
  },
  {
    "id": "23b1680822eb071a",
    "code": "202603153672417028",
    "title": "3·15晚会丨曝光黑心“漂白鸡爪”！生产车间令人作呕！有毒的双氧水随便用！",
    "summary": "【3·15晚会丨曝光黑心“漂白鸡爪”！生产车间令人作呕！有毒的双氧水随便用！】“3·15”晚会的记者在鸡爪火爆销售的川渝地区展开调查。在未办理健康证、未做任何健康体检、未经过任何卫生消毒的情况下，记者很轻松地进入成都市明扬食品生产车间，这里正是为蜀福香食品有限责任公司鸡爪产品进行前期加工的场所。",
    "content": "【3·15晚会丨曝光黑心“漂白鸡爪”！生产车间令人作呕！有毒的双氧水随便用！】“3·15”晚会的记者在鸡爪火爆销售的川渝地区展开调查。在未办理健康证、未做任何健康体检、未经过任何卫生消毒的情况下，记者很轻松地进入成都市明扬食品生产车间，这里正是为蜀福香食品有限责任公司鸡爪产品进行前期加工的场所。",
    "full_content": "【3·15晚会丨曝光黑心“漂白鸡爪”！生产车间令人作呕！有毒的双氧水随便用！】“3·15”晚会的记者在鸡爪火爆销售的川渝地区展开调查。在未办理健康证、未做任何健康体检、未经过任何卫生消毒的情况下，记者很轻松地进入成都市明扬食品生产车间，这里正是为蜀福香食品有限责任公司鸡爪产品进行前期加工的场所。",
    "sort_time": "1773576515017028",
    "showTime": "2026-03-15 20:08:35",
    "time": "2026-03-15 20:08:35",
    "publish_time": "2026-03-15 20:08:35",
    "raw_data": {
      "code": "202603153672417028",
      "image": [],
      "pinglun_Num": 64,
      "realSort": "1773576515017028",
      "share": 1292,
      "showTime": "2026-03-15 20:08:35",
      "stockList": [
        "90.BK0438",
        "90.BK0614"
      ],
      "summary": "【3·15晚会丨曝光黑心“漂白鸡爪”！生产车间令人作呕！有毒的双氧水随便用！】“3·15”晚会的记者在鸡爪火爆销售的川渝地区展开调查。在未办理健康证、未做任何健康体检、未经过任何卫生消毒的情况下，记者很轻松地进入成都市明扬食品生产车间，这里正是为蜀福香食品有限责任公司鸡爪产品进行前期加工的场所。",
      "title": "3·15晚会丨曝光黑心“漂白鸡爪”！生产车间令人作呕！有毒的双氧水随便用！",
      "titleColor": 3
    },
    "source": "东方财富快讯",
    "url": "https://kuaixun.eastmoney.com/news/202603153672417028.html",
    "category": "其他",
    "importance": 6,
    "sentiment": "neutral",
    "related_stocks": [
      "90.BK0438",
      "90.BK0614"
    ],
    "has_stock_mention": true,
    "comment_count": 64,
    "share_count": 1292,
    "tags": {
      "industries": [],
      "concepts": [
        {
          "id": "C602",
          "name": "食品饮料",
          "matched_keyword": "食品"
        }
      ],
      "industry_ids": [],
      "concept_ids": [
        "C602"
      ]
    }
  },
  {
    "id": "161760b24c2aa478",
    "code": "202603153672417123",
    "title": "黄天鹅鸡蛋否认添加角黄素",
    "summary": "【黄天鹅鸡蛋否认添加角黄素】3月15日晚，凤集食品集团有限公司发布声明称，黄天鹅鸡蛋不添加人工合成色素。黄天鹅鸡蛋中检出的角黄素含量仅为0.399mg/kg，远低于其他检测值，该数值属于鸡蛋可能含有天然角黄素本底水平，并非人工添加。",
    "content": "【黄天鹅鸡蛋否认添加角黄素】3月15日晚，凤集食品集团有限公司发布声明称，黄天鹅鸡蛋不添加人工合成色素。黄天鹅鸡蛋中检出的角黄素含量仅为0.399mg/kg，远低于其他检测值，该数值属于鸡蛋可能含有天然角黄素本底水平，并非人工添加。",
    "full_content": "【黄天鹅鸡蛋否认添加角黄素】3月15日晚，凤集食品集团有限公司发布声明称，黄天鹅鸡蛋不添加人工合成色素。黄天鹅鸡蛋中检出的角黄素含量仅为0.399mg/kg，远低于其他检测值，该数值属于鸡蛋可能含有天然角黄素本底水平，并非人工添加。",
    "sort_time": "1773576511017123",
    "showTime": "2026-03-15 20:08:31",
    "time": "2026-03-15 20:08:31",
    "publish_time": "2026-03-15 20:08:31",
    "raw_data": {
      "code": "202603153672417123",
      "image": [],
      "pinglun_Num": 0,
      "realSort": "1773576511017123",
      "share": 15,
      "showTime": "2026-03-15 20:08:31",
      "stockList": [],
      "summary": "【黄天鹅鸡蛋否认添加角黄素】3月15日晚，凤集食品集团有限公司发布声明称，黄天鹅鸡蛋不添加人工合成色素。黄天鹅鸡蛋中检出的角黄素含量仅为0.399mg/kg，远低于其他检测值，该数值属于鸡蛋可能含有天然角黄素本底水平，并非人工添加。",
      "title": "黄天鹅鸡蛋否认添加角黄素",
      "titleColor": 0
    },
    "source": "东方财富快讯",
    "url": "https://kuaixun.eastmoney.com/news/202603153672417123.html",
    "category": "其他",
    "importance": 5,
    "sentiment": "neutral",
    "related_stocks": [],
    "has_stock_mention": false,
    "comment_count": 0,
    "share_count": 15,
    "tags": {
      "industries": [],
      "concepts": [
        {
          "id": "C602",
          "name": "食品饮料",
          "matched_keyword": "食品"
        }
      ],
      "industry_ids": [],
      "concept_ids": [
        "C602"
      ]
    }
  },
  {
    "id": "170303187f0e6593",
    "code": "202603153672416925",
    "title": "以色列外长称以美决心作战直至“目标实现”",
    "summary": "【以色列外长称以美决心作战直至“目标实现”】以色列外交部长萨尔15日说，以色列和美国有着共同的决心，“将继续与伊朗作战，直到我们的目标实现为止”。",
    "content": "【以色列外长称以美决心作战直至“目标实现”】以色列外交部长萨尔15日说，以色列和美国有着共同的决心，“将继续与伊朗作战，直到我们的目标实现为止”。",
    "full_content": "【以色列外长称以美决心作战直至“目标实现”】以色列外交部长萨尔15日说，以色列和美国有着共同的决心，“将继续与伊朗作战，直到我们的目标实现为止”。",
    "sort_time": "1773576259016925",
    "showTime": "2026-03-15 20:04:19",
    "time": "2026-03-15 20:04:19",
    "publish_time": "2026-03-15 20:04:19",
    "raw_data": {
      "code": "202603153672416925",
      "image": [],
      "pinglun_Num": 15,
      "realSort": "1773576259016925",
      "share": 4,
      "showTime": "2026-03-15 20:04:19",
      "stockList": [],
      "summary": "【以色列外长称以美决心作战直至“目标实现”】以色列外交部长萨尔15日说，以色列和美国有着共同的决心，“将继续与伊朗作战，直到我们的目标实现为止”。",
      "title": "以色列外长称以美决心作战直至“目标实现”",
      "titleColor": 0
    },
    "source": "东方财富快讯",
    "url": "https://kuaixun.eastmoney.com/news/202603153672416925.html",
    "category": "其他",
    "importance": 5,
    "sentiment": "neutral",
    "related_stocks": [],
    "has_stock_mention": false,
    "comment_count": 15,
    "share_count": 4,
    "tags": {
      "industries": [],
      "concepts": [],
      "industry_ids": [],
      "concept_ids": []
    }
  },
  {
    "id": "3df003cf99c4d367",
    "code": "202603153672416773",
    "title": "央视315晚会重磅来袭！一起来看看今年曝光哪些问题",
    "summary": "2026年央视“3·15”晚会开播，节目预告内容涉及漂白的鸡爪、“万能”的外泌体、增高营销的套路等问题。",
    "content": "2026年央视“3·15”晚会开播，节目预告内容涉及漂白的鸡爪、“万能”的外泌体、增高营销的套路等问题。",
    "full_content": "2026年央视“3·15”晚会开播，节目预告内容涉及漂白的鸡爪、“万能”的外泌体、增高营销的套路等问题。",
    "sort_time": "1773576233016773",
    "showTime": "2026-03-15 20:03:53",
    "time": "2026-03-15 20:03:53",
    "publish_time": "2026-03-15 20:03:53",
    "raw_data": {
      "code": "202603153672416773",
      "image": [],
      "pinglun_Num": 96,
      "realSort": "1773576233016773",
      "share": 317,
      "showTime": "2026-03-15 20:03:53",
      "stockList": [
        "90.BK0465",
        "150.012341"
      ],
      "summary": "2026年央视“3·15”晚会开播，节目预告内容涉及漂白的鸡爪、“万能”的外泌体、增高营销的套路等问题。",
      "title": "央视315晚会重磅来袭！一起来看看今年曝光哪些问题",
      "titleColor": 3
    },
    "source": "东方财富快讯",
    "url": "https://kuaixun.eastmoney.com/news/202603153672416773.html",
    "category": "其他",
    "importance": 6,
    "sentiment": "neutral",
    "related_stocks": [
      "90.BK0465",
      "150.012341"
    ],
    "has_stock_mention": true,
    "comment_count": 96,
    "share_count": 317,
    "tags": {
      "industries": [],
      "concepts": [],
      "industry_ids": [],
      "concept_ids": []
    }
  },
  {
    "id": "6c44b9c36c80a3ac",
    "code": "202603153672416358",
    "title": "伊朗外长：地区不安全源于“美以侵略”",
    "summary": "【伊朗外长：地区不安全源于“美以侵略”】伊朗外交部15日发表声明说，伊朗外长阿拉格齐表示，霍尔木兹海峡及整个地区的不安全原因在于“美国和以色列的侵略行为”，伊朗的防御行动不应被视为对地区其他国家的攻击。",
    "content": "【伊朗外长：地区不安全源于“美以侵略”】伊朗外交部15日发表声明说，伊朗外长阿拉格齐表示，霍尔木兹海峡及整个地区的不安全原因在于“美国和以色列的侵略行为”，伊朗的防御行动不应被视为对地区其他国家的攻击。",
    "full_content": "【伊朗外长：地区不安全源于“美以侵略”】伊朗外交部15日发表声明说，伊朗外长阿拉格齐表示，霍尔木兹海峡及整个地区的不安全原因在于“美国和以色列的侵略行为”，伊朗的防御行动不应被视为对地区其他国家的攻击。",
    "sort_time": "1773575947016358",
    "showTime": "2026-03-15 19:59:07",
    "time": "2026-03-15 19:59:07",
    "publish_time": "2026-03-15 19:59:07",
    "raw_data": {
      "code": "202603153672416358",
      "image": [],
      "pinglun_Num": 7,
      "realSort": "1773575947016358",
      "share": 3,
      "showTime": "2026-03-15 19:59:07",
      "stockList": [],
      "summary": "【伊朗外长：地区不安全源于“美以侵略”】伊朗外交部15日发表声明说，伊朗外长阿拉格齐表示，霍尔木兹海峡及整个地区的不安全原因在于“美国和以色列的侵略行为”，伊朗的防御行动不应被视为对地区其他国家的攻击。",
      "title": "伊朗外长：地区不安全源于“美以侵略”",
      "titleColor": 0
    },
    "source": "东方财富快讯",
    "url": "https://kuaixun.eastmoney.com/news/202603153672416358.html",
    "category": "其他",
    "importance": 5,
    "sentiment": "neutral",
    "related_stocks": [],
    "has_stock_mention": false,
    "comment_count": 7,
    "share_count": 3,
    "tags": {
      "industries": [],
      "concepts": [],
      "industry_ids": [],
      "concept_ids": []
    }
  },
  {
    "id": "755fefa24da62ba9",
    "code": "202603153672416238",
    "title": "美议员：美政府严重误判伊朗能力 已失去对战争的控制",
    "summary": "【美议员：美政府严重误判伊朗能力 已失去对战争的控制】美国民主党籍参议员克里斯·墨菲当地时间3月14日在社交媒体上发文表示，美国政府严重误判了伊朗的能力，已经失去对伊朗军事行动的控制，并且目前美国政府还没有结束战争的计划。",
    "content": "【美议员：美政府严重误判伊朗能力 已失去对战争的控制】美国民主党籍参议员克里斯·墨菲当地时间3月14日在社交媒体上发文表示，美国政府严重误判了伊朗的能力，已经失去对伊朗军事行动的控制，并且目前美国政府还没有结束战争的计划。",
    "full_content": "【美议员：美政府严重误判伊朗能力 已失去对战争的控制】美国民主党籍参议员克里斯·墨菲当地时间3月14日在社交媒体上发文表示，美国政府严重误判了伊朗的能力，已经失去对伊朗军事行动的控制，并且目前美国政府还没有结束战争的计划。",
    "sort_time": "1773575891016238",
    "showTime": "2026-03-15 19:58:11",
    "time": "2026-03-15 19:58:11",
    "publish_time": "2026-03-15 19:58:11",
    "raw_data": {
      "code": "202603153672416238",
      "image": [],
      "pinglun_Num": 4,
      "realSort": "1773575891016238",
      "share": 7,
      "showTime": "2026-03-15 19:58:11",
      "stockList": [],
      "summary": "【美议员：美政府严重误判伊朗能力 已失去对战争的控制】美国民主党籍参议员克里斯·墨菲当地时间3月14日在社交媒体上发文表示，美国政府严重误判了伊朗的能力，已经失去对伊朗军事行动的控制，并且目前美国政府还没有结束战争的计划。",
      "title": "美议员：美政府严重误判伊朗能力 已失去对战争的控制",
      "titleColor": 0
    },
    "source": "东方财富快讯",
    "url": "https://kuaixun.eastmoney.com/news/202603153672416238.html",
    "category": "其他",
    "importance": 5,
    "sentiment": "neutral",
    "related_stocks": [],
    "has_stock_mention": false,
    "comment_count": 4,
    "share_count": 7,
    "tags": {
      "industries": [],
      "concepts": [],
      "industry_ids": [],
      "concept_ids": []
    }
  },
  {
    "id": "62fca758a82317f1",
    "code": "202603153672416053",
    "title": "泽连斯基：不知何时举行新一轮乌美俄三方会谈",
    "summary": "【泽连斯基：不知何时举行新一轮乌美俄三方会谈】据乌克兰国家通讯社15日报道，乌克兰总统泽连斯基14日说，目前尚不清楚被推迟的乌美俄三方会谈何时重启。",
    "content": "【泽连斯基：不知何时举行新一轮乌美俄三方会谈】据乌克兰国家通讯社15日报道，乌克兰总统泽连斯基14日说，目前尚不清楚被推迟的乌美俄三方会谈何时重启。",
    "full_content": "【泽连斯基：不知何时举行新一轮乌美俄三方会谈】据乌克兰国家通讯社15日报道，乌克兰总统泽连斯基14日说，目前尚不清楚被推迟的乌美俄三方会谈何时重启。",
    "sort_time": "1773575840016053",
    "showTime": "2026-03-15 19:57:20",
    "time": "2026-03-15 19:57:20",
    "publish_time": "2026-03-15 19:57:20",
    "raw_data": {
      "code": "202603153672416053",
      "image": [],
      "pinglun_Num": 1,
      "realSort": "1773575840016053",
      "share": 0,
      "showTime": "2026-03-15 19:57:20",
      "stockList": [],
      "summary": "【泽连斯基：不知何时举行新一轮乌美俄三方会谈】据乌克兰国家通讯社15日报道，乌克兰总统泽连斯基14日说，目前尚不清楚被推迟的乌美俄三方会谈何时重启。",
      "title": "泽连斯基：不知何时举行新一轮乌美俄三方会谈",
      "titleColor": 0
    },
    "source": "东方财富快讯",
    "url": "https://kuaixun.eastmoney.com/news/202603153672416053.html",
    "category": "其他",
    "importance": 5,
    "sentiment": "neutral",
    "related_stocks": [],
    "has_stock_mention": false,
    "comment_count": 1,
    "share_count": 0,
    "tags": {
      "industries": [],
      "concepts": [],
      "industry_ids": [],
      "concept_ids": []
    }
  },
  {
    "id": "195303654db8c55a",
    "code": "202603153672414593",
    "title": "伊朗导弹碎片击中美国驻以色列领事官邸建筑",
    "summary": "【伊朗导弹碎片击中美国驻以色列领事官邸建筑】总台记者当地时间15日自以色列方面获悉，伊朗导弹的碎片击中美国驻以色列领事官邸建筑。",
    "content": "【伊朗导弹碎片击中美国驻以色列领事官邸建筑】总台记者当地时间15日自以色列方面获悉，伊朗导弹的碎片击中美国驻以色列领事官邸建筑。",
    "full_content": "【伊朗导弹碎片击中美国驻以色列领事官邸建筑】总台记者当地时间15日自以色列方面获悉，伊朗导弹的碎片击中美国驻以色列领事官邸建筑。",
    "sort_time": "1773575253014593",
    "showTime": "2026-03-15 19:47:33",
    "time": "2026-03-15 19:47:33",
    "publish_time": "2026-03-15 19:47:33",
    "raw_data": {
      "code": "202603153672414593",
      "image": [],
      "pinglun_Num": 3,
      "realSort": "1773575253014593",
      "share": 3,
      "showTime": "2026-03-15 19:47:33",
      "stockList": [],
      "summary": "【伊朗导弹碎片击中美国驻以色列领事官邸建筑】总台记者当地时间15日自以色列方面获悉，伊朗导弹的碎片击中美国驻以色列领事官邸建筑。",
      "title": "伊朗导弹碎片击中美国驻以色列领事官邸建筑",
      "titleColor": 0
    },
    "source": "东方财富快讯",
    "url": "https://kuaixun.eastmoney.com/news/202603153672414593.html",
    "category": "其他",
    "importance": 5,
    "sentiment": "neutral",
    "related_stocks": [],
    "has_stock_mention": false,
    "comment_count": 3,
    "share_count": 3,
    "tags": {
      "industries": [],
      "concepts": [],
      "industry_ids": [],
      "concept_ids": []
    }
  },
  {
    "id": "73162c880118024f",
    "code": "202603153672414360",
    "title": "中银证券：化工板块迎来配置窗口",
    "summary": "【中银证券：化工板块迎来配置窗口】中银证券指出，大宗商品周期轮动的必然趋势、原油价格的上行支撑、行业供需格局的持续改善，共同构成了A股化工行业上行的核心逻辑。",
    "content": "【中银证券：化工板块迎来配置窗口】中银证券指出，大宗商品周期轮动的必然趋势、原油价格的上行支撑、行业供需格局的持续改善，共同构成了A股化工行业上行的核心逻辑。",
    "full_content": "【中银证券：化工板块迎来配置窗口】中银证券指出，大宗商品周期轮动的必然趋势、原油价格的上行支撑、行业供需格局的持续改善，共同构成了A股化工行业上行的核心逻辑。",
    "sort_time": "1773574989014360",
    "showTime": "2026-03-15 19:43:09",
    "time": "2026-03-15 19:43:09",
    "publish_time": "2026-03-15 19:43:09",
    "raw_data": {
      "code": "202603153672414360",
      "image": [],
      "pinglun_Num": 20,
      "realSort": "1773574989014360",
      "share": 7,
      "showTime": "2026-03-15 19:43:09",
      "stockList": [
        "90.BK0538"
      ],
      "summary": "【中银证券：化工板块迎来配置窗口】中银证券指出，大宗商品周期轮动的必然趋势、原油价格的上行支撑、行业供需格局的持续改善，共同构成了A股化工行业上行的核心逻辑。",
      "title": "中银证券：化工板块迎来配置窗口",
      "titleColor": 0
    },
    "source": "东方财富快讯",
    "url": "https://kuaixun.eastmoney.com/news/202603153672414360.html",
    "category": "股市",
    "importance": 6,
    "sentiment": "neutral",
    "related_stocks": [
      "90.BK0538"
    ],
    "has_stock_mention": true,
    "comment_count": 20,
    "share_count": 7,
    "tags": {
      "industries": [
        {
          "id": "I020102",
          "name": "证券",
          "level1": "金融业",
          "level2": "货币金融服务",
          "matched_keyword": "证券"
        }
      ],
      "concepts": [
        {
          "id": "C401",
          "name": "券商",
          "matched_keyword": "证券"
        },
        {
          "id": "C506",
          "name": "石油",
          "matched_keyword": "原油"
        },
        {
          "id": "C508",
          "name": "化工",
          "matched_keyword": "化工"
        }
      ],
      "industry_ids": [
        "I020102"
      ],
      "concept_ids": [
        "C401",
        "C506",
        "C508"
      ]
    }
  },
  {
    "id": "6cdb8b1e21b20738",
    "code": "202603153672413317",
    "title": "以军否认防空弹药不足",
    "summary": "【以军否认防空弹药不足】据以色列方面15日消息，以色列国防军否认以军防空拦截弹“严重不足”且库存正在耗尽的说法。",
    "content": "【以军否认防空弹药不足】据以色列方面15日消息，以色列国防军否认以军防空拦截弹“严重不足”且库存正在耗尽的说法。",
    "full_content": "【以军否认防空弹药不足】据以色列方面15日消息，以色列国防军否认以军防空拦截弹“严重不足”且库存正在耗尽的说法。",
    "sort_time": "1773574647013317",
    "showTime": "2026-03-15 19:37:27",
    "time": "2026-03-15 19:37:27",
    "publish_time": "2026-03-15 19:37:27",
    "raw_data": {
      "code": "202603153672413317",
      "image": [],
      "pinglun_Num": 16,
      "realSort": "1773574647013317",
      "share": 2,
      "showTime": "2026-03-15 19:37:27",
      "stockList": [],
      "summary": "【以军否认防空弹药不足】据以色列方面15日消息，以色列国防军否认以军防空拦截弹“严重不足”且库存正在耗尽的说法。",
      "title": "以军否认防空弹药不足",
      "titleColor": 0
    },
    "source": "东方财富快讯",
    "url": "https://kuaixun.eastmoney.com/news/202603153672413317.html",
    "category": "其他",
    "importance": 5,
    "sentiment": "neutral",
    "related_stocks": [],
    "has_stock_mention": false,
    "comment_count": 16,
    "share_count": 2,
    "tags": {
      "industries": [],
      "concepts": [
        {
          "id": "C201",
          "name": "军工",
          "matched_keyword": "国防"
        }
      ],
      "industry_ids": [],
      "concept_ids": [
        "C201"
      ]
    }
  },
  {
    "id": "175b1f320912ae6c",
    "code": "202603153672412594",
    "title": "伊朗表示愿与地区国家组建联合调查委员会",
    "summary": "【伊朗表示愿与地区国家组建联合调查委员会】伊朗外交部长阿拉格齐15日表示，伊朗已准备与地区国家举行会谈，组建联合调查委员会，以查明遭袭目标的性质及是否属于美国在该地区的设施和利益。",
    "content": "【伊朗表示愿与地区国家组建联合调查委员会】伊朗外交部长阿拉格齐15日表示，伊朗已准备与地区国家举行会谈，组建联合调查委员会，以查明遭袭目标的性质及是否属于美国在该地区的设施和利益。",
    "full_content": "【伊朗表示愿与地区国家组建联合调查委员会】伊朗外交部长阿拉格齐15日表示，伊朗已准备与地区国家举行会谈，组建联合调查委员会，以查明遭袭目标的性质及是否属于美国在该地区的设施和利益。",
    "sort_time": "1773574139012594",
    "showTime": "2026-03-15 19:28:59",
    "time": "2026-03-15 19:28:59",
    "publish_time": "2026-03-15 19:28:59",
    "raw_data": {
      "code": "202603153672412594",
      "image": [],
      "pinglun_Num": 23,
      "realSort": "1773574139012594",
      "share": 10,
      "showTime": "2026-03-15 19:28:59",
      "stockList": [],
      "summary": "【伊朗表示愿与地区国家组建联合调查委员会】伊朗外交部长阿拉格齐15日表示，伊朗已准备与地区国家举行会谈，组建联合调查委员会，以查明遭袭目标的性质及是否属于美国在该地区的设施和利益。",
      "title": "伊朗表示愿与地区国家组建联合调查委员会",
      "titleColor": 0
    },
    "source": "东方财富快讯",
    "url": "https://kuaixun.eastmoney.com/news/202603153672412594.html",
    "category": "其他",
    "importance": 5,
    "sentiment": "neutral",
    "related_stocks": [],
    "has_stock_mention": false,
    "comment_count": 23,
    "share_count": 10,
    "tags": {
      "industries": [],
      "concepts": [],
      "industry_ids": [],
      "concept_ids": []
    }
  },
  {
    "id": "b91298f1ccdfb09c",
    "code": "202603153672411069",
    "title": "中信建投：中东局势影响深远 中国迎来战略机遇",
    "summary": "【中信建投：中东局势影响深远 中国迎来战略机遇】中信建投研报指出，美伊冲突进入相持阶段，原油价格剧烈波动。中国原油进口多元化，能源结构转型与石油战略储备也将发挥缓冲作用。但在全球风险偏好扰动及国内市场资金面约束下，A股短期可能仍将维持震荡格局。美伊冲突若长期化，可能带来三方面主要影响：1）油价中枢上行，全球通胀升温，美联储降息节奏受扰；2）石油美元体系松动加速，中国有望成为全球资本避风港，人民币资产可能受益；3）或催生中国战略机遇，凭借“煤炭+新能源”的双支柱能源底座，不仅保障自身能源安全，更可能成为全球能源转型的引领者。",
    "content": "【中信建投：中东局势影响深远 中国迎来战略机遇】中信建投研报指出，美伊冲突进入相持阶段，原油价格剧烈波动。中国原油进口多元化，能源结构转型与石油战略储备也将发挥缓冲作用。但在全球风险偏好扰动及国内市场资金面约束下，A股短期可能仍将维持震荡格局。美伊冲突若长期化，可能带来三方面主要影响：1）油价中枢上行，全球通胀升温，美联储降息节奏受扰；2）石油美元体系松动加速，中国有望成为全球资本避风港，人民币资产可能受益；3）或催生中国战略机遇，凭借“煤炭+新能源”的双支柱能源底座，不仅保障自身能源安全，更可能成为全球能源转型的引领者。",
    "full_content": "【中信建投：中东局势影响深远 中国迎来战略机遇】中信建投研报指出，美伊冲突进入相持阶段，原油价格剧烈波动。中国原油进口多元化，能源结构转型与石油战略储备也将发挥缓冲作用。但在全球风险偏好扰动及国内市场资金面约束下，A股短期可能仍将维持震荡格局。美伊冲突若长期化，可能带来三方面主要影响：1）油价中枢上行，全球通胀升温，美联储降息节奏受扰；2）石油美元体系松动加速，中国有望成为全球资本避风港，人民币资产可能受益；3）或催生中国战略机遇，凭借“煤炭+新能源”的双支柱能源底座，不仅保障自身能源安全，更可能成为全球能源转型的引领者。",
    "sort_time": "1773573541011069",
    "showTime": "2026-03-15 19:19:01",
    "time": "2026-03-15 19:19:01",
    "publish_time": "2026-03-15 19:19:01",
    "raw_data": {
      "code": "202603153672411069",
      "image": [],
      "pinglun_Num": 37,
      "realSort": "1773573541011069",
      "share": 28,
      "showTime": "2026-03-15 19:19:01",
      "stockList": [
        "90.BK0464",
        "150.014238"
      ],
      "summary": "【中信建投：中东局势影响深远 中国迎来战略机遇】中信建投研报指出，美伊冲突进入相持阶段，原油价格剧烈波动。中国原油进口多元化，能源结构转型与石油战略储备也将发挥缓冲作用。但在全球风险偏好扰动及国内市场资金面约束下，A股短期可能仍将维持震荡格局。美伊冲突若长期化，可能带来三方面主要影响：1）油价中枢上行，全球通胀升温，美联储降息节奏受扰；2）石油美元体系松动加速，中国有望成为全球资本避风港，人民币资产可能受益；3）或催生中国战略机遇，凭借“煤炭+新能源”的双支柱能源底座，不仅保障自身能源安全，更可能成为全球能源转型的引领者。",
      "title": "中信建投：中东局势影响深远 中国迎来战略机遇",
      "titleColor": 0
    },
    "source": "东方财富快讯",
    "url": "https://kuaixun.eastmoney.com/news/202603153672411069.html",
    "category": "宏观",
    "importance": 6,
    "sentiment": "neutral",
    "related_stocks": [
      "90.BK0464",
      "150.014238"
    ],
    "has_stock_mention": true,
    "comment_count": 37,
    "share_count": 28,
    "tags": {
      "industries": [
        {
          "id": "I020101",
          "name": "银行",
          "level1": "金融业",
          "level2": "货币金融服务",
          "matched_keyword": "降息"
        }
      ],
      "concepts": [
        {
          "id": "C402",
          "name": "银行",
          "matched_keyword": "降息"
        },
        {
          "id": "C505",
          "name": "煤炭",
          "matched_keyword": "煤炭"
        },
        {
          "id": "C506",
          "name": "石油",
          "matched_keyword": "原油"
        }
      ],
      "industry_ids": [
        "I020101"
      ],
      "concept_ids": [
        "C402",
        "C505",
        "C506"
      ]
    }
  },
  {
    "id": "3fdaa2c28325b642",
    "code": "202603153672410934",
    "title": "宇环数控：2025年度公司产品未应用于商业航天领域 间接用于航空航天领域的业务收入占比不足5%",
    "summary": "【宇环数控：2025年度公司产品未应用于商业航天领域 间接用于航空航天领域的业务收入占比不足5%】宇环数控(002903.SZ)发布风险提示公告，公司主要从事数控磨削、拉削设备的研发、生产、销售与服务；2025年度，公司产品未应用于商业航天领域，未直接应用于航空航天领域，且间接用于航空航天领域的业务收入占营业收入的比重不足5%，占比较小，对公司业绩的影响程度较小。",
    "content": "【宇环数控：2025年度公司产品未应用于商业航天领域 间接用于航空航天领域的业务收入占比不足5%】宇环数控(002903.SZ)发布风险提示公告，公司主要从事数控磨削、拉削设备的研发、生产、销售与服务；2025年度，公司产品未应用于商业航天领域，未直接应用于航空航天领域，且间接用于航空航天领域的业务收入占营业收入的比重不足5%，占比较小，对公司业绩的影响程度较小。",
    "full_content": "【宇环数控：2025年度公司产品未应用于商业航天领域 间接用于航空航天领域的业务收入占比不足5%】宇环数控(002903.SZ)发布风险提示公告，公司主要从事数控磨削、拉削设备的研发、生产、销售与服务；2025年度，公司产品未应用于商业航天领域，未直接应用于航空航天领域，且间接用于航空航天领域的业务收入占营业收入的比重不足5%，占比较小，对公司业绩的影响程度较小。",
    "sort_time": "1773573478010934",
    "showTime": "2026-03-15 19:17:58",
    "time": "2026-03-15 19:17:58",
    "publish_time": "2026-03-15 19:17:58",
    "raw_data": {
      "code": "202603153672410934",
      "image": [],
      "pinglun_Num": 7,
      "realSort": "1773573478010934",
      "share": 3,
      "showTime": "2026-03-15 19:17:58",
      "stockList": [],
      "summary": "【宇环数控：2025年度公司产品未应用于商业航天领域 间接用于航空航天领域的业务收入占比不足5%】宇环数控(002903.SZ)发布风险提示公告，公司主要从事数控磨削、拉削设备的研发、生产、销售与服务；2025年度，公司产品未应用于商业航天领域，未直接应用于航空航天领域，且间接用于航空航天领域的业务收入占营业收入的比重不足5%，占比较小，对公司业绩的影响程度较小。",
      "title": "宇环数控：2025年度公司产品未应用于商业航天领域 间接用于航空航天领域的业务收入占比不足5%",
      "titleColor": 3
    },
    "source": "东方财富快讯",
    "url": "https://kuaixun.eastmoney.com/news/202603153672410934.html",
    "category": "公司",
    "importance": 5,
    "sentiment": "neutral",
    "related_stocks": [],
    "has_stock_mention": false,
    "comment_count": 7,
    "share_count": 3,
    "tags": {
      "industries": [],
      "concepts": [
        {
          "id": "C202",
          "name": "航天",
          "matched_keyword": "航天"
        },
        {
          "id": "C201",
          "name": "军工",
          "matched_keyword": "航空"
        }
      ],
      "industry_ids": [],
      "concept_ids": [
        "C202",
        "C201"
      ]
    }
  },
  {
    "id": "c61179f2f227825c",
    "code": "202603153672410872",
    "title": "中信建投：燃机景气预计创历史新高 国产链弹性最大",
    "summary": "【中信建投：燃机景气预计创历史新高 国产链弹性最大】中信建投研报认为，虽然当前燃机订单正接近历史高位，但存在地区集中度、驱动因素、天然气价格影响、交付能力等显著差异。本轮需求在AI的实际拉动下具备较强的持续性，后续燃机板块将继续演绎订单上行、产业链扩产、供需矛盾下产业链利润中枢上移。由于欧美原供应链扩产意愿度较低，国内自主燃机、叶片、铸锻件、HRSG等环节正在推进产品认证及订单导入，国产链将在本轮三十年一遇的燃机周期中充分受益。",
    "content": "【中信建投：燃机景气预计创历史新高 国产链弹性最大】中信建投研报认为，虽然当前燃机订单正接近历史高位，但存在地区集中度、驱动因素、天然气价格影响、交付能力等显著差异。本轮需求在AI的实际拉动下具备较强的持续性，后续燃机板块将继续演绎订单上行、产业链扩产、供需矛盾下产业链利润中枢上移。由于欧美原供应链扩产意愿度较低，国内自主燃机、叶片、铸锻件、HRSG等环节正在推进产品认证及订单导入，国产链将在本轮三十年一遇的燃机周期中充分受益。",
    "full_content": "【中信建投：燃机景气预计创历史新高 国产链弹性最大】中信建投研报认为，虽然当前燃机订单正接近历史高位，但存在地区集中度、驱动因素、天然气价格影响、交付能力等显著差异。本轮需求在AI的实际拉动下具备较强的持续性，后续燃机板块将继续演绎订单上行、产业链扩产、供需矛盾下产业链利润中枢上移。由于欧美原供应链扩产意愿度较低，国内自主燃机、叶片、铸锻件、HRSG等环节正在推进产品认证及订单导入，国产链将在本轮三十年一遇的燃机周期中充分受益。",
    "sort_time": "1773573427010872",
    "showTime": "2026-03-15 19:17:07",
    "time": "2026-03-15 19:17:07",
    "publish_time": "2026-03-15 19:17:07",
    "raw_data": {
      "code": "202603153672410872",
      "image": [],
      "pinglun_Num": 9,
      "realSort": "1773573427010872",
      "share": 8,
      "showTime": "2026-03-15 19:17:07",
      "stockList": [],
      "summary": "【中信建投：燃机景气预计创历史新高 国产链弹性最大】中信建投研报认为，虽然当前燃机订单正接近历史高位，但存在地区集中度、驱动因素、天然气价格影响、交付能力等显著差异。本轮需求在AI的实际拉动下具备较强的持续性，后续燃机板块将继续演绎订单上行、产业链扩产、供需矛盾下产业链利润中枢上移。由于欧美原供应链扩产意愿度较低，国内自主燃机、叶片、铸锻件、HRSG等环节正在推进产品认证及订单导入，国产链将在本轮三十年一遇的燃机周期中充分受益。",
      "title": "中信建投：燃机景气预计创历史新高 国产链弹性最大",
      "titleColor": 0
    },
    "source": "东方财富快讯",
    "url": "https://kuaixun.eastmoney.com/news/202603153672410872.html",
    "category": "行业",
    "importance": 5,
    "sentiment": "neutral",
    "related_stocks": [],
    "has_stock_mention": false,
    "comment_count": 9,
    "share_count": 8,
    "tags": {
      "industries": [],
      "concepts": [
        {
          "id": "C001",
          "name": "人工智能",
          "matched_keyword": "AI"
        },
        {
          "id": "C507",
          "name": "天然气",
          "matched_keyword": "天然气"
        },
        {
          "id": "C807",
          "name": "苹果概念",
          "matched_keyword": "供应链"
        }
      ],
      "industry_ids": [],
      "concept_ids": [
        "C001",
        "C507",
        "C807"
      ]
    }
  },
  {
    "id": "20e2e4a119139712",
    "code": "202603153672410683",
    "title": "招商证券：A股投资者持仓风格可能进一步均衡 向偏价值、涨价顺周期方向漂移",
    "summary": "【招商证券：A股投资者持仓风格可能进一步均衡 向偏价值、涨价顺周期方向漂移】招商证券最新研报指出，地缘冲突使市场核心矛盾转向供给安全与战略资源，驱动逻辑从避险切换为再通胀担忧。油价上涨强化通胀预期，压制降息前景，冲击多数资产。短期油价持续上行导致的再通胀交易和美联储降息预期推迟，会对市场风险偏好形成一定影响，使得A股仍以震荡为主，市场结构分化明显，资源品板块相对受益。同时，在PPI回升及转正预期之下，投资者持仓风格可能进一步均衡，向偏价值、涨价顺周期方向漂移。",
    "content": "【招商证券：A股投资者持仓风格可能进一步均衡 向偏价值、涨价顺周期方向漂移】招商证券最新研报指出，地缘冲突使市场核心矛盾转向供给安全与战略资源，驱动逻辑从避险切换为再通胀担忧。油价上涨强化通胀预期，压制降息前景，冲击多数资产。短期油价持续上行导致的再通胀交易和美联储降息预期推迟，会对市场风险偏好形成一定影响，使得A股仍以震荡为主，市场结构分化明显，资源品板块相对受益。同时，在PPI回升及转正预期之下，投资者持仓风格可能进一步均衡，向偏价值、涨价顺周期方向漂移。",
    "full_content": "【招商证券：A股投资者持仓风格可能进一步均衡 向偏价值、涨价顺周期方向漂移】招商证券最新研报指出，地缘冲突使市场核心矛盾转向供给安全与战略资源，驱动逻辑从避险切换为再通胀担忧。油价上涨强化通胀预期，压制降息前景，冲击多数资产。短期油价持续上行导致的再通胀交易和美联储降息预期推迟，会对市场风险偏好形成一定影响，使得A股仍以震荡为主，市场结构分化明显，资源品板块相对受益。同时，在PPI回升及转正预期之下，投资者持仓风格可能进一步均衡，向偏价值、涨价顺周期方向漂移。",
    "sort_time": "1773573263010683",
    "showTime": "2026-03-15 19:14:23",
    "time": "2026-03-15 19:14:23",
    "publish_time": "2026-03-15 19:14:23",
    "raw_data": {
      "code": "202603153672410683",
      "image": [],
      "pinglun_Num": 6,
      "realSort": "1773573263010683",
      "share": 3,
      "showTime": "2026-03-15 19:14:23",
      "stockList": [],
      "summary": "【招商证券：A股投资者持仓风格可能进一步均衡 向偏价值、涨价顺周期方向漂移】招商证券最新研报指出，地缘冲突使市场核心矛盾转向供给安全与战略资源，驱动逻辑从避险切换为再通胀担忧。油价上涨强化通胀预期，压制降息前景，冲击多数资产。短期油价持续上行导致的再通胀交易和美联储降息预期推迟，会对市场风险偏好形成一定影响，使得A股仍以震荡为主，市场结构分化明显，资源品板块相对受益。同时，在PPI回升及转正预期之下，投资者持仓风格可能进一步均衡，向偏价值、涨价顺周期方向漂移。",
      "title": "招商证券：A股投资者持仓风格可能进一步均衡 向偏价值、涨价顺周期方向漂移",
      "titleColor": 0
    },
    "source": "东方财富快讯",
    "url": "https://kuaixun.eastmoney.com/news/202603153672410683.html",
    "category": "宏观",
    "importance": 5,
    "sentiment": "bullish",
    "related_stocks": [],
    "has_stock_mention": false,
    "comment_count": 6,
    "share_count": 3,
    "tags": {
      "industries": [
        {
          "id": "I020101",
          "name": "银行",
          "level1": "金融业",
          "level2": "货币金融服务",
          "matched_keyword": "降息"
        },
        {
          "id": "I020102",
          "name": "证券",
          "level1": "金融业",
          "level2": "货币金融服务",
          "matched_keyword": "证券"
        }
      ],
      "concepts": [
        {
          "id": "C401",
          "name": "券商",
          "matched_keyword": "证券"
        },
        {
          "id": "C402",
          "name": "银行",
          "matched_keyword": "降息"
        }
      ],
      "industry_ids": [
        "I020101",
        "I020102"
      ],
      "concept_ids": [
        "C401",
        "C402"
      ]
    }
  },
  {
    "id": "c3ed5b151bcac0e3",
    "code": "202603153672408896",
    "title": "中信证券：当前建筑行业板块具备进可攻、退可守的双重投资逻辑",
    "summary": "【中信证券：当前建筑行业板块具备进可攻、退可守的双重投资逻辑】中信证券研报指出，建筑行业在过往下行周期中，一方面竞争格局得以优化，另一方面持续加大第二增长曲线布局。在“十五五”期间行业总需求有望迎来底部反转+行业估值整体处于相对洼地背景下，中信证券认为当前板块具备进可攻、退可守的双重投资逻辑：1）进攻端，过去几年在第二主业已有充分布局的企业，有望率先迎来价值重估；2）防御端，部分企业分红率逆势提升，同时股息率处于较高水平。维持行业“强于大市”评级。",
    "content": "【中信证券：当前建筑行业板块具备进可攻、退可守的双重投资逻辑】中信证券研报指出，建筑行业在过往下行周期中，一方面竞争格局得以优化，另一方面持续加大第二增长曲线布局。在“十五五”期间行业总需求有望迎来底部反转+行业估值整体处于相对洼地背景下，中信证券认为当前板块具备进可攻、退可守的双重投资逻辑：1）进攻端，过去几年在第二主业已有充分布局的企业，有望率先迎来价值重估；2）防御端，部分企业分红率逆势提升，同时股息率处于较高水平。维持行业“强于大市”评级。",
    "full_content": "【中信证券：当前建筑行业板块具备进可攻、退可守的双重投资逻辑】中信证券研报指出，建筑行业在过往下行周期中，一方面竞争格局得以优化，另一方面持续加大第二增长曲线布局。在“十五五”期间行业总需求有望迎来底部反转+行业估值整体处于相对洼地背景下，中信证券认为当前板块具备进可攻、退可守的双重投资逻辑：1）进攻端，过去几年在第二主业已有充分布局的企业，有望率先迎来价值重估；2）防御端，部分企业分红率逆势提升，同时股息率处于较高水平。维持行业“强于大市”评级。",
    "sort_time": "1773573081008896",
    "showTime": "2026-03-15 19:11:21",
    "time": "2026-03-15 19:11:21",
    "publish_time": "2026-03-15 19:11:21",
    "raw_data": {
      "code": "202603153672408896",
      "image": [],
      "pinglun_Num": 11,
      "realSort": "1773573081008896",
      "share": 3,
      "showTime": "2026-03-15 19:11:21",
      "stockList": [
        "90.BK0425"
      ],
      "summary": "【中信证券：当前建筑行业板块具备进可攻、退可守的双重投资逻辑】中信证券研报指出，建筑行业在过往下行周期中，一方面竞争格局得以优化，另一方面持续加大第二增长曲线布局。在“十五五”期间行业总需求有望迎来底部反转+行业估值整体处于相对洼地背景下，中信证券认为当前板块具备进可攻、退可守的双重投资逻辑：1）进攻端，过去几年在第二主业已有充分布局的企业，有望率先迎来价值重估；2）防御端，部分企业分红率逆势提升，同时股息率处于较高水平。维持行业“强于大市”评级。",
      "title": "中信证券：当前建筑行业板块具备进可攻、退可守的双重投资逻辑",
      "titleColor": 0
    },
    "source": "东方财富快讯",
    "url": "https://kuaixun.eastmoney.com/news/202603153672408896.html",
    "category": "公司",
    "importance": 6,
    "sentiment": "bullish",
    "related_stocks": [
      "90.BK0425"
    ],
    "has_stock_mention": true,
    "comment_count": 11,
    "share_count": 3,
    "tags": {
      "industries": [
        {
          "id": "I020102",
          "name": "证券",
          "level1": "金融业",
          "level2": "货币金融服务",
          "matched_keyword": "证券"
        }
      ],
      "concepts": [
        {
          "id": "C401",
          "name": "券商",
          "matched_keyword": "证券"
        }
      ],
      "industry_ids": [
        "I020102"
      ],
      "concept_ids": [
        "C401"
      ]
    }
  },
  {
    "id": "dfe63910397f09cc",
    "code": "202603153672406663",
    "title": "2026年中国家电及消费电子博览会闭幕",
    "summary": "【2026年中国家电及消费电子博览会闭幕】2026年中国家电及消费电子博览会（AWE2026）3月15日闭幕。两大展区之一的新国际展区观众人数较上届预计增长30%以上。本届展会期间，中国家用电器协会家用服务机器人专委会成立，并发布首份《家用服务机器人产业发展白皮书》。",
    "content": "【2026年中国家电及消费电子博览会闭幕】2026年中国家电及消费电子博览会（AWE2026）3月15日闭幕。两大展区之一的新国际展区观众人数较上届预计增长30%以上。本届展会期间，中国家用电器协会家用服务机器人专委会成立，并发布首份《家用服务机器人产业发展白皮书》。",
    "full_content": "【2026年中国家电及消费电子博览会闭幕】2026年中国家电及消费电子博览会（AWE2026）3月15日闭幕。两大展区之一的新国际展区观众人数较上届预计增长30%以上。本届展会期间，中国家用电器协会家用服务机器人专委会成立，并发布首份《家用服务机器人产业发展白皮书》。",
    "sort_time": "1773572944006663",
    "showTime": "2026-03-15 19:09:04",
    "time": "2026-03-15 19:09:04",
    "publish_time": "2026-03-15 19:09:04",
    "raw_data": {
      "code": "202603153672406663",
      "image": [],
      "pinglun_Num": 0,
      "realSort": "1773572944006663",
      "share": 1,
      "showTime": "2026-03-15 19:09:04",
      "stockList": [
        "90.BK0456",
        "90.BK1037"
      ],
      "summary": "【2026年中国家电及消费电子博览会闭幕】2026年中国家电及消费电子博览会（AWE2026）3月15日闭幕。两大展区之一的新国际展区观众人数较上届预计增长30%以上。本届展会期间，中国家用电器协会家用服务机器人专委会成立，并发布首份《家用服务机器人产业发展白皮书》。",
      "title": "2026年中国家电及消费电子博览会闭幕",
      "titleColor": 0
    },
    "source": "东方财富快讯",
    "url": "https://kuaixun.eastmoney.com/news/202603153672406663.html",
    "category": "其他",
    "importance": 6,
    "sentiment": "bullish",
    "related_stocks": [
      "90.BK0456",
      "90.BK1037"
    ],
    "has_stock_mention": true,
    "comment_count": 0,
    "share_count": 1,
    "tags": {
      "industries": [
        {
          "id": "I010103",
          "name": "消费电子",
          "level1": "制造业",
          "level2": "计算机、通信和其他电子设备制造业",
          "matched_keyword": "消费电子"
        }
      ],
      "concepts": [
        {
          "id": "C012",
          "name": "机器人",
          "matched_keyword": "机器人"
        },
        {
          "id": "C013",
          "name": "消费电子",
          "matched_keyword": "消费电子"
        },
        {
          "id": "C606",
          "name": "家电",
          "matched_keyword": "家电"
        }
      ],
      "industry_ids": [
        "I010103"
      ],
      "concept_ids": [
        "C012",
        "C013",
        "C606"
      ]
    }
  },
  {
    "id": "c2a20f9842457e3d",
    "code": "202603153672406146",
    "title": "中信证券：目前饮料企业成本端整体可控，建议把握板块回调后龙头企业布局机会",
    "summary": "【中信证券：目前饮料企业成本端整体可控，建议把握板块回调后龙头企业布局机会】3月15日，中信证券最新研报指出，近期饮料企业主要原材料PET价格大幅上涨引发市场关注，饮料公司股价出现较大幅度回调。通过复盘历史油价/PET涨价潮和成本敏感性分析，我们认为目前饮料企业成本端整体可控；若后续PET价格持续维持在高位，可能导致行业竞争趋缓，企业有望通过缩减费投的方式部分抵消原材料带来的负面影响。建议把握板块回调后龙头企业的布局机会。",
    "content": "【中信证券：目前饮料企业成本端整体可控，建议把握板块回调后龙头企业布局机会】3月15日，中信证券最新研报指出，近期饮料企业主要原材料PET价格大幅上涨引发市场关注，饮料公司股价出现较大幅度回调。通过复盘历史油价/PET涨价潮和成本敏感性分析，我们认为目前饮料企业成本端整体可控；若后续PET价格持续维持在高位，可能导致行业竞争趋缓，企业有望通过缩减费投的方式部分抵消原材料带来的负面影响。建议把握板块回调后龙头企业的布局机会。",
    "full_content": "【中信证券：目前饮料企业成本端整体可控，建议把握板块回调后龙头企业布局机会】3月15日，中信证券最新研报指出，近期饮料企业主要原材料PET价格大幅上涨引发市场关注，饮料公司股价出现较大幅度回调。通过复盘历史油价/PET涨价潮和成本敏感性分析，我们认为目前饮料企业成本端整体可控；若后续PET价格持续维持在高位，可能导致行业竞争趋缓，企业有望通过缩减费投的方式部分抵消原材料带来的负面影响。建议把握板块回调后龙头企业的布局机会。",
    "sort_time": "1773572607006146",
    "showTime": "2026-03-15 19:03:27",
    "time": "2026-03-15 19:03:27",
    "publish_time": "2026-03-15 19:03:27",
    "raw_data": {
      "code": "202603153672406146",
      "image": [],
      "pinglun_Num": 3,
      "realSort": "1773572607006146",
      "share": 0,
      "showTime": "2026-03-15 19:03:27",
      "stockList": [
        "90.BK0438"
      ],
      "summary": "【中信证券：目前饮料企业成本端整体可控，建议把握板块回调后龙头企业布局机会】3月15日，中信证券最新研报指出，近期饮料企业主要原材料PET价格大幅上涨引发市场关注，饮料公司股价出现较大幅度回调。通过复盘历史油价/PET涨价潮和成本敏感性分析，我们认为目前饮料企业成本端整体可控；若后续PET价格持续维持在高位，可能导致行业竞争趋缓，企业有望通过缩减费投的方式部分抵消原材料带来的负面影响。建议把握板块回调后龙头企业的布局机会。",
      "title": "中信证券：目前饮料企业成本端整体可控，建议把握板块回调后龙头企业布局机会",
      "titleColor": 0
    },
    "source": "东方财富快讯",
    "url": "https://kuaixun.eastmoney.com/news/202603153672406146.html",
    "category": "行业",
    "importance": 6,
    "sentiment": "bullish",
    "related_stocks": [
      "90.BK0438"
    ],
    "has_stock_mention": true,
    "comment_count": 3,
    "share_count": 0,
    "tags": {
      "industries": [
        {
          "id": "I020102",
          "name": "证券",
          "level1": "金融业",
          "level2": "货币金融服务",
          "matched_keyword": "证券"
        }
      ],
      "concepts": [
        {
          "id": "C401",
          "name": "券商",
          "matched_keyword": "证券"
        },
        {
          "id": "C602",
          "name": "食品饮料",
          "matched_keyword": "饮料"
        }
      ],
      "industry_ids": [
        "I020102"
      ],
      "concept_ids": [
        "C401",
        "C602"
      ]
    }
  },
  {
    "id": "df4c7a81299d9ac3",
    "code": "202603153672406096",
    "title": "伊朗发动“真实承诺-4”第54轮军事行动",
    "summary": "【伊朗发动“真实承诺-4”第54轮军事行动】总台记者获悉，当地时间3月15日下午，伊朗发动“真实承诺-4”第54轮军事行动。在本次行动中，伊朗首次使用“泥石”（Sejjil）弹道导弹。",
    "content": "【伊朗发动“真实承诺-4”第54轮军事行动】总台记者获悉，当地时间3月15日下午，伊朗发动“真实承诺-4”第54轮军事行动。在本次行动中，伊朗首次使用“泥石”（Sejjil）弹道导弹。",
    "full_content": "【伊朗发动“真实承诺-4”第54轮军事行动】总台记者获悉，当地时间3月15日下午，伊朗发动“真实承诺-4”第54轮军事行动。在本次行动中，伊朗首次使用“泥石”（Sejjil）弹道导弹。",
    "sort_time": "1773572554006096",
    "showTime": "2026-03-15 19:02:34",
    "time": "2026-03-15 19:02:34",
    "publish_time": "2026-03-15 19:02:34",
    "raw_data": {
      "code": "202603153672406096",
      "image": [],
      "pinglun_Num": 45,
      "realSort": "1773572554006096",
      "share": 25,
      "showTime": "2026-03-15 19:02:34",
      "stockList": [],
      "summary": "【伊朗发动“真实承诺-4”第54轮军事行动】总台记者获悉，当地时间3月15日下午，伊朗发动“真实承诺-4”第54轮军事行动。在本次行动中，伊朗首次使用“泥石”（Sejjil）弹道导弹。",
      "title": "伊朗发动“真实承诺-4”第54轮军事行动",
      "titleColor": 0
    },
    "source": "东方财富快讯",
    "url": "https://kuaixun.eastmoney.com/news/202603153672406096.html",
    "category": "其他",
    "importance": 5,
    "sentiment": "neutral",
    "related_stocks": [],
    "has_stock_mention": false,
    "comment_count": 45,
    "share_count": 25,
    "tags": {
      "industries": [],
      "concepts": [],
      "industry_ids": [],
      "concept_ids": []
    }
  },
  {
    "id": "067d4dfac37cfad1",
    "code": "202603153672405880",
    "title": "以色列外长否认近期将与黎巴嫩政府直接对话",
    "summary": "【以色列外长否认近期将与黎巴嫩政府直接对话】以色列外长萨尔当地时间15日表示，在未来几天内没有与黎巴嫩政府进行直接对话的计划。",
    "content": "【以色列外长否认近期将与黎巴嫩政府直接对话】以色列外长萨尔当地时间15日表示，在未来几天内没有与黎巴嫩政府进行直接对话的计划。",
    "full_content": "【以色列外长否认近期将与黎巴嫩政府直接对话】以色列外长萨尔当地时间15日表示，在未来几天内没有与黎巴嫩政府进行直接对话的计划。",
    "sort_time": "1773572521005880",
    "showTime": "2026-03-15 19:02:01",
    "time": "2026-03-15 19:02:01",
    "publish_time": "2026-03-15 19:02:01",
    "raw_data": {
      "code": "202603153672405880",
      "image": [],
      "pinglun_Num": 0,
      "realSort": "1773572521005880",
      "share": 0,
      "showTime": "2026-03-15 19:02:01",
      "stockList": [],
      "summary": "【以色列外长否认近期将与黎巴嫩政府直接对话】以色列外长萨尔当地时间15日表示，在未来几天内没有与黎巴嫩政府进行直接对话的计划。",
      "title": "以色列外长否认近期将与黎巴嫩政府直接对话",
      "titleColor": 0
    },
    "source": "东方财富快讯",
    "url": "https://kuaixun.eastmoney.com/news/202603153672405880.html",
    "category": "其他",
    "importance": 5,
    "sentiment": "neutral",
    "related_stocks": [],
    "has_stock_mention": false,
    "comment_count": 0,
    "share_count": 0,
    "tags": {
      "industries": [],
      "concepts": [],
      "industry_ids": [],
      "concept_ids": []
    }
  },
  {
    "id": "f4a5aec9608575fa",
    "code": "202603153672405626",
    "title": "中信证券：坚定围绕中国优势制造定价权重估布局 涨价依然是核心交易线索",
    "summary": "【中信证券：坚定围绕中国优势制造定价权重估布局 涨价依然是核心交易线索】3月15日，中信证券最新研报指出，站在指数层面，估值继续修复的空间有限，企业利润率的回升是下个阶段A股接续牛市的关键，全球供应链的扰动再一次带来校验中国优势制造业定价权的契机；站在风格层面，中东冲突是今年风格切换的催化剂，全球成本上升叠加金融条件走弱的背景下，低估值和定价权是最重要的两个要素；站在产业趋势层面，代码膨胀、实物稀缺，在中国的体现就是优势制造业定价权的提升，AI的破坏式创新加速以及全球能化供应链的扰动都在加强这一趋势。",
    "content": "【中信证券：坚定围绕中国优势制造定价权重估布局 涨价依然是核心交易线索】3月15日，中信证券最新研报指出，站在指数层面，估值继续修复的空间有限，企业利润率的回升是下个阶段A股接续牛市的关键，全球供应链的扰动再一次带来校验中国优势制造业定价权的契机；站在风格层面，中东冲突是今年风格切换的催化剂，全球成本上升叠加金融条件走弱的背景下，低估值和定价权是最重要的两个要素；站在产业趋势层面，代码膨胀、实物稀缺，在中国的体现就是优势制造业定价权的提升，AI的破坏式创新加速以及全球能化供应链的扰动都在加强这一趋势。",
    "full_content": "【中信证券：坚定围绕中国优势制造定价权重估布局 涨价依然是核心交易线索】3月15日，中信证券最新研报指出，站在指数层面，估值继续修复的空间有限，企业利润率的回升是下个阶段A股接续牛市的关键，全球供应链的扰动再一次带来校验中国优势制造业定价权的契机；站在风格层面，中东冲突是今年风格切换的催化剂，全球成本上升叠加金融条件走弱的背景下，低估值和定价权是最重要的两个要素；站在产业趋势层面，代码膨胀、实物稀缺，在中国的体现就是优势制造业定价权的提升，AI的破坏式创新加速以及全球能化供应链的扰动都在加强这一趋势。",
    "sort_time": "1773572443005626",
    "showTime": "2026-03-15 19:00:43",
    "time": "2026-03-15 19:00:43",
    "publish_time": "2026-03-15 19:00:43",
    "raw_data": {
      "code": "202603153672405626",
      "image": [],
      "pinglun_Num": 14,
      "realSort": "1773572443005626",
      "share": 5,
      "showTime": "2026-03-15 19:00:43",
      "stockList": [
        "150.014238"
      ],
      "summary": "【中信证券：坚定围绕中国优势制造定价权重估布局 涨价依然是核心交易线索】3月15日，中信证券最新研报指出，站在指数层面，估值继续修复的空间有限，企业利润率的回升是下个阶段A股接续牛市的关键，全球供应链的扰动再一次带来校验中国优势制造业定价权的契机；站在风格层面，中东冲突是今年风格切换的催化剂，全球成本上升叠加金融条件走弱的背景下，低估值和定价权是最重要的两个要素；站在产业趋势层面，代码膨胀、实物稀缺，在中国的体现就是优势制造业定价权的提升，AI的破坏式创新加速以及全球能化供应链的扰动都在加强这一趋势。",
      "title": "中信证券：坚定围绕中国优势制造定价权重估布局 涨价依然是核心交易线索",
      "titleColor": 0
    },
    "source": "东方财富快讯",
    "url": "https://kuaixun.eastmoney.com/news/202603153672405626.html",
    "category": "股市",
    "importance": 6,
    "sentiment": "neutral",
    "related_stocks": [
      "150.014238"
    ],
    "has_stock_mention": true,
    "comment_count": 14,
    "share_count": 5,
    "tags": {
      "industries": [
        {
          "id": "I020102",
          "name": "证券",
          "level1": "金融业",
          "level2": "货币金融服务",
          "matched_keyword": "证券"
        }
      ],
      "concepts": [
        {
          "id": "C001",
          "name": "人工智能",
          "matched_keyword": "AI"
        },
        {
          "id": "C401",
          "name": "券商",
          "matched_keyword": "证券"
        },
        {
          "id": "C807",
          "name": "苹果概念",
          "matched_keyword": "供应链"
        }
      ],
      "industry_ids": [
        "I020102"
      ],
      "concept_ids": [
        "C001",
        "C401",
        "C807"
      ]
    }
  },
  {
    "id": "c0a252ec4e7ed011",
    "code": "202603153672405252",
    "title": "受中东冲突波及旅客已超600万人次",
    "summary": "【受中东冲突波及旅客已超600万人次】英国一家航空数据分析公司的数据显示，自2月28日美以对伊朗发动军事行动以来，大量进出中东地区的航班取消，受波及旅客已超过600万人次。",
    "content": "【受中东冲突波及旅客已超600万人次】英国一家航空数据分析公司的数据显示，自2月28日美以对伊朗发动军事行动以来，大量进出中东地区的航班取消，受波及旅客已超过600万人次。",
    "full_content": "【受中东冲突波及旅客已超600万人次】英国一家航空数据分析公司的数据显示，自2月28日美以对伊朗发动军事行动以来，大量进出中东地区的航班取消，受波及旅客已超过600万人次。",
    "sort_time": "1773572289005252",
    "showTime": "2026-03-15 18:58:09",
    "time": "2026-03-15 18:58:09",
    "publish_time": "2026-03-15 18:58:09",
    "raw_data": {
      "code": "202603153672405252",
      "image": [],
      "pinglun_Num": 0,
      "realSort": "1773572289005252",
      "share": 0,
      "showTime": "2026-03-15 18:58:09",
      "stockList": [],
      "summary": "【受中东冲突波及旅客已超600万人次】英国一家航空数据分析公司的数据显示，自2月28日美以对伊朗发动军事行动以来，大量进出中东地区的航班取消，受波及旅客已超过600万人次。",
      "title": "受中东冲突波及旅客已超600万人次",
      "titleColor": 0
    },
    "source": "东方财富快讯",
    "url": "https://kuaixun.eastmoney.com/news/202603153672405252.html",
    "category": "其他",
    "importance": 5,
    "sentiment": "neutral",
    "related_stocks": [],
    "has_stock_mention": false,
    "comment_count": 0,
    "share_count": 0,
    "tags": {
      "industries": [],
      "concepts": [
        {
          "id": "C201",
          "name": "军工",
          "matched_keyword": "航空"
        }
      ],
      "industry_ids": [],
      "concept_ids": [
        "C201"
      ]
    }
  },
  {
    "id": "7ac805e1c77c49a3",
    "code": "202603153672405152",
    "title": "“雪龙”号开始返航 中国第42次南极考察接近尾声",
    "summary": "【“雪龙”号开始返航 中国第42次南极考察接近尾声】今天（15日），正在执行中国第42次南极考察任务的“雪龙”号，离开中山站，开始返航，预计4月上旬抵达上海。",
    "content": "【“雪龙”号开始返航 中国第42次南极考察接近尾声】今天（15日），正在执行中国第42次南极考察任务的“雪龙”号，离开中山站，开始返航，预计4月上旬抵达上海。",
    "full_content": "【“雪龙”号开始返航 中国第42次南极考察接近尾声】今天（15日），正在执行中国第42次南极考察任务的“雪龙”号，离开中山站，开始返航，预计4月上旬抵达上海。",
    "sort_time": "1773572081005152",
    "showTime": "2026-03-15 18:54:41",
    "time": "2026-03-15 18:54:41",
    "publish_time": "2026-03-15 18:54:41",
    "raw_data": {
      "code": "202603153672405152",
      "image": [],
      "pinglun_Num": 0,
      "realSort": "1773572081005152",
      "share": 0,
      "showTime": "2026-03-15 18:54:41",
      "stockList": [],
      "summary": "【“雪龙”号开始返航 中国第42次南极考察接近尾声】今天（15日），正在执行中国第42次南极考察任务的“雪龙”号，离开中山站，开始返航，预计4月上旬抵达上海。",
      "title": "“雪龙”号开始返航 中国第42次南极考察接近尾声",
      "titleColor": 0
    },
    "source": "东方财富快讯",
    "url": "https://kuaixun.eastmoney.com/news/202603153672405152.html",
    "category": "其他",
    "importance": 5,
    "sentiment": "neutral",
    "related_stocks": [],
    "has_stock_mention": false,
    "comment_count": 0,
    "share_count": 0,
    "tags": {
      "industries": [],
      "concepts": [],
      "industry_ids": [],
      "concept_ids": []
    }
  },
  {
    "id": "11d1dcee9708ddab",
    "code": "202603153672405037",
    "title": "伊朗称对以色列安全中心和警察总部发动大规模袭击",
    "summary": "【伊朗称对以色列安全中心和警察总部发动大规模袭击】当地时间3月15日，伊朗军队宣布，自当天凌晨起，伊朗军队出动无人机对以色列境内的安全中心以及警察总部发动了大规模袭击。",
    "content": "【伊朗称对以色列安全中心和警察总部发动大规模袭击】当地时间3月15日，伊朗军队宣布，自当天凌晨起，伊朗军队出动无人机对以色列境内的安全中心以及警察总部发动了大规模袭击。",
    "full_content": "【伊朗称对以色列安全中心和警察总部发动大规模袭击】当地时间3月15日，伊朗军队宣布，自当天凌晨起，伊朗军队出动无人机对以色列境内的安全中心以及警察总部发动了大规模袭击。",
    "sort_time": "1773571760005037",
    "showTime": "2026-03-15 18:49:20",
    "time": "2026-03-15 18:49:20",
    "publish_time": "2026-03-15 18:49:20",
    "raw_data": {
      "code": "202603153672405037",
      "image": [],
      "pinglun_Num": 8,
      "realSort": "1773571760005037",
      "share": 3,
      "showTime": "2026-03-15 18:49:20",
      "stockList": [],
      "summary": "【伊朗称对以色列安全中心和警察总部发动大规模袭击】当地时间3月15日，伊朗军队宣布，自当天凌晨起，伊朗军队出动无人机对以色列境内的安全中心以及警察总部发动了大规模袭击。",
      "title": "伊朗称对以色列安全中心和警察总部发动大规模袭击",
      "titleColor": 0
    },
    "source": "东方财富快讯",
    "url": "https://kuaixun.eastmoney.com/news/202603153672405037.html",
    "category": "其他",
    "importance": 5,
    "sentiment": "neutral",
    "related_stocks": [],
    "has_stock_mention": false,
    "comment_count": 8,
    "share_count": 3,
    "tags": {
      "industries": [],
      "concepts": [
        {
          "id": "C205",
          "name": "低空经济",
          "matched_keyword": "无人机"
        }
      ],
      "industry_ids": [],
      "concept_ids": [
        "C205"
      ]
    }
  },
  {
    "id": "e9172928b8a2ea8b",
    "code": "202603153672403296",
    "title": "央行将开展买断式逆回购操作5000亿元",
    "summary": "【央行将开展买断式逆回购操作5000亿元】中国人民银行发布公告称，明日（3月16日）将以固定数量、利率招标、多重价位中标方式开展5000亿元买断式逆回购操作，期限为六个月（182天）。",
    "content": "【央行将开展买断式逆回购操作5000亿元】中国人民银行发布公告称，明日（3月16日）将以固定数量、利率招标、多重价位中标方式开展5000亿元买断式逆回购操作，期限为六个月（182天）。",
    "full_content": "【央行将开展买断式逆回购操作5000亿元】中国人民银行发布公告称，明日（3月16日）将以固定数量、利率招标、多重价位中标方式开展5000亿元买断式逆回购操作，期限为六个月（182天）。",
    "sort_time": "1773571042003296",
    "showTime": "2026-03-15 18:37:22",
    "time": "2026-03-15 18:37:22",
    "publish_time": "2026-03-15 18:37:22",
    "raw_data": {
      "code": "202603153672403296",
      "image": [],
      "pinglun_Num": 12,
      "realSort": "1773571042003296",
      "share": 11,
      "showTime": "2026-03-15 18:37:22",
      "stockList": [],
      "summary": "【央行将开展买断式逆回购操作5000亿元】中国人民银行发布公告称，明日（3月16日）将以固定数量、利率招标、多重价位中标方式开展5000亿元买断式逆回购操作，期限为六个月（182天）。",
      "title": "央行将开展买断式逆回购操作5000亿元",
      "titleColor": 0
    },
    "source": "东方财富快讯",
    "url": "https://kuaixun.eastmoney.com/news/202603153672403296.html",
    "category": "宏观",
    "importance": 5,
    "sentiment": "neutral",
    "related_stocks": [],
    "has_stock_mention": false,
    "comment_count": 12,
    "share_count": 11,
    "tags": {
      "industries": [
        {
          "id": "I020101",
          "name": "银行",
          "level1": "金融业",
          "level2": "货币金融服务",
          "matched_keyword": "央行"
        }
      ],
      "concepts": [
        {
          "id": "C402",
          "name": "银行",
          "matched_keyword": "央行"
        }
      ],
      "industry_ids": [
        "I020101"
      ],
      "concept_ids": [
        "C402"
      ]
    }
  },
  {
    "id": "58e56950dfd8576f",
    "code": "202603153672403090",
    "title": "加拿大与北欧国家将加强北极地区的安全及防御能力",
    "summary": "加拿大与北欧国家将加强北极地区的安全及防御能力。",
    "content": "加拿大与北欧国家将加强北极地区的安全及防御能力。",
    "full_content": "加拿大与北欧国家将加强北极地区的安全及防御能力。",
    "sort_time": "1773571008003090",
    "showTime": "2026-03-15 18:36:48",
    "time": "2026-03-15 18:36:48",
    "publish_time": "2026-03-15 18:36:48",
    "raw_data": {
      "code": "202603153672403090",
      "image": [],
      "pinglun_Num": 0,
      "realSort": "1773571008003090",
      "share": 0,
      "showTime": "2026-03-15 18:36:48",
      "stockList": [],
      "summary": "加拿大与北欧国家将加强北极地区的安全及防御能力。",
      "title": "加拿大与北欧国家将加强北极地区的安全及防御能力",
      "titleColor": 0
    },
    "source": "东方财富快讯",
    "url": "https://kuaixun.eastmoney.com/news/202603153672403090.html",
    "category": "其他",
    "importance": 5,
    "sentiment": "neutral",
    "related_stocks": [],
    "has_stock_mention": false,
    "comment_count": 0,
    "share_count": 0,
    "tags": {
      "industries": [],
      "concepts": [],
      "industry_ids": [],
      "concept_ids": []
    }
  },
  {
    "id": "207a149aee0270e6",
    "code": "202603153672402956",
    "title": "美军1万架无人机从乌克兰转向中东",
    "summary": "【美军1万架无人机从乌克兰转向中东】美国已向中东地区部署1万架原本用于乌克兰的拦截无人机，以应对伊朗的空中打击。",
    "content": "【美军1万架无人机从乌克兰转向中东】美国已向中东地区部署1万架原本用于乌克兰的拦截无人机，以应对伊朗的空中打击。",
    "full_content": "【美军1万架无人机从乌克兰转向中东】美国已向中东地区部署1万架原本用于乌克兰的拦截无人机，以应对伊朗的空中打击。",
    "sort_time": "1773570938002956",
    "showTime": "2026-03-15 18:35:38",
    "time": "2026-03-15 18:35:38",
    "publish_time": "2026-03-15 18:35:38",
    "raw_data": {
      "code": "202603153672402956",
      "image": [],
      "pinglun_Num": 14,
      "realSort": "1773570938002956",
      "share": 20,
      "showTime": "2026-03-15 18:35:38",
      "stockList": [
        "90.BK0704"
      ],
      "summary": "【美军1万架无人机从乌克兰转向中东】美国已向中东地区部署1万架原本用于乌克兰的拦截无人机，以应对伊朗的空中打击。",
      "title": "美军1万架无人机从乌克兰转向中东",
      "titleColor": 0
    },
    "source": "东方财富快讯",
    "url": "https://kuaixun.eastmoney.com/news/202603153672402956.html",
    "category": "其他",
    "importance": 6,
    "sentiment": "neutral",
    "related_stocks": [
      "90.BK0704"
    ],
    "has_stock_mention": true,
    "comment_count": 14,
    "share_count": 20,
    "tags": {
      "industries": [],
      "concepts": [
        {
          "id": "C205",
          "name": "低空经济",
          "matched_keyword": "无人机"
        }
      ],
      "industry_ids": [],
      "concept_ids": [
        "C205"
      ]
    }
  },
  {
    "id": "9483fd240d73820b",
    "code": "202603153672402823",
    "title": "泽连斯基称乌克兰“未卷入与伊朗的战争”",
    "summary": "【泽连斯基称乌克兰“未卷入与伊朗的战争”】据乌克兰国际文传电讯社15日报道，乌克兰总统泽连斯基说，乌方仅向中东有关国家提供技术支持，“并未卷入与伊朗的战争”。",
    "content": "【泽连斯基称乌克兰“未卷入与伊朗的战争”】据乌克兰国际文传电讯社15日报道，乌克兰总统泽连斯基说，乌方仅向中东有关国家提供技术支持，“并未卷入与伊朗的战争”。",
    "full_content": "【泽连斯基称乌克兰“未卷入与伊朗的战争”】据乌克兰国际文传电讯社15日报道，乌克兰总统泽连斯基说，乌方仅向中东有关国家提供技术支持，“并未卷入与伊朗的战争”。",
    "sort_time": "1773570881002823",
    "showTime": "2026-03-15 18:34:41",
    "time": "2026-03-15 18:34:41",
    "publish_time": "2026-03-15 18:34:41",
    "raw_data": {
      "code": "202603153672402823",
      "image": [],
      "pinglun_Num": 21,
      "realSort": "1773570881002823",
      "share": 5,
      "showTime": "2026-03-15 18:34:41",
      "stockList": [],
      "summary": "【泽连斯基称乌克兰“未卷入与伊朗的战争”】据乌克兰国际文传电讯社15日报道，乌克兰总统泽连斯基说，乌方仅向中东有关国家提供技术支持，“并未卷入与伊朗的战争”。",
      "title": "泽连斯基称乌克兰“未卷入与伊朗的战争”",
      "titleColor": 0
    },
    "source": "东方财富快讯",
    "url": "https://kuaixun.eastmoney.com/news/202603153672402823.html",
    "category": "其他",
    "importance": 5,
    "sentiment": "neutral",
    "related_stocks": [],
    "has_stock_mention": false,
    "comment_count": 21,
    "share_count": 5,
    "tags": {
      "industries": [],
      "concepts": [],
      "industry_ids": [],
      "concept_ids": []
    }
  },
  {
    "id": "7f3b8f03981edb41",
    "code": "202603153672402773",
    "title": "十大机构论市：美伊冲突预期反复 A股沿着自身路径前进",
    "summary": "【十大机构论市：美伊冲突预期反复 A股沿着自身路径前进】本周沪指下跌0.70%，深证成指上涨0.76%，创业板指上涨2.51%。下周A股将如何运行？我们汇总了各大机构的最新投资策略，供投资者参考。",
    "content": "【十大机构论市：美伊冲突预期反复 A股沿着自身路径前进】本周沪指下跌0.70%，深证成指上涨0.76%，创业板指上涨2.51%。下周A股将如何运行？我们汇总了各大机构的最新投资策略，供投资者参考。",
    "full_content": "【十大机构论市：美伊冲突预期反复 A股沿着自身路径前进】本周沪指下跌0.70%，深证成指上涨0.76%，创业板指上涨2.51%。下周A股将如何运行？我们汇总了各大机构的最新投资策略，供投资者参考。",
    "sort_time": "1773570655002773",
    "showTime": "2026-03-15 18:30:55",
    "time": "2026-03-15 18:30:55",
    "publish_time": "2026-03-15 18:30:55",
    "raw_data": {
      "code": "202603153672402773",
      "image": [],
      "pinglun_Num": 42,
      "realSort": "1773570655002773",
      "share": 37,
      "showTime": "2026-03-15 18:30:55",
      "stockList": [
        "90.BK0464",
        "90.BK0427"
      ],
      "summary": "【十大机构论市：美伊冲突预期反复 A股沿着自身路径前进】本周沪指下跌0.70%，深证成指上涨0.76%，创业板指上涨2.51%。下周A股将如何运行？我们汇总了各大机构的最新投资策略，供投资者参考。",
      "title": "十大机构论市：美伊冲突预期反复 A股沿着自身路径前进",
      "titleColor": 3
    },
    "source": "东方财富快讯",
    "url": "https://kuaixun.eastmoney.com/news/202603153672402773.html",
    "category": "股市",
    "importance": 6,
    "sentiment": "neutral",
    "related_stocks": [
      "90.BK0464",
      "90.BK0427"
    ],
    "has_stock_mention": true,
    "comment_count": 42,
    "share_count": 37,
    "tags": {
      "industries": [],
      "concepts": [],
      "industry_ids": [],
      "concept_ids": []
    }
  },
  {
    "id": "c0fbac9c328d8861",
    "code": "202603153672402664",
    "title": "乘联分会崔东树：2月乘用车均价18.0万元 同比提升1.5万元",
    "summary": "【乘联分会崔东树：2月乘用车均价18.0万元 同比提升1.5万元】乘联分会秘书长崔东树发文表示，2021年乘用车零售均价是16.5万元，一路上升到2024年均价是18.4万元。2025年乘用车均价是17.0万元，较2024年均价下降1.4万元。2026年2月乘用车均价18.0万元，均价较同期提升1.5万元。",
    "content": "【乘联分会崔东树：2月乘用车均价18.0万元 同比提升1.5万元】乘联分会秘书长崔东树发文表示，2021年乘用车零售均价是16.5万元，一路上升到2024年均价是18.4万元。2025年乘用车均价是17.0万元，较2024年均价下降1.4万元。2026年2月乘用车均价18.0万元，均价较同期提升1.5万元。",
    "full_content": "【乘联分会崔东树：2月乘用车均价18.0万元 同比提升1.5万元】乘联分会秘书长崔东树发文表示，2021年乘用车零售均价是16.5万元，一路上升到2024年均价是18.4万元。2025年乘用车均价是17.0万元，较2024年均价下降1.4万元。2026年2月乘用车均价18.0万元，均价较同期提升1.5万元。",
    "sort_time": "1773570445002664",
    "showTime": "2026-03-15 18:27:25",
    "time": "2026-03-15 18:27:25",
    "publish_time": "2026-03-15 18:27:25",
    "raw_data": {
      "code": "202603153672402664",
      "image": [],
      "pinglun_Num": 1,
      "realSort": "1773570445002664",
      "share": 1,
      "showTime": "2026-03-15 18:27:25",
      "stockList": [
        "90.BK0481",
        "90.BK1262"
      ],
      "summary": "【乘联分会崔东树：2月乘用车均价18.0万元 同比提升1.5万元】乘联分会秘书长崔东树发文表示，2021年乘用车零售均价是16.5万元，一路上升到2024年均价是18.4万元。2025年乘用车均价是17.0万元，较2024年均价下降1.4万元。2026年2月乘用车均价18.0万元，均价较同期提升1.5万元。",
      "title": "乘联分会崔东树：2月乘用车均价18.0万元 同比提升1.5万元",
      "titleColor": 0
    },
    "source": "东方财富快讯",
    "url": "https://kuaixun.eastmoney.com/news/202603153672402664.html",
    "category": "其他",
    "importance": 6,
    "sentiment": "neutral",
    "related_stocks": [
      "90.BK0481",
      "90.BK1262"
    ],
    "has_stock_mention": true,
    "comment_count": 1,
    "share_count": 1,
    "tags": {
      "industries": [
        {
          "id": "I010301",
          "name": "汽车整车",
          "level1": "制造业",
          "level2": "汽车制造业",
          "matched_keyword": "乘用车"
        }
      ],
      "concepts": [
        {
          "id": "C605",
          "name": "零售",
          "matched_keyword": "零售"
        }
      ],
      "industry_ids": [
        "I010301"
      ],
      "concept_ids": [
        "C605"
      ]
    }
  },
  {
    "id": "34d0dba74ad675d3",
    "code": "202603153672401640",
    "title": "以军称监测到伊朗方面第七次弹道导弹袭击",
    "summary": "【以军称监测到伊朗方面第七次弹道导弹袭击】当地时间3月15日中午，以色列国防军称，再次监测到伊朗方面发射的弹道导弹，这也是自当天午夜以来，伊朗对以色列发动的第七次弹道导弹袭击。",
    "content": "【以军称监测到伊朗方面第七次弹道导弹袭击】当地时间3月15日中午，以色列国防军称，再次监测到伊朗方面发射的弹道导弹，这也是自当天午夜以来，伊朗对以色列发动的第七次弹道导弹袭击。",
    "full_content": "【以军称监测到伊朗方面第七次弹道导弹袭击】当地时间3月15日中午，以色列国防军称，再次监测到伊朗方面发射的弹道导弹，这也是自当天午夜以来，伊朗对以色列发动的第七次弹道导弹袭击。",
    "sort_time": "1773570237001640",
    "showTime": "2026-03-15 18:23:57",
    "time": "2026-03-15 18:23:57",
    "publish_time": "2026-03-15 18:23:57",
    "raw_data": {
      "code": "202603153672401640",
      "image": [],
      "pinglun_Num": 15,
      "realSort": "1773570237001640",
      "share": 4,
      "showTime": "2026-03-15 18:23:57",
      "stockList": [],
      "summary": "【以军称监测到伊朗方面第七次弹道导弹袭击】当地时间3月15日中午，以色列国防军称，再次监测到伊朗方面发射的弹道导弹，这也是自当天午夜以来，伊朗对以色列发动的第七次弹道导弹袭击。",
      "title": "以军称监测到伊朗方面第七次弹道导弹袭击",
      "titleColor": 0
    },
    "source": "东方财富快讯",
    "url": "https://kuaixun.eastmoney.com/news/202603153672401640.html",
    "category": "其他",
    "importance": 5,
    "sentiment": "neutral",
    "related_stocks": [],
    "has_stock_mention": false,
    "comment_count": 15,
    "share_count": 4,
    "tags": {
      "industries": [],
      "concepts": [
        {
          "id": "C201",
          "name": "军工",
          "matched_keyword": "国防"
        }
      ],
      "industry_ids": [],
      "concept_ids": [
        "C201"
      ]
    }
  },
  {
    "id": "f59ec3118805f729",
    "code": "202603153672401454",
    "title": "乌克兰对俄罗斯及伊朗相关实体及个人实施制裁",
    "summary": "【乌克兰对俄罗斯及伊朗相关实体及个人实施制裁】当地时间15日，乌克兰总统新闻局通报称，乌方已对俄罗斯、伊朗两国公司及个人实施制裁，此次制裁共涉及130名个人、48家法人实体。",
    "content": "【乌克兰对俄罗斯及伊朗相关实体及个人实施制裁】当地时间15日，乌克兰总统新闻局通报称，乌方已对俄罗斯、伊朗两国公司及个人实施制裁，此次制裁共涉及130名个人、48家法人实体。",
    "full_content": "【乌克兰对俄罗斯及伊朗相关实体及个人实施制裁】当地时间15日，乌克兰总统新闻局通报称，乌方已对俄罗斯、伊朗两国公司及个人实施制裁，此次制裁共涉及130名个人、48家法人实体。",
    "sort_time": "1773570159001454",
    "showTime": "2026-03-15 18:22:39",
    "time": "2026-03-15 18:22:39",
    "publish_time": "2026-03-15 18:22:39",
    "raw_data": {
      "code": "202603153672401454",
      "image": [],
      "pinglun_Num": 14,
      "realSort": "1773570159001454",
      "share": 4,
      "showTime": "2026-03-15 18:22:39",
      "stockList": [],
      "summary": "【乌克兰对俄罗斯及伊朗相关实体及个人实施制裁】当地时间15日，乌克兰总统新闻局通报称，乌方已对俄罗斯、伊朗两国公司及个人实施制裁，此次制裁共涉及130名个人、48家法人实体。",
      "title": "乌克兰对俄罗斯及伊朗相关实体及个人实施制裁",
      "titleColor": 0
    },
    "source": "东方财富快讯",
    "url": "https://kuaixun.eastmoney.com/news/202603153672401454.html",
    "category": "其他",
    "importance": 5,
    "sentiment": "neutral",
    "related_stocks": [],
    "has_stock_mention": false,
    "comment_count": 14,
    "share_count": 4,
    "tags": {
      "industries": [],
      "concepts": [],
      "industry_ids": [],
      "concept_ids": []
    }
  },
  {
    "id": "7f6de33fb0bb8954",
    "code": "202603153672401397",
    "title": "近20家A股上市公司本周披露并购重组最新公告 东吴证券拟购买东海证券83.77%股份股票明起复牌",
    "summary": "【近20家A股上市公司本周披露并购重组最新公告 东吴证券拟购买东海证券83.77%股份股票明起复牌】据不完全统计，截至发稿，本周（3月9日-3月15日）包括京投发展、圣湘生物、*ST步森、金富科技、顶固集创、仟源医药、经纬辉开、亨通股份、优利德、锴威特、东吴证券、恒天海龙、方邦股份、通威股份、中洲控股、长龄液压、*ST清研、新劲刚、珂玛科技在内的19家A股上市公司披露并购重组进展最新公告。其中，东吴证券拟购买东海证券83.77%股份，股票将于3月16日复牌。",
    "content": "【近20家A股上市公司本周披露并购重组最新公告 东吴证券拟购买东海证券83.77%股份股票明起复牌】据不完全统计，截至发稿，本周（3月9日-3月15日）包括京投发展、圣湘生物、*ST步森、金富科技、顶固集创、仟源医药、经纬辉开、亨通股份、优利德、锴威特、东吴证券、恒天海龙、方邦股份、通威股份、中洲控股、长龄液压、*ST清研、新劲刚、珂玛科技在内的19家A股上市公司披露并购重组进展最新公告。其中，东吴证券拟购买东海证券83.77%股份，股票将于3月16日复牌。",
    "full_content": "【近20家A股上市公司本周披露并购重组最新公告 东吴证券拟购买东海证券83.77%股份股票明起复牌】据不完全统计，截至发稿，本周（3月9日-3月15日）包括京投发展、圣湘生物、*ST步森、金富科技、顶固集创、仟源医药、经纬辉开、亨通股份、优利德、锴威特、东吴证券、恒天海龙、方邦股份、通威股份、中洲控股、长龄液压、*ST清研、新劲刚、珂玛科技在内的19家A股上市公司披露并购重组进展最新公告。其中，东吴证券拟购买东海证券83.77%股份，股票将于3月16日复牌。",
    "sort_time": "1773570043001397",
    "showTime": "2026-03-15 18:20:43",
    "time": "2026-03-15 18:20:43",
    "publish_time": "2026-03-15 18:20:43",
    "raw_data": {
      "code": "202603153672401397",
      "image": [],
      "pinglun_Num": 4,
      "realSort": "1773570043001397",
      "share": 15,
      "showTime": "2026-03-15 18:20:43",
      "stockList": [
        "0.161123"
      ],
      "summary": "【近20家A股上市公司本周披露并购重组最新公告 东吴证券拟购买东海证券83.77%股份股票明起复牌】据不完全统计，截至发稿，本周（3月9日-3月15日）包括京投发展、圣湘生物、*ST步森、金富科技、顶固集创、仟源医药、经纬辉开、亨通股份、优利德、锴威特、东吴证券、恒天海龙、方邦股份、通威股份、中洲控股、长龄液压、*ST清研、新劲刚、珂玛科技在内的19家A股上市公司披露并购重组进展最新公告。其中，东吴证券拟购买东海证券83.77%股份，股票将于3月16日复牌。",
      "title": "近20家A股上市公司本周披露并购重组最新公告 东吴证券拟购买东海证券83.77%股份股票明起复牌",
      "titleColor": 3
    },
    "source": "东方财富快讯",
    "url": "https://kuaixun.eastmoney.com/news/202603153672401397.html",
    "category": "股市",
    "importance": 6,
    "sentiment": "neutral",
    "related_stocks": [
      "0.161123"
    ],
    "has_stock_mention": true,
    "comment_count": 4,
    "share_count": 15,
    "tags": {
      "industries": [
        {
          "id": "I020102",
          "name": "证券",
          "level1": "金融业",
          "level2": "货币金融服务",
          "matched_keyword": "证券"
        },
        {
          "id": "I020202",
          "name": "投资银行",
          "level1": "金融业",
          "level2": "资本市场服务",
          "matched_keyword": "并购"
        }
      ],
      "concepts": [
        {
          "id": "C401",
          "name": "券商",
          "matched_keyword": "证券"
        },
        {
          "id": "C814",
          "name": "ST板块",
          "matched_keyword": "*ST"
        }
      ],
      "industry_ids": [
        "I020102",
        "I020202"
      ],
      "concept_ids": [
        "C401",
        "C814"
      ]
    }
  },
  {
    "id": "8c15e6a47a6795ad",
    "code": "202603153672401244",
    "title": "伊拉克石油部：准备通过杰伊汉输油管道恢复每日不超过30万桶的石油出口",
    "summary": "伊拉克石油部发表声明称，准备通过杰伊汉输油管道恢复每日不超过30万桶的石油出口。",
    "content": "伊拉克石油部发表声明称，准备通过杰伊汉输油管道恢复每日不超过30万桶的石油出口。",
    "full_content": "伊拉克石油部发表声明称，准备通过杰伊汉输油管道恢复每日不超过30万桶的石油出口。",
    "sort_time": "1773569946001244",
    "showTime": "2026-03-15 18:19:06",
    "time": "2026-03-15 18:19:06",
    "publish_time": "2026-03-15 18:19:06",
    "raw_data": {
      "code": "202603153672401244",
      "image": [],
      "pinglun_Num": 18,
      "realSort": "1773569946001244",
      "share": 3,
      "showTime": "2026-03-15 18:19:06",
      "stockList": [
        "90.BK0464"
      ],
      "summary": "伊拉克石油部发表声明称，准备通过杰伊汉输油管道恢复每日不超过30万桶的石油出口。",
      "title": "伊拉克石油部：准备通过杰伊汉输油管道恢复每日不超过30万桶的石油出口",
      "titleColor": 0
    },
    "source": "东方财富快讯",
    "url": "https://kuaixun.eastmoney.com/news/202603153672401244.html",
    "category": "其他",
    "importance": 6,
    "sentiment": "neutral",
    "related_stocks": [
      "90.BK0464"
    ],
    "has_stock_mention": true,
    "comment_count": 18,
    "share_count": 3,
    "tags": {
      "industries": [],
      "concepts": [
        {
          "id": "C506",
          "name": "石油",
          "matched_keyword": "石油"
        }
      ],
      "industry_ids": [],
      "concept_ids": [
        "C506"
      ]
    }
  },
  {
    "id": "020669a724fd4b4b",
    "code": "202603153672400817",
    "title": "巴林铝业：已采取行动以确保业务持续进行",
    "summary": "巴林铝业表示，鉴于当前影响霍尔木兹海峡的供应和运输中断情况，已采取行动以确保业务持续进行。",
    "content": "巴林铝业表示，鉴于当前影响霍尔木兹海峡的供应和运输中断情况，已采取行动以确保业务持续进行。",
    "full_content": "巴林铝业表示，鉴于当前影响霍尔木兹海峡的供应和运输中断情况，已采取行动以确保业务持续进行。",
    "sort_time": "1773569687000817",
    "showTime": "2026-03-15 18:14:47",
    "time": "2026-03-15 18:14:47",
    "publish_time": "2026-03-15 18:14:47",
    "raw_data": {
      "code": "202603153672400817",
      "image": [],
      "pinglun_Num": 3,
      "realSort": "1773569687000817",
      "share": 5,
      "showTime": "2026-03-15 18:14:47",
      "stockList": [],
      "summary": "巴林铝业表示，鉴于当前影响霍尔木兹海峡的供应和运输中断情况，已采取行动以确保业务持续进行。",
      "title": "巴林铝业：已采取行动以确保业务持续进行",
      "titleColor": 0
    },
    "source": "东方财富快讯",
    "url": "https://kuaixun.eastmoney.com/news/202603153672400817.html",
    "category": "期货",
    "importance": 5,
    "sentiment": "neutral",
    "related_stocks": [],
    "has_stock_mention": false,
    "comment_count": 3,
    "share_count": 5,
    "tags": {
      "industries": [],
      "concepts": [
        {
          "id": "C501",
          "name": "有色金属",
          "matched_keyword": "铝"
        }
      ],
      "industry_ids": [],
      "concept_ids": [
        "C501"
      ]
    }
  },
  {
    "id": "4a254e2b1e42782e",
    "code": "202603153672400772",
    "title": "鱼泡直聘被工信部点名通报",
    "summary": "【鱼泡直聘被工信部点名通报】今年“3·15”前夕，工业和信息化部发布了一则关于侵害用户权益行为的APP（SDK）通报，鱼泡直聘被点名直指“欺骗误导用户提供个人信息”。",
    "content": "【鱼泡直聘被工信部点名通报】今年“3·15”前夕，工业和信息化部发布了一则关于侵害用户权益行为的APP（SDK）通报，鱼泡直聘被点名直指“欺骗误导用户提供个人信息”。",
    "full_content": "【鱼泡直聘被工信部点名通报】今年“3·15”前夕，工业和信息化部发布了一则关于侵害用户权益行为的APP（SDK）通报，鱼泡直聘被点名直指“欺骗误导用户提供个人信息”。",
    "sort_time": "1773569508000772",
    "showTime": "2026-03-15 18:11:48",
    "time": "2026-03-15 18:11:48",
    "publish_time": "2026-03-15 18:11:48",
    "raw_data": {
      "code": "202603153672400772",
      "image": [],
      "pinglun_Num": 2,
      "realSort": "1773569508000772",
      "share": 7,
      "showTime": "2026-03-15 18:11:48",
      "stockList": [],
      "summary": "【鱼泡直聘被工信部点名通报】今年“3·15”前夕，工业和信息化部发布了一则关于侵害用户权益行为的APP（SDK）通报，鱼泡直聘被点名直指“欺骗误导用户提供个人信息”。",
      "title": "鱼泡直聘被工信部点名通报",
      "titleColor": 0
    },
    "source": "东方财富快讯",
    "url": "https://kuaixun.eastmoney.com/news/202603153672400772.html",
    "category": "其他",
    "importance": 5,
    "sentiment": "neutral",
    "related_stocks": [],
    "has_stock_mention": false,
    "comment_count": 2,
    "share_count": 7,
    "tags": {
      "industries": [],
      "concepts": [],
      "industry_ids": [],
      "concept_ids": []
    }
  },
  {
    "id": "8c78b8d7cd05219d",
    "code": "202603153672400677",
    "title": "伊朗外长同法国外长通电话",
    "summary": "【伊朗外长同法国外长通电话】当地时间3月14日晚，伊朗外长阿拉格齐同法国外长巴罗通电话。双方就当前美以对伊军事行动及地区局势交换意见。",
    "content": "【伊朗外长同法国外长通电话】当地时间3月14日晚，伊朗外长阿拉格齐同法国外长巴罗通电话。双方就当前美以对伊军事行动及地区局势交换意见。",
    "full_content": "【伊朗外长同法国外长通电话】当地时间3月14日晚，伊朗外长阿拉格齐同法国外长巴罗通电话。双方就当前美以对伊军事行动及地区局势交换意见。",
    "sort_time": "1773569067000677",
    "showTime": "2026-03-15 18:04:27",
    "time": "2026-03-15 18:04:27",
    "publish_time": "2026-03-15 18:04:27",
    "raw_data": {
      "code": "202603153672400677",
      "image": [],
      "pinglun_Num": 9,
      "realSort": "1773569067000677",
      "share": 4,
      "showTime": "2026-03-15 18:04:27",
      "stockList": [],
      "summary": "【伊朗外长同法国外长通电话】当地时间3月14日晚，伊朗外长阿拉格齐同法国外长巴罗通电话。双方就当前美以对伊军事行动及地区局势交换意见。",
      "title": "伊朗外长同法国外长通电话",
      "titleColor": 0
    },
    "source": "东方财富快讯",
    "url": "https://kuaixun.eastmoney.com/news/202603153672400677.html",
    "category": "其他",
    "importance": 5,
    "sentiment": "neutral",
    "related_stocks": [],
    "has_stock_mention": false,
    "comment_count": 9,
    "share_count": 4,
    "tags": {
      "industries": [],
      "concepts": [],
      "industry_ids": [],
      "concept_ids": []
    }
  },
  {
    "id": "5971b9bbbe05e825",
    "code": "202603153672400357",
    "title": "国务院安委办对近期4起典型较大事故查处挂牌督办",
    "summary": "【国务院安委办对近期4起典型较大事故查处挂牌督办】3月15日，国务院安委会办公室决定对上述4起事故查处挂牌督办，要求相关地方按照“四不放过”的原则提级调查，依法依规严肃追责问责。并印发关于近期典型较大事故情况的紧急通报，要求举一反三深刻汲取事故教训，坚决防范遏制重特大事故，有效防止重大涉险事故和较大事故反弹，确保全国安全形势持续稳定。",
    "content": "【国务院安委办对近期4起典型较大事故查处挂牌督办】3月15日，国务院安委会办公室决定对上述4起事故查处挂牌督办，要求相关地方按照“四不放过”的原则提级调查，依法依规严肃追责问责。并印发关于近期典型较大事故情况的紧急通报，要求举一反三深刻汲取事故教训，坚决防范遏制重特大事故，有效防止重大涉险事故和较大事故反弹，确保全国安全形势持续稳定。",
    "full_content": "【国务院安委办对近期4起典型较大事故查处挂牌督办】3月15日，国务院安委会办公室决定对上述4起事故查处挂牌督办，要求相关地方按照“四不放过”的原则提级调查，依法依规严肃追责问责。并印发关于近期典型较大事故情况的紧急通报，要求举一反三深刻汲取事故教训，坚决防范遏制重特大事故，有效防止重大涉险事故和较大事故反弹，确保全国安全形势持续稳定。",
    "sort_time": "1773568923000357",
    "showTime": "2026-03-15 18:02:03",
    "time": "2026-03-15 18:02:03",
    "publish_time": "2026-03-15 18:02:03",
    "raw_data": {
      "code": "202603153672400357",
      "image": [],
      "pinglun_Num": 0,
      "realSort": "1773568923000357",
      "share": 4,
      "showTime": "2026-03-15 18:02:03",
      "stockList": [],
      "summary": "【国务院安委办对近期4起典型较大事故查处挂牌督办】3月15日，国务院安委会办公室决定对上述4起事故查处挂牌督办，要求相关地方按照“四不放过”的原则提级调查，依法依规严肃追责问责。并印发关于近期典型较大事故情况的紧急通报，要求举一反三深刻汲取事故教训，坚决防范遏制重特大事故，有效防止重大涉险事故和较大事故反弹，确保全国安全形势持续稳定。",
      "title": "国务院安委办对近期4起典型较大事故查处挂牌督办",
      "titleColor": 0
    },
    "source": "东方财富快讯",
    "url": "https://kuaixun.eastmoney.com/news/202603153672400357.html",
    "category": "其他",
    "importance": 5,
    "sentiment": "neutral",
    "related_stocks": [],
    "has_stock_mention": false,
    "comment_count": 0,
    "share_count": 4,
    "tags": {
      "industries": [],
      "concepts": [],
      "industry_ids": [],
      "concept_ids": []
    }
  },
  {
    "id": "be896b6ba9c32711",
    "code": "202603153672400151",
    "title": "泽连斯基称俄军本周动用上千架无人机和炸弹发动袭击",
    "summary": "【泽连斯基称俄军本周动用上千架无人机和炸弹发动袭击】当地时间15日，乌克兰总统泽连斯基在社交媒体发表声明称，本周内，俄罗斯动用1770架攻击型无人机、超过1530枚制导航空炸弹以及86枚导弹对乌克兰发动袭击，其中弹道导弹数量超过20枚。",
    "content": "【泽连斯基称俄军本周动用上千架无人机和炸弹发动袭击】当地时间15日，乌克兰总统泽连斯基在社交媒体发表声明称，本周内，俄罗斯动用1770架攻击型无人机、超过1530枚制导航空炸弹以及86枚导弹对乌克兰发动袭击，其中弹道导弹数量超过20枚。",
    "full_content": "【泽连斯基称俄军本周动用上千架无人机和炸弹发动袭击】当地时间15日，乌克兰总统泽连斯基在社交媒体发表声明称，本周内，俄罗斯动用1770架攻击型无人机、超过1530枚制导航空炸弹以及86枚导弹对乌克兰发动袭击，其中弹道导弹数量超过20枚。",
    "sort_time": "1773568448000151",
    "showTime": "2026-03-15 17:54:08",
    "time": "2026-03-15 17:54:08",
    "publish_time": "2026-03-15 17:54:08",
    "raw_data": {
      "code": "202603153672400151",
      "image": [],
      "pinglun_Num": 3,
      "realSort": "1773568448000151",
      "share": 4,
      "showTime": "2026-03-15 17:54:08",
      "stockList": [
        "90.BK0704"
      ],
      "summary": "【泽连斯基称俄军本周动用上千架无人机和炸弹发动袭击】当地时间15日，乌克兰总统泽连斯基在社交媒体发表声明称，本周内，俄罗斯动用1770架攻击型无人机、超过1530枚制导航空炸弹以及86枚导弹对乌克兰发动袭击，其中弹道导弹数量超过20枚。",
      "title": "泽连斯基称俄军本周动用上千架无人机和炸弹发动袭击",
      "titleColor": 0
    },
    "source": "东方财富快讯",
    "url": "https://kuaixun.eastmoney.com/news/202603153672400151.html",
    "category": "其他",
    "importance": 6,
    "sentiment": "neutral",
    "related_stocks": [
      "90.BK0704"
    ],
    "has_stock_mention": true,
    "comment_count": 3,
    "share_count": 4,
    "tags": {
      "industries": [],
      "concepts": [
        {
          "id": "C201",
          "name": "军工",
          "matched_keyword": "航空"
        },
        {
          "id": "C205",
          "name": "低空经济",
          "matched_keyword": "无人机"
        }
      ],
      "industry_ids": [],
      "concept_ids": [
        "C201",
        "C205"
      ]
    }
  },
  {
    "id": "93bdddd377f7731c",
    "code": "202603153672399624",
    "title": "英国3月16日电力价格确定为每兆瓦时73.00英镑",
    "summary": "英国3月16日电力价格确定为每兆瓦时73.00英镑。",
    "content": "英国3月16日电力价格确定为每兆瓦时73.00英镑。",
    "full_content": "英国3月16日电力价格确定为每兆瓦时73.00英镑。",
    "sort_time": "1773567644099624",
    "showTime": "2026-03-15 17:40:44",
    "time": "2026-03-15 17:40:44",
    "publish_time": "2026-03-15 17:40:44",
    "raw_data": {
      "code": "202603153672399624",
      "image": [],
      "pinglun_Num": 40,
      "realSort": "1773567644099624",
      "share": 5,
      "showTime": "2026-03-15 17:40:44",
      "stockList": [
        "90.BK0428",
        "201.HK49"
      ],
      "summary": "英国3月16日电力价格确定为每兆瓦时73.00英镑。",
      "title": "英国3月16日电力价格确定为每兆瓦时73.00英镑",
      "titleColor": 0
    },
    "source": "东方财富快讯",
    "url": "https://kuaixun.eastmoney.com/news/202603153672399624.html",
    "category": "其他",
    "importance": 6,
    "sentiment": "neutral",
    "related_stocks": [
      "90.BK0428",
      "201.HK49"
    ],
    "has_stock_mention": true,
    "comment_count": 40,
    "share_count": 5,
    "tags": {
      "industries": [],
      "concepts": [],
      "industry_ids": [],
      "concept_ids": []
    }
  },
  {
    "id": "523ce8268820381d",
    "code": "202603153672399139",
    "title": "今年以来消费品以旧换新带动销售额超3000亿元",
    "summary": "【今年以来消费品以旧换新带动销售额超3000亿元】记者从商务部了解到，今年以来，消费品以旧换新政策扎实有序推进，目前已带动销售额超3000亿元。",
    "content": "【今年以来消费品以旧换新带动销售额超3000亿元】记者从商务部了解到，今年以来，消费品以旧换新政策扎实有序推进，目前已带动销售额超3000亿元。",
    "full_content": "【今年以来消费品以旧换新带动销售额超3000亿元】记者从商务部了解到，今年以来，消费品以旧换新政策扎实有序推进，目前已带动销售额超3000亿元。",
    "sort_time": "1773567216099139",
    "showTime": "2026-03-15 17:33:36",
    "time": "2026-03-15 17:33:36",
    "publish_time": "2026-03-15 17:33:36",
    "raw_data": {
      "code": "202603153672399139",
      "image": [],
      "pinglun_Num": 9,
      "realSort": "1773567216099139",
      "share": 0,
      "showTime": "2026-03-15 17:33:36",
      "stockList": [],
      "summary": "【今年以来消费品以旧换新带动销售额超3000亿元】记者从商务部了解到，今年以来，消费品以旧换新政策扎实有序推进，目前已带动销售额超3000亿元。",
      "title": "今年以来消费品以旧换新带动销售额超3000亿元",
      "titleColor": 0
    },
    "source": "东方财富快讯",
    "url": "https://kuaixun.eastmoney.com/news/202603153672399139.html",
    "category": "政策",
    "importance": 5,
    "sentiment": "neutral",
    "related_stocks": [],
    "has_stock_mention": false,
    "comment_count": 9,
    "share_count": 0,
    "tags": {
      "industries": [],
      "concepts": [],
      "industry_ids": [],
      "concept_ids": []
    }
  },
  {
    "id": "99346a1408d0b199",
    "code": "202603153672398189",
    "title": "美以袭击已致伊朗至少202名儿童死亡",
    "summary": "【美以袭击已致伊朗至少202名儿童死亡】伊朗卫生部当地时间15日表示，美国和以色列对伊朗的袭击已造成至少202名儿童和223名妇女死亡，其中包括3名孕妇，遇难儿童中有12名年龄在5岁以下。",
    "content": "【美以袭击已致伊朗至少202名儿童死亡】伊朗卫生部当地时间15日表示，美国和以色列对伊朗的袭击已造成至少202名儿童和223名妇女死亡，其中包括3名孕妇，遇难儿童中有12名年龄在5岁以下。",
    "full_content": "【美以袭击已致伊朗至少202名儿童死亡】伊朗卫生部当地时间15日表示，美国和以色列对伊朗的袭击已造成至少202名儿童和223名妇女死亡，其中包括3名孕妇，遇难儿童中有12名年龄在5岁以下。",
    "sort_time": "1773566589098189",
    "showTime": "2026-03-15 17:23:09",
    "time": "2026-03-15 17:23:09",
    "publish_time": "2026-03-15 17:23:09",
    "raw_data": {
      "code": "202603153672398189",
      "image": [],
      "pinglun_Num": 14,
      "realSort": "1773566589098189",
      "share": 4,
      "showTime": "2026-03-15 17:23:09",
      "stockList": [],
      "summary": "【美以袭击已致伊朗至少202名儿童死亡】伊朗卫生部当地时间15日表示，美国和以色列对伊朗的袭击已造成至少202名儿童和223名妇女死亡，其中包括3名孕妇，遇难儿童中有12名年龄在5岁以下。",
      "title": "美以袭击已致伊朗至少202名儿童死亡",
      "titleColor": 0
    },
    "source": "东方财富快讯",
    "url": "https://kuaixun.eastmoney.com/news/202603153672398189.html",
    "category": "其他",
    "importance": 5,
    "sentiment": "neutral",
    "related_stocks": [],
    "has_stock_mention": false,
    "comment_count": 14,
    "share_count": 4,
    "tags": {
      "industries": [],
      "concepts": [],
      "industry_ids": [],
      "concept_ids": []
    }
  },
  {
    "id": "3c19aab4aebe22fd",
    "code": "202603153672397020",
    "title": "印尼总统要求煤炭和棕榈油优先供应国内需求",
    "summary": "【印尼总统要求煤炭和棕榈油优先供应国内需求】印度尼西亚总统普拉博沃·苏比延多3月13日表示，印尼煤炭、毛棕榈油及其衍生品生产企业在满足国内需求之前，不得出口相关产品，以确保国家能源和重要商品供应安全。",
    "content": "【印尼总统要求煤炭和棕榈油优先供应国内需求】印度尼西亚总统普拉博沃·苏比延多3月13日表示，印尼煤炭、毛棕榈油及其衍生品生产企业在满足国内需求之前，不得出口相关产品，以确保国家能源和重要商品供应安全。",
    "full_content": "【印尼总统要求煤炭和棕榈油优先供应国内需求】印度尼西亚总统普拉博沃·苏比延多3月13日表示，印尼煤炭、毛棕榈油及其衍生品生产企业在满足国内需求之前，不得出口相关产品，以确保国家能源和重要商品供应安全。",
    "sort_time": "1773565642097020",
    "showTime": "2026-03-15 17:07:22",
    "time": "2026-03-15 17:07:22",
    "publish_time": "2026-03-15 17:07:22",
    "raw_data": {
      "code": "202603153672397020",
      "image": [],
      "pinglun_Num": 26,
      "realSort": "1773565642097020",
      "share": 43,
      "showTime": "2026-03-15 17:07:22",
      "stockList": [
        "90.BK0437",
        "0.161032"
      ],
      "summary": "【印尼总统要求煤炭和棕榈油优先供应国内需求】印度尼西亚总统普拉博沃·苏比延多3月13日表示，印尼煤炭、毛棕榈油及其衍生品生产企业在满足国内需求之前，不得出口相关产品，以确保国家能源和重要商品供应安全。",
      "title": "印尼总统要求煤炭和棕榈油优先供应国内需求",
      "titleColor": 0
    },
    "source": "东方财富快讯",
    "url": "https://kuaixun.eastmoney.com/news/202603153672397020.html",
    "category": "其他",
    "importance": 6,
    "sentiment": "neutral",
    "related_stocks": [
      "90.BK0437",
      "0.161032"
    ],
    "has_stock_mention": true,
    "comment_count": 26,
    "share_count": 43,
    "tags": {
      "industries": [],
      "concepts": [
        {
          "id": "C505",
          "name": "煤炭",
          "matched_keyword": "煤炭"
        }
      ],
      "industry_ids": [],
      "concept_ids": [
        "C505"
      ]
    }
  }
]